Workbook
Name CADDRESS1CUSTOMERMAIN: #REF!
Name CCOUHEADCUSTOMERMAIN: #REF!
Name CCOUNTRYCUSTOMERMAIN: #REF!
Name CCUSTYPECUSTOMERMAIN: #REF!
Name CIDCUSTOMERMAIN: #REF!
Name CLOCALITYCUSTOMERMAIN: #REF!
Name CNAME1CUSTOMERMAIN: #REF!
Name CVATCATCUSTOMERMAIN: #REF!
Name CVATNOCUSTOMERMAIN: #REF!
Name CVATREFCUSTOMERMAIN: #REF!
Name CZIPCODECUSTOMERMAIN: #REF!

Sheet 2) BOB compta (completer-forcer
A1: Journal | B1: Annee | C1: Mois | D1: Date facture | E1: Echeance | F1: Piece | G1: Tiers | H1: Compte | I1: Communication | J1: Remarque | K1: Mnt.TVAC | L1: TVA | M1: Taux | N1: Mnt.HTVA | O1: Mnt.TVA | P1: Devise | Q1: Cours | R1: NOM | S1: Adresse | T1: Code Postal | U1: Localite | V1: Assujetti | W1: Numéro | X1: Email | Y1: Pdf | Z1: PERSONNEL | AA1: RCP_PERDEB | AB1: RCP_PERFIN | AC1: CLIENT
A2: =IF('1) Import fichier Remi (coller)'!D2="","",'1) Import fichier Remi (coller)'!D2) -> NCV | B2: =IF(A2="","",YEAR('1) Import fichier Remi (coller)'!F2)) -> 2026 | C2: =IF(A2="","",MONTH('1) Import fichier Remi (coller)'!F2)) -> 9 | D2: =IF(A2="","",'1) Import fichier Remi (coller)'!F2) -> 46281 | E2: =IF(A2="","",'1) Import fichier Remi (coller)'!G2) -> 46281 | F2: =IF(A2="","",'1) Import fichier Remi (coller)'!E2) -> 12260077 | G2: JPSFITEST | H2: =IF(A2="","",IF(ISERROR(VLOOKUP('1) Import fichier Remi (coller)'!K2&" - "&'1) Import fichier Remi (coller)'!L2,'Spécifique comptes'!$A:$G,1,FALSE))=TRUE,'1) Import fichier Remi (coller)'!V2,VLOOKUP('1) Import fichier Remi (coller)'!K2&" - "&'1) Import fichier Remi (coller)'!L2,'Spécifique comptes'!$A:$G,IF(LEFT('2) BOB compta (completer-forcer'!F2,2)="11",4,IF(LEFT('2) BOB compta (completer-forcer'!F2,2)="12",5,IF(LEFT('2) BOB compta (completer-forcer'!F2,2)="13",6,IF(LEFT('2) BOB compta (completer-forcer'!F2,2)="15",7,"Erreur Compte")))),FALSE))) -> 705099999 | I2: =IF(A2="","",IF(H2="70100000",'1) Import fichier Remi (coller)'!J2,'1) Import fichier Remi (coller)'!U2)) -> +++003/8260/07776+++ | J2: =IF(A2="","",'1) Import fichier Remi (coller)'!U2) -> +++003/8260/07776+++ | K2: =IF(A2="","",SUMIFS(N:N,A:A,A2,F:F,F2)+SUMIFS(O:O,A:A,A2,F:F,F2)) -> 28.74 | L2: =IF(A2="","",IF(LEFT(T2,1)="B","V","PRT")) -> V | M2: =IF(A2="","",'1) Import fichier Remi (coller)'!S2) -> 21 | N2: =IF($A2="","",IF(OR($A2="NCV",$A2="NC15"),-'1) Import fichier Remi (coller)'!R2,'1) Import fichier Remi (coller)'!R2)) -> 23.75 | O2: =IF($A2="","",IF(OR($A2="NCV",$A2="NC15"),-'1) Import fichier Remi (coller)'!T2,'1) Import fichier Remi (coller)'!T2)) -> 4.99 | R2: =IF($A2="","",IF(ISERROR(VLOOKUP(LEFT('1) Import fichier Remi (coller)'!$A2,9),'Concordance client liv et fact'!$A:$H,8,FALSE))=TRUE,VLOOKUP(LEFT('1) Import fichier Remi (coller)'!$A2,9)+0,'Clients R2'!$A:$CY,2,FALSE),VLOOKUP(VLOOKUP(LEFT('1) Import fichier Remi (coller)'!$A2,9),'Concordance client liv et fact'!$A:$H,7,FALSE)+0,'Clients R2'!$A:$CY,2,FALSE))) -> JPS FINANCIAL SRL | S2: =IF($A2="","",PROPER(IF(ISERROR(VLOOKUP(LEFT('1) Import fichier Remi (coller)'!$A2,9),'Concordance client liv et fact'!$A:$H,8,FALSE))=TRUE,VLOOKUP(LEFT('1) Import fichier Remi (coller)'!$A2,9)+0,'Clients R2'!$A:$CY,27,FALSE),VLOOKUP(VLOOKUP(LEFT('1) Import fichier Remi (coller)'!$A2,9),'Concordance client liv et fact'!$A:$H,7,FALSE)+0,'Clients R2'!$A:$CY,27,FALSE)))) -> Rue De Mont 213 | T2: =IF($A2="","",LEFT(UPPER(IF(ISERROR(VLOOKUP(LEFT('1) Import fichier Remi (coller)'!$A2,9),'Concordance client liv et fact'!$A:$H,8,FALSE))=TRUE,VLOOKUP(LEFT('1) Import fichier Remi (coller)'!$A2,9)+0,'Clients R2'!$A:$CY,28,FALSE),VLOOKUP(VLOOKUP(LEFT('1) Import fichier Remi (coller)'!$A2,9),'Concordance client liv et fact'!$A:$H,7,FALSE)+0,'Clients R2'!$A:$CY,28,FALSE))),2)&UPPER(IF(ISERROR(VLOOKUP(LEFT('1) Import fichier Remi (coller)'!$A2,9),'Concordance client liv et fact'!$A:$H,8,FALSE))=TRUE,VLOOKUP(LEFT('1) Import fichier Remi (coller)'!$A2,9)+0,'Clients R2'!$A:$CY,29,FALSE),VLOOKUP(VLOOKUP(LEFT('1) Import fichier Remi (coller)'!$A2,9),'Concordance client liv et fact'!$A:$H,7,FALSE)+0,'Clients R2'!$A:$CY,29,FALSE)))) -> B 4820 | U2: =IF($A2="","",PROPER(IF(ISERROR(VLOOKUP(LEFT('1) Import fichier Remi (coller)'!$A2,9),'Concordance client liv et fact'!$A:$H,8,FALSE))=TRUE,VLOOKUP(LEFT('1) Import fichier Remi (coller)'!$A2,9)+0,'Clients R2'!$A:$CY,30,FALSE),VLOOKUP(VLOOKUP(LEFT('1) Import fichier Remi (coller)'!$A2,9),'Concordance client liv et fact'!$A:$H,7,FALSE)+0,'Clients R2'!$A:$CY,30,FALSE)))) -> Dison | V2: =IF($A2="","",LEFT(UPPER(IF(ISERROR(VLOOKUP(LEFT('1) Import fichier Remi (coller)'!$A2,9),'Concordance client liv et fact'!$A:$H,8,FALSE))=TRUE,IF(VLOOKUP(LEFT('1) Import fichier Remi (coller)'!$A2,9)+0,'Clients R2'!$A:$CY,22,FALSE)=4,"NA",VLOOKUP(LEFT('1) Import fichier Remi (coller)'!$A2,9)+0,'Clients R2'!$A:$CY,3,FALSE)),IF(VLOOKUP(VLOOKUP(LEFT('1) Import fichier Remi (coller)'!$A2,9),'Concordance client liv et fact'!$A:$H,7,FALSE)+0,'Clients R2'!$A:$CY,22,FALSE)=4,"NA",VLOOKUP(VLOOKUP(LEFT('1) Import fichier Remi (coller)'!$A2,9),'Concordance client liv et fact'!$A:$H,7,FALSE)+0,'Clients R2'!$A:$CY,3,FALSE)))),2)) -> BE | X2: =IF($A2="","",IF(ISERROR(VLOOKUP(LEFT('1) Import fichier Remi (coller)'!$A2,9),'Concordance client liv et fact'!$A:$H,8,FALSE))=TRUE,VLOOKUP(LEFT('1) Import fichier Remi (coller)'!$A2,9)+0,'Clients R2'!$A:$CY,102,FALSE),VLOOKUP(VLOOKUP(LEFT('1) Import fichier Remi (coller)'!$A2,9),'Concordance client liv et fact'!$A:$H,7,FALSE)+0,'Clients R2'!$A:$CY,102,FALSE))) -> jpierresch@voo.be | Y2: CF11261601.PDF | Z2: =IF(A2="","",IF(OR(H2="705099999",H2="705001002"),VLOOKUP('1) Import fichier Remi (coller)'!J2,'Analytique personnel'!$A:$B,2,FALSE),"")) -> LLHOMME | AA2: =IF($A2="VE11","",IF(LEFT($H2,4)="7050","",IF('1) Import fichier Remi (coller)'!M2="","",'1) Import fichier Remi (coller)'!M2))) | AB2: =IF($A2="VE11","",IF(LEFT($H2,4)="7050","",IF('1) Import fichier Remi (coller)'!N2="","",'1) Import fichier Remi (coller)'!N2))) | AC2: =IF(A2="","",VLOOKUP(LEFT('1) Import fichier Remi (coller)'!A2,9)+0,'Concordance Client R2 BOB'!$B:$C,2,FALSE)) -> JPSFINANCI
A3: =IF('1) Import fichier Remi (coller)'!D3="","",'1) Import fichier Remi (coller)'!D3) -> NCV | B3: =IF(A3="","",YEAR('1) Import fichier Remi (coller)'!F3)) -> 2026 | C3: =IF(A3="","",MONTH('1) Import fichier Remi (coller)'!F3)) -> 9 | D3: =IF(A3="","",'1) Import fichier Remi (coller)'!F3) -> 46281 | E3: =IF(A3="","",'1) Import fichier Remi (coller)'!G3) -> 46281 | F3: =IF(A3="","",'1) Import fichier Remi (coller)'!E3) -> 12260078 | G3: =IF(A3="","",IF(ISERROR(VLOOKUP(LEFT('1) Import fichier Remi (coller)'!A3,9),'Concordance client liv et fact'!$A:$H,8,FALSE))=TRUE,'1) Import fichier Remi (coller)'!B3,VLOOKUP(LEFT('1) Import fichier Remi (coller)'!A3,9),'Concordance client liv et fact'!$A:$H,8,FALSE))) -> IVZINC | H3: =IF(A3="","",IF(ISERROR(VLOOKUP('1) Import fichier Remi (coller)'!K3&" - "&'1) Import fichier Remi (coller)'!L3,'Spécifique comptes'!$A:$G,1,FALSE))=TRUE,'1) Import fichier Remi (coller)'!V3,VLOOKUP('1) Import fichier Remi (coller)'!K3&" - "&'1) Import fichier Remi (coller)'!L3,'Spécifique comptes'!$A:$G,IF(LEFT('2) BOB compta (completer-forcer'!F3,2)="11",4,IF(LEFT('2) BOB compta (completer-forcer'!F3,2)="12",5,IF(LEFT('2) BOB compta (completer-forcer'!F3,2)="13",6,IF(LEFT('2) BOB compta (completer-forcer'!F3,2)="15",7,"Erreur Compte")))),FALSE))) -> 705099999 | I3: =IF(A3="","",IF(H3="70100000",'1) Import fichier Remi (coller)'!J3,'1) Import fichier Remi (coller)'!U3)) -> +++003/8260/07877+++ | J3: =IF(A3="","",'1) Import fichier Remi (coller)'!U3) -> +++003/8260/07877+++ | K3: =IF(A3="","",SUMIFS(N:N,A:A,A3,F:F,F3)+SUMIFS(O:O,A:A,A3,F:F,F3)) -> 28.74 | L3: =IF(A3="","",IF(LEFT(T3,1)="B","V","PRT")) -> V | M3: =IF(A3="","",'1) Import fichier Remi (coller)'!S3) -> 21 | N3: =IF($A3="","",IF(OR($A3="NCV",$A3="NC15"),-'1) Import fichier Remi (coller)'!R3,'1) Import fichier Remi (coller)'!R3)) -> 23.75 | O3: =IF($A3="","",IF(OR($A3="NCV",$A3="NC15"),-'1) Import fichier Remi (coller)'!T3,'1) Import fichier Remi (coller)'!T3)) -> 4.99 | R3: =IF($A3="","",IF(ISERROR(VLOOKUP(LEFT('1) Import fichier Remi (coller)'!$A3,9),'Concordance client liv et fact'!$A:$H,8,FALSE))=TRUE,VLOOKUP(LEFT('1) Import fichier Remi (coller)'!$A3,9)+0,'Clients R2'!$A:$CY,2,FALSE),VLOOKUP(VLOOKUP(LEFT('1) Import fichier Remi (coller)'!$A3,9),'Concordance client liv et fact'!$A:$H,7,FALSE)+0,'Clients R2'!$A:$CY,2,FALSE))) -> IV ZINC SRL | S3: =IF($A3="","",PROPER(IF(ISERROR(VLOOKUP(LEFT('1) Import fichier Remi (coller)'!$A3,9),'Concordance client liv et fact'!$A:$H,8,FALSE))=TRUE,VLOOKUP(LEFT('1) Import fichier Remi (coller)'!$A3,9)+0,'Clients R2'!$A:$CY,27,FALSE),VLOOKUP(VLOOKUP(LEFT('1) Import fichier Remi (coller)'!$A3,9),'Concordance client liv et fact'!$A:$H,7,FALSE)+0,'Clients R2'!$A:$CY,27,FALSE)))) -> Rue De L'Eperonnerie 21 | T3: =IF($A3="","",LEFT(UPPER(IF(ISERROR(VLOOKUP(LEFT('1) Import fichier Remi (coller)'!$A3,9),'Concordance client liv et fact'!$A:$H,8,FALSE))=TRUE,VLOOKUP(LEFT('1) Import fichier Remi (coller)'!$A3,9)+0,'Clients R2'!$A:$CY,28,FALSE),VLOOKUP(VLOOKUP(LEFT('1) Import fichier Remi (coller)'!$A3,9),'Concordance client liv et fact'!$A:$H,7,FALSE)+0,'Clients R2'!$A:$CY,28,FALSE))),2)&UPPER(IF(ISERROR(VLOOKUP(LEFT('1) Import fichier Remi (coller)'!$A3,9),'Concordance client liv et fact'!$A:$H,8,FALSE))=TRUE,VLOOKUP(LEFT('1) Import fichier Remi (coller)'!$A3,9)+0,'Clients R2'!$A:$CY,29,FALSE),VLOOKUP(VLOOKUP(LEFT('1) Import fichier Remi (coller)'!$A3,9),'Concordance client liv et fact'!$A:$H,7,FALSE)+0,'Clients R2'!$A:$CY,29,FALSE)))) -> B 4081 | U3: =IF($A3="","",PROPER(IF(ISERROR(VLOOKUP(LEFT('1) Import fichier Remi (coller)'!$A3,9),'Concordance client liv et fact'!$A:$H,8,FALSE))=TRUE,VLOOKUP(LEFT('1) Import fichier Remi (coller)'!$A3,9)+0,'Clients R2'!$A:$CY,30,FALSE),VLOOKUP(VLOOKUP(LEFT('1) Import fichier Remi (coller)'!$A3,9),'Concordance client liv et fact'!$A:$H,7,FALSE)+0,'Clients R2'!$A:$CY,30,FALSE)))) -> Milmort | V3: =IF($A3="","",LEFT(UPPER(IF(ISERROR(VLOOKUP(LEFT('1) Import fichier Remi (coller)'!$A3,9),'Concordance client liv et fact'!$A:$H,8,FALSE))=TRUE,IF(VLOOKUP(LEFT('1) Import fichier Remi (coller)'!$A3,9)+0,'Clients R2'!$A:$CY,22,FALSE)=4,"NA",VLOOKUP(LEFT('1) Import fichier Remi (coller)'!$A3,9)+0,'Clients R2'!$A:$CY,3,FALSE)),IF(VLOOKUP(VLOOKUP(LEFT('1) Import fichier Remi (coller)'!$A3,9),'Concordance client liv et fact'!$A:$H,7,FALSE)+0,'Clients R2'!$A:$CY,22,FALSE)=4,"NA",VLOOKUP(VLOOKUP(LEFT('1) Import fichier Remi (coller)'!$A3,9),'Concordance client liv et fact'!$A:$H,7,FALSE)+0,'Clients R2'!$A:$CY,3,FALSE)))),2)) -> BE | X3: =IF($A3="","",IF(ISERROR(VLOOKUP(LEFT('1) Import fichier Remi (coller)'!$A3,9),'Concordance client liv et fact'!$A:$H,8,FALSE))=TRUE,VLOOKUP(LEFT('1) Import fichier Remi (coller)'!$A3,9)+0,'Clients R2'!$A:$CY,102,FALSE),VLOOKUP(VLOOKUP(LEFT('1) Import fichier Remi (coller)'!$A3,9),'Concordance client liv et fact'!$A:$H,7,FALSE)+0,'Clients R2'!$A:$CY,102,FALSE))) -> comptabilite.sabanigroup@gmail.com | Y3: CF11261601.PDF | Z3: =IF(A3="","",IF(OR(H3="705099999",H3="705001002"),VLOOKUP('1) Import fichier Remi (coller)'!J3,'Analytique personnel'!$A:$B,2,FALSE),"")) -> LLHOMME | AA3: =IF($A3="VE11","",IF(LEFT($H3,4)="7050","",IF('1) Import fichier Remi (coller)'!M3="","",'1) Import fichier Remi (coller)'!M3))) | AB3: =IF($A3="VE11","",IF(LEFT($H3,4)="7050","",IF('1) Import fichier Remi (coller)'!N3="","",'1) Import fichier Remi (coller)'!N3))) | AC3: =IF(A3="","",VLOOKUP(LEFT('1) Import fichier Remi (coller)'!A3,9)+0,'Concordance Client R2 BOB'!$B:$C,2,FALSE)) -> IVZINC
A4: =IF('1) Import fichier Remi (coller)'!D4="","",'1) Import fichier Remi (coller)'!D4) -> VE11 | B4: =IF(A4="","",YEAR('1) Import fichier Remi (coller)'!F4)) -> 2026 | C4: =IF(A4="","",MONTH('1) Import fichier Remi (coller)'!F4)) -> 9 | D4: =IF(A4="","",'1) Import fichier Remi (coller)'!F4) -> 46281 | E4: =IF(A4="","",'1) Import fichier Remi (coller)'!G4) -> 46281 | F4: =IF(A4="","",'1) Import fichier Remi (coller)'!E4) -> 11261511 | G4: =IF(A4="","",IF(ISERROR(VLOOKUP(LEFT('1) Import fichier Remi (coller)'!A4,9),'Concordance client liv et fact'!$A:$H,8,FALSE))=TRUE,'1) Import fichier Remi (coller)'!B4,VLOOKUP(LEFT('1) Import fichier Remi (coller)'!A4,9),'Concordance client liv et fact'!$A:$H,8,FALSE))) -> IBS | H4: =IF(A4="","",IF(ISERROR(VLOOKUP('1) Import fichier Remi (coller)'!K4&" - "&'1) Import fichier Remi (coller)'!L4,'Spécifique comptes'!$A:$G,1,FALSE))=TRUE,'1) Import fichier Remi (coller)'!V4,VLOOKUP('1) Import fichier Remi (coller)'!K4&" - "&'1) Import fichier Remi (coller)'!L4,'Spécifique comptes'!$A:$G,IF(LEFT('2) BOB compta (completer-forcer'!F4,2)="11",4,IF(LEFT('2) BOB compta (completer-forcer'!F4,2)="12",5,IF(LEFT('2) BOB compta (completer-forcer'!F4,2)="13",6,IF(LEFT('2) BOB compta (completer-forcer'!F4,2)="15",7,"Erreur Compte")))),FALSE))) -> 705002000 | I4: =IF(A4="","",IF(H4="70100000",'1) Import fichier Remi (coller)'!J4,'1) Import fichier Remi (coller)'!U4)) -> +++003/7261/51128+++ | J4: =IF(A4="","",'1) Import fichier Remi (coller)'!U4) -> +++003/7261/51128+++ | K4: =IF(A4="","",SUMIFS(N:N,A:A,A4,F:F,F4)+SUMIFS(O:O,A:A,A4,F:F,F4)) -> 152.46 | L4: =IF(A4="","",IF(LEFT(T4,1)="B","V","PRT")) -> V | M4: =IF(A4="","",'1) Import fichier Remi (coller)'!S4) -> 21 | N4: =IF($A4="","",IF(OR($A4="NCV",$A4="NC15"),-'1) Import fichier Remi (coller)'!R4,'1) Import fichier Remi (coller)'!R4)) -> 18 | O4: =IF($A4="","",IF(OR($A4="NCV",$A4="NC15"),-'1) Import fichier Remi (coller)'!T4,'1) Import fichier Remi (coller)'!T4)) -> 3.78 | R4: =IF($A4="","",IF(ISERROR(VLOOKUP(LEFT('1) Import fichier Remi (coller)'!$A4,9),'Concordance client liv et fact'!$A:$H,8,FALSE))=TRUE,VLOOKUP(LEFT('1) Import fichier Remi (coller)'!$A4,9)+0,'Clients R2'!$A:$CY,2,FALSE),VLOOKUP(VLOOKUP(LEFT('1) Import fichier Remi (coller)'!$A4,9),'Concordance client liv et fact'!$A:$H,7,FALSE)+0,'Clients R2'!$A:$CY,2,FALSE))) -> IBGRAF BUSINESS SOL. | S4: =IF($A4="","",PROPER(IF(ISERROR(VLOOKUP(LEFT('1) Import fichier Remi (coller)'!$A4,9),'Concordance client liv et fact'!$A:$H,8,FALSE))=TRUE,VLOOKUP(LEFT('1) Import fichier Remi (coller)'!$A4,9)+0,'Clients R2'!$A:$CY,27,FALSE),VLOOKUP(VLOOKUP(LEFT('1) Import fichier Remi (coller)'!$A4,9),'Concordance client liv et fact'!$A:$H,7,FALSE)+0,'Clients R2'!$A:$CY,27,FALSE)))) -> Rue D'Abhooz, 27 | T4: =IF($A4="","",LEFT(UPPER(IF(ISERROR(VLOOKUP(LEFT('1) Import fichier Remi (coller)'!$A4,9),'Concordance client liv et fact'!$A:$H,8,FALSE))=TRUE,VLOOKUP(LEFT('1) Import fichier Remi (coller)'!$A4,9)+0,'Clients R2'!$A:$CY,28,FALSE),VLOOKUP(VLOOKUP(LEFT('1) Import fichier Remi (coller)'!$A4,9),'Concordance client liv et fact'!$A:$H,7,FALSE)+0,'Clients R2'!$A:$CY,28,FALSE))),2)&UPPER(IF(ISERROR(VLOOKUP(LEFT('1) Import fichier Remi (coller)'!$A4,9),'Concordance client liv et fact'!$A:$H,8,FALSE))=TRUE,VLOOKUP(LEFT('1) Import fichier Remi (coller)'!$A4,9)+0,'Clients R2'!$A:$CY,29,FALSE),VLOOKUP(VLOOKUP(LEFT('1) Import fichier Remi (coller)'!$A4,9),'Concordance client liv et fact'!$A:$H,7,FALSE)+0,'Clients R2'!$A:$CY,29,FALSE)))) -> B 4040 | U4: =IF($A4="","",PROPER(IF(ISERROR(VLOOKUP(LEFT('1) Import fichier Remi (coller)'!$A4,9),'Concordance client liv et fact'!$A:$H,8,FALSE))=TRUE,VLOOKUP(LEFT('1) Import fichier Remi (coller)'!$A4,9)+0,'Clients R2'!$A:$CY,30,FALSE),VLOOKUP(VLOOKUP(LEFT('1) Import fichier Remi (coller)'!$A4,9),'Concordance client liv et fact'!$A:$H,7,FALSE)+0,'Clients R2'!$A:$CY,30,FALSE)))) -> Herstal | V4: =IF($A4="","",LEFT(UPPER(IF(ISERROR(VLOOKUP(LEFT('1) Import fichier Remi (coller)'!$A4,9),'Concordance client liv et fact'!$A:$H,8,FALSE))=TRUE,IF(VLOOKUP(LEFT('1) Import fichier Remi (coller)'!$A4,9)+0,'Clients R2'!$A:$CY,22,FALSE)=4,"NA",VLOOKUP(LEFT('1) Import fichier Remi (coller)'!$A4,9)+0,'Clients R2'!$A:$CY,3,FALSE)),IF(VLOOKUP(VLOOKUP(LEFT('1) Import fichier Remi (coller)'!$A4,9),'Concordance client liv et fact'!$A:$H,7,FALSE)+0,'Clients R2'!$A:$CY,22,FALSE)=4,"NA",VLOOKUP(VLOOKUP(LEFT('1) Import fichier Remi (coller)'!$A4,9),'Concordance client liv et fact'!$A:$H,7,FALSE)+0,'Clients R2'!$A:$CY,3,FALSE)))),2)) -> BE | X4: =IF($A4="","",IF(ISERROR(VLOOKUP(LEFT('1) Import fichier Remi (coller)'!$A4,9),'Concordance client liv et fact'!$A:$H,8,FALSE))=TRUE,VLOOKUP(LEFT('1) Import fichier Remi (coller)'!$A4,9)+0,'Clients R2'!$A:$CY,102,FALSE),VLOOKUP(VLOOKUP(LEFT('1) Import fichier Remi (coller)'!$A4,9),'Concordance client liv et fact'!$A:$H,7,FALSE)+0,'Clients R2'!$A:$CY,102,FALSE))) -> compta.ibs@ibgraf.com | Y4: CF11261601.PDF | Z4: BMELIN | AA4: =IF($A4="VE11","",IF(LEFT($H4,4)="7050","",IF('1) Import fichier Remi (coller)'!M4="","",'1) Import fichier Remi (coller)'!M4))) | AB4: =IF($A4="VE11","",IF(LEFT($H4,4)="7050","",IF('1) Import fichier Remi (coller)'!N4="","",'1) Import fichier Remi (coller)'!N4))) | AC4: =IF(A4="","",VLOOKUP(LEFT('1) Import fichier Remi (coller)'!A4,9)+0,'Concordance Client R2 BOB'!$B:$C,2,FALSE)) -> IBS
A5: =IF('1) Import fichier Remi (coller)'!D5="","",'1) Import fichier Remi (coller)'!D5) -> VE11 | B5: =IF(A5="","",YEAR('1) Import fichier Remi (coller)'!F5)) -> 2026 | C5: =IF(A5="","",MONTH('1) Import fichier Remi (coller)'!F5)) -> 9 | D5: =IF(A5="","",'1) Import fichier Remi (coller)'!F5) -> 46281 | E5: =IF(A5="","",'1) Import fichier Remi (coller)'!G5) -> 46281 | F5: =IF(A5="","",'1) Import fichier Remi (coller)'!E5) -> 11261511 | G5: =IF(A5="","",IF(ISERROR(VLOOKUP(LEFT('1) Import fichier Remi (coller)'!A5,9),'Concordance client liv et fact'!$A:$H,8,FALSE))=TRUE,'1) Import fichier Remi (coller)'!B5,VLOOKUP(LEFT('1) Import fichier Remi (coller)'!A5,9),'Concordance client liv et fact'!$A:$H,8,FALSE))) -> IBS | H5: =IF(A5="","",IF(ISERROR(VLOOKUP('1) Import fichier Remi (coller)'!K5&" - "&'1) Import fichier Remi (coller)'!L5,'Spécifique comptes'!$A:$G,1,FALSE))=TRUE,'1) Import fichier Remi (coller)'!V5,VLOOKUP('1) Import fichier Remi (coller)'!K5&" - "&'1) Import fichier Remi (coller)'!L5,'Spécifique comptes'!$A:$G,IF(LEFT('2) BOB compta (completer-forcer'!F5,2)="11",4,IF(LEFT('2) BOB compta (completer-forcer'!F5,2)="12",5,IF(LEFT('2) BOB compta (completer-forcer'!F5,2)="13",6,IF(LEFT('2) BOB compta (completer-forcer'!F5,2)="15",7,"Erreur Compte")))),FALSE))) -> 705002000 | I5: =IF(A5="","",IF(H5="70100000",'1) Import fichier Remi (coller)'!J5,'1) Import fichier Remi (coller)'!U5)) -> +++003/7261/51128+++ | J5: =IF(A5="","",'1) Import fichier Remi (coller)'!U5) -> +++003/7261/51128+++ | K5: =IF(A5="","",SUMIFS(N:N,A:A,A5,F:F,F5)+SUMIFS(O:O,A:A,A5,F:F,F5)) -> 152.46 | L5: =IF(A5="","",IF(LEFT(T5,1)="B","V","PRT")) -> V | M5: =IF(A5="","",'1) Import fichier Remi (coller)'!S5) -> 21 | N5: =IF($A5="","",IF(OR($A5="NCV",$A5="NC15"),-'1) Import fichier Remi (coller)'!R5,'1) Import fichier Remi (coller)'!R5)) -> 72 | O5: =IF($A5="","",IF(OR($A5="NCV",$A5="NC15"),-'1) Import fichier Remi (coller)'!T5,'1) Import fichier Remi (coller)'!T5)) -> 15.12 | R5: =IF($A5="","",IF(ISERROR(VLOOKUP(LEFT('1) Import fichier Remi (coller)'!$A5,9),'Concordance client liv et fact'!$A:$H,8,FALSE))=TRUE,VLOOKUP(LEFT('1) Import fichier Remi (coller)'!$A5,9)+0,'Clients R2'!$A:$CY,2,FALSE),VLOOKUP(VLOOKUP(LEFT('1) Import fichier Remi (coller)'!$A5,9),'Concordance client liv et fact'!$A:$H,7,FALSE)+0,'Clients R2'!$A:$CY,2,FALSE))) -> IBGRAF BUSINESS SOL. | S5: =IF($A5="","",PROPER(IF(ISERROR(VLOOKUP(LEFT('1) Import fichier Remi (coller)'!$A5,9),'Concordance client liv et fact'!$A:$H,8,FALSE))=TRUE,VLOOKUP(LEFT('1) Import fichier Remi (coller)'!$A5,9)+0,'Clients R2'!$A:$CY,27,FALSE),VLOOKUP(VLOOKUP(LEFT('1) Import fichier Remi (coller)'!$A5,9),'Concordance client liv et fact'!$A:$H,7,FALSE)+0,'Clients R2'!$A:$CY,27,FALSE)))) -> Rue D'Abhooz, 27 | T5: =IF($A5="","",LEFT(UPPER(IF(ISERROR(VLOOKUP(LEFT('1) Import fichier Remi (coller)'!$A5,9),'Concordance client liv et fact'!$A:$H,8,FALSE))=TRUE,VLOOKUP(LEFT('1) Import fichier Remi (coller)'!$A5,9)+0,'Clients R2'!$A:$CY,28,FALSE),VLOOKUP(VLOOKUP(LEFT('1) Import fichier Remi (coller)'!$A5,9),'Concordance client liv et fact'!$A:$H,7,FALSE)+0,'Clients R2'!$A:$CY,28,FALSE))),2)&UPPER(IF(ISERROR(VLOOKUP(LEFT('1) Import fichier Remi (coller)'!$A5,9),'Concordance client liv et fact'!$A:$H,8,FALSE))=TRUE,VLOOKUP(LEFT('1) Import fichier Remi (coller)'!$A5,9)+0,'Clients R2'!$A:$CY,29,FALSE),VLOOKUP(VLOOKUP(LEFT('1) Import fichier Remi (coller)'!$A5,9),'Concordance client liv et fact'!$A:$H,7,FALSE)+0,'Clients R2'!$A:$CY,29,FALSE)))) -> B 4040 | U5: =IF($A5="","",PROPER(IF(ISERROR(VLOOKUP(LEFT('1) Import fichier Remi (coller)'!$A5,9),'Concordance client liv et fact'!$A:$H,8,FALSE))=TRUE,VLOOKUP(LEFT('1) Import fichier Remi (coller)'!$A5,9)+0,'Clients R2'!$A:$CY,30,FALSE),VLOOKUP(VLOOKUP(LEFT('1) Import fichier Remi (coller)'!$A5,9),'Concordance client liv et fact'!$A:$H,7,FALSE)+0,'Clients R2'!$A:$CY,30,FALSE)))) -> Herstal | V5: =IF($A5="","",LEFT(UPPER(IF(ISERROR(VLOOKUP(LEFT('1) Import fichier Remi (coller)'!$A5,9),'Concordance client liv et fact'!$A:$H,8,FALSE))=TRUE,IF(VLOOKUP(LEFT('1) Import fichier Remi (coller)'!$A5,9)+0,'Clients R2'!$A:$CY,22,FALSE)=4,"NA",VLOOKUP(LEFT('1) Import fichier Remi (coller)'!$A5,9)+0,'Clients R2'!$A:$CY,3,FALSE)),IF(VLOOKUP(VLOOKUP(LEFT('1) Import fichier Remi (coller)'!$A5,9),'Concordance client liv et fact'!$A:$H,7,FALSE)+0,'Clients R2'!$A:$CY,22,FALSE)=4,"NA",VLOOKUP(VLOOKUP(LEFT('1) Import fichier Remi (coller)'!$A5,9),'Concordance client liv et fact'!$A:$H,7,FALSE)+0,'Clients R2'!$A:$CY,3,FALSE)))),2)) -> BE | X5: =IF($A5="","",IF(ISERROR(VLOOKUP(LEFT('1) Import fichier Remi (coller)'!$A5,9),'Concordance client liv et fact'!$A:$H,8,FALSE))=TRUE,VLOOKUP(LEFT('1) Import fichier Remi (coller)'!$A5,9)+0,'Clients R2'!$A:$CY,102,FALSE),VLOOKUP(VLOOKUP(LEFT('1) Import fichier Remi (coller)'!$A5,9),'Concordance client liv et fact'!$A:$H,7,FALSE)+0,'Clients R2'!$A:$CY,102,FALSE))) -> compta.ibs@ibgraf.com | Y5: CF11261601.PDF | Z5: BMELIN | AA5: =IF($A5="VE11","",IF(LEFT($H5,4)="7050","",IF('1) Import fichier Remi (coller)'!M5="","",'1) Import fichier Remi (coller)'!M5))) | AB5: =IF($A5="VE11","",IF(LEFT($H5,4)="7050","",IF('1) Import fichier Remi (coller)'!N5="","",'1) Import fichier Remi (coller)'!N5))) | AC5: =IF(A5="","",VLOOKUP(LEFT('1) Import fichier Remi (coller)'!A5,9)+0,'Concordance Client R2 BOB'!$B:$C,2,FALSE)) -> IBS
A6: =IF('1) Import fichier Remi (coller)'!D6="","",'1) Import fichier Remi (coller)'!D6) -> VE11 | B6: =IF(A6="","",YEAR('1) Import fichier Remi (coller)'!F6)) -> 2026 | C6: =IF(A6="","",MONTH('1) Import fichier Remi (coller)'!F6)) -> 9 | D6: =IF(A6="","",'1) Import fichier Remi (coller)'!F6) -> 46281 | E6: =IF(A6="","",'1) Import fichier Remi (coller)'!G6) -> 46281 | F6: =IF(A6="","",'1) Import fichier Remi (coller)'!E6) -> 11261511 | G6: =IF(A6="","",IF(ISERROR(VLOOKUP(LEFT('1) Import fichier Remi (coller)'!A6,9),'Concordance client liv et fact'!$A:$H,8,FALSE))=TRUE,'1) Import fichier Remi (coller)'!B6,VLOOKUP(LEFT('1) Import fichier Remi (coller)'!A6,9),'Concordance client liv et fact'!$A:$H,8,FALSE))) -> IBS | H6: =IF(A6="","",IF(ISERROR(VLOOKUP('1) Import fichier Remi (coller)'!K6&" - "&'1) Import fichier Remi (coller)'!L6,'Spécifique comptes'!$A:$G,1,FALSE))=TRUE,'1) Import fichier Remi (coller)'!V6,VLOOKUP('1) Import fichier Remi (coller)'!K6&" - "&'1) Import fichier Remi (coller)'!L6,'Spécifique comptes'!$A:$G,IF(LEFT('2) BOB compta (completer-forcer'!F6,2)="11",4,IF(LEFT('2) BOB compta (completer-forcer'!F6,2)="12",5,IF(LEFT('2) BOB compta (completer-forcer'!F6,2)="13",6,IF(LEFT('2) BOB compta (completer-forcer'!F6,2)="15",7,"Erreur Compte")))),FALSE))) -> 705002000 | I6: =IF(A6="","",IF(H6="70100000",'1) Import fichier Remi (coller)'!J6,'1) Import fichier Remi (coller)'!U6)) -> +++003/7261/51128+++ | J6: =IF(A6="","",'1) Import fichier Remi (coller)'!U6) -> +++003/7261/51128+++ | K6: =IF(A6="","",SUMIFS(N:N,A:A,A6,F:F,F6)+SUMIFS(O:O,A:A,A6,F:F,F6)) -> 152.46 | L6: =IF(A6="","",IF(LEFT(T6,1)="B","V","PRT")) -> V | M6: =IF(A6="","",'1) Import fichier Remi (coller)'!S6) -> 21 | N6: =IF($A6="","",IF(OR($A6="NCV",$A6="NC15"),-'1) Import fichier Remi (coller)'!R6,'1) Import fichier Remi (coller)'!R6)) -> 18 | O6: =IF($A6="","",IF(OR($A6="NCV",$A6="NC15"),-'1) Import fichier Remi (coller)'!T6,'1) Import fichier Remi (coller)'!T6)) -> 3.78 | R6: =IF($A6="","",IF(ISERROR(VLOOKUP(LEFT('1) Import fichier Remi (coller)'!$A6,9),'Concordance client liv et fact'!$A:$H,8,FALSE))=TRUE,VLOOKUP(LEFT('1) Import fichier Remi (coller)'!$A6,9)+0,'Clients R2'!$A:$CY,2,FALSE),VLOOKUP(VLOOKUP(LEFT('1) Import fichier Remi (coller)'!$A6,9),'Concordance client liv et fact'!$A:$H,7,FALSE)+0,'Clients R2'!$A:$CY,2,FALSE))) -> IBGRAF BUSINESS SOL. | S6: =IF($A6="","",PROPER(IF(ISERROR(VLOOKUP(LEFT('1) Import fichier Remi (coller)'!$A6,9),'Concordance client liv et fact'!$A:$H,8,FALSE))=TRUE,VLOOKUP(LEFT('1) Import fichier Remi (coller)'!$A6,9)+0,'Clients R2'!$A:$CY,27,FALSE),VLOOKUP(VLOOKUP(LEFT('1) Import fichier Remi (coller)'!$A6,9),'Concordance client liv et fact'!$A:$H,7,FALSE)+0,'Clients R2'!$A:$CY,27,FALSE)))) -> Rue D'Abhooz, 27 | T6: =IF($A6="","",LEFT(UPPER(IF(ISERROR(VLOOKUP(LEFT('1) Import fichier Remi (coller)'!$A6,9),'Concordance client liv et fact'!$A:$H,8,FALSE))=TRUE,VLOOKUP(LEFT('1) Import fichier Remi (coller)'!$A6,9)+0,'Clients R2'!$A:$CY,28,FALSE),VLOOKUP(VLOOKUP(LEFT('1) Import fichier Remi (coller)'!$A6,9),'Concordance client liv et fact'!$A:$H,7,FALSE)+0,'Clients R2'!$A:$CY,28,FALSE))),2)&UPPER(IF(ISERROR(VLOOKUP(LEFT('1) Import fichier Remi (coller)'!$A6,9),'Concordance client liv et fact'!$A:$H,8,FALSE))=TRUE,VLOOKUP(LEFT('1) Import fichier Remi (coller)'!$A6,9)+0,'Clients R2'!$A:$CY,29,FALSE),VLOOKUP(VLOOKUP(LEFT('1) Import fichier Remi (coller)'!$A6,9),'Concordance client liv et fact'!$A:$H,7,FALSE)+0,'Clients R2'!$A:$CY,29,FALSE)))) -> B 4040 | U6: =IF($A6="","",PROPER(IF(ISERROR(VLOOKUP(LEFT('1) Import fichier Remi (coller)'!$A6,9),'Concordance client liv et fact'!$A:$H,8,FALSE))=TRUE,VLOOKUP(LEFT('1) Import fichier Remi (coller)'!$A6,9)+0,'Clients R2'!$A:$CY,30,FALSE),VLOOKUP(VLOOKUP(LEFT('1) Import fichier Remi (coller)'!$A6,9),'Concordance client liv et fact'!$A:$H,7,FALSE)+0,'Clients R2'!$A:$CY,30,FALSE)))) -> Herstal | V6: =IF($A6="","",LEFT(UPPER(IF(ISERROR(VLOOKUP(LEFT('1) Import fichier Remi (coller)'!$A6,9),'Concordance client liv et fact'!$A:$H,8,FALSE))=TRUE,IF(VLOOKUP(LEFT('1) Import fichier Remi (coller)'!$A6,9)+0,'Clients R2'!$A:$CY,22,FALSE)=4,"NA",VLOOKUP(LEFT('1) Import fichier Remi (coller)'!$A6,9)+0,'Clients R2'!$A:$CY,3,FALSE)),IF(VLOOKUP(VLOOKUP(LEFT('1) Import fichier Remi (coller)'!$A6,9),'Concordance client liv et fact'!$A:$H,7,FALSE)+0,'Clients R2'!$A:$CY,22,FALSE)=4,"NA",VLOOKUP(VLOOKUP(LEFT('1) Import fichier Remi (coller)'!$A6,9),'Concordance client liv et fact'!$A:$H,7,FALSE)+0,'Clients R2'!$A:$CY,3,FALSE)))),2)) -> BE | X6: =IF($A6="","",IF(ISERROR(VLOOKUP(LEFT('1) Import fichier Remi (coller)'!$A6,9),'Concordance client liv et fact'!$A:$H,8,FALSE))=TRUE,VLOOKUP(LEFT('1) Import fichier Remi (coller)'!$A6,9)+0,'Clients R2'!$A:$CY,102,FALSE),VLOOKUP(VLOOKUP(LEFT('1) Import fichier Remi (coller)'!$A6,9),'Concordance client liv et fact'!$A:$H,7,FALSE)+0,'Clients R2'!$A:$CY,102,FALSE))) -> compta.ibs@ibgraf.com | Y6: CF11261601.PDF | Z6: GDUHOUX | AA6: =IF($A6="VE11","",IF(LEFT($H6,4)="7050","",IF('1) Import fichier Remi (coller)'!M6="","",'1) Import fichier Remi (coller)'!M6))) | AB6: =IF($A6="VE11","",IF(LEFT($H6,4)="7050","",IF('1) Import fichier Remi (coller)'!N6="","",'1) Import fichier Remi (coller)'!N6))) | AC6: =IF(A6="","",VLOOKUP(LEFT('1) Import fichier Remi (coller)'!A6,9)+0,'Concordance Client R2 BOB'!$B:$C,2,FALSE)) -> IBS
A7: =IF('1) Import fichier Remi (coller)'!D7="","",'1) Import fichier Remi (coller)'!D7) -> VE11 | B7: =IF(A7="","",YEAR('1) Import fichier Remi (coller)'!F7)) -> 2026 | C7: =IF(A7="","",MONTH('1) Import fichier Remi (coller)'!F7)) -> 9 | D7: =IF(A7="","",'1) Import fichier Remi (coller)'!F7) -> 46281 | E7: =IF(A7="","",'1) Import fichier Remi (coller)'!G7) -> 46281 | F7: =IF(A7="","",'1) Import fichier Remi (coller)'!E7) -> 11261511 | G7: =IF(A7="","",IF(ISERROR(VLOOKUP(LEFT('1) Import fichier Remi (coller)'!A7,9),'Concordance client liv et fact'!$A:$H,8,FALSE))=TRUE,'1) Import fichier Remi (coller)'!B7,VLOOKUP(LEFT('1) Import fichier Remi (coller)'!A7,9),'Concordance client liv et fact'!$A:$H,8,FALSE))) -> IBS | H7: =IF(A7="","",IF(ISERROR(VLOOKUP('1) Import fichier Remi (coller)'!K7&" - "&'1) Import fichier Remi (coller)'!L7,'Spécifique comptes'!$A:$G,1,FALSE))=TRUE,'1) Import fichier Remi (coller)'!V7,VLOOKUP('1) Import fichier Remi (coller)'!K7&" - "&'1) Import fichier Remi (coller)'!L7,'Spécifique comptes'!$A:$G,IF(LEFT('2) BOB compta (completer-forcer'!F7,2)="11",4,IF(LEFT('2) BOB compta (completer-forcer'!F7,2)="12",5,IF(LEFT('2) BOB compta (completer-forcer'!F7,2)="13",6,IF(LEFT('2) BOB compta (completer-forcer'!F7,2)="15",7,"Erreur Compte")))),FALSE))) -> 705002000 | I7: =IF(A7="","",IF(H7="70100000",'1) Import fichier Remi (coller)'!J7,'1) Import fichier Remi (coller)'!U7)) -> +++003/7261/51128+++ | J7: =IF(A7="","",'1) Import fichier Remi (coller)'!U7) -> +++003/7261/51128+++ | K7: =IF(A7="","",SUMIFS(N:N,A:A,A7,F:F,F7)+SUMIFS(O:O,A:A,A7,F:F,F7)) -> 152.46 | L7: =IF(A7="","",IF(LEFT(T7,1)="B","V","PRT")) -> V | M7: =IF(A7="","",'1) Import fichier Remi (coller)'!S7) -> 21 | N7: =IF($A7="","",IF(OR($A7="NCV",$A7="NC15"),-'1) Import fichier Remi (coller)'!R7,'1) Import fichier Remi (coller)'!R7)) -> 18 | O7: =IF($A7="","",IF(OR($A7="NCV",$A7="NC15"),-'1) Import fichier Remi (coller)'!T7,'1) Import fichier Remi (coller)'!T7)) -> 3.78 | R7: =IF($A7="","",IF(ISERROR(VLOOKUP(LEFT('1) Import fichier Remi (coller)'!$A7,9),'Concordance client liv et fact'!$A:$H,8,FALSE))=TRUE,VLOOKUP(LEFT('1) Import fichier Remi (coller)'!$A7,9)+0,'Clients R2'!$A:$CY,2,FALSE),VLOOKUP(VLOOKUP(LEFT('1) Import fichier Remi (coller)'!$A7,9),'Concordance client liv et fact'!$A:$H,7,FALSE)+0,'Clients R2'!$A:$CY,2,FALSE))) -> IBGRAF BUSINESS SOL. | S7: =IF($A7="","",PROPER(IF(ISERROR(VLOOKUP(LEFT('1) Import fichier Remi (coller)'!$A7,9),'Concordance client liv et fact'!$A:$H,8,FALSE))=TRUE,VLOOKUP(LEFT('1) Import fichier Remi (coller)'!$A7,9)+0,'Clients R2'!$A:$CY,27,FALSE),VLOOKUP(VLOOKUP(LEFT('1) Import fichier Remi (coller)'!$A7,9),'Concordance client liv et fact'!$A:$H,7,FALSE)+0,'Clients R2'!$A:$CY,27,FALSE)))) -> Rue D'Abhooz, 27 | T7: =IF($A7="","",LEFT(UPPER(IF(ISERROR(VLOOKUP(LEFT('1) Import fichier Remi (coller)'!$A7,9),'Concordance client liv et fact'!$A:$H,8,FALSE))=TRUE,VLOOKUP(LEFT('1) Import fichier Remi (coller)'!$A7,9)+0,'Clients R2'!$A:$CY,28,FALSE),VLOOKUP(VLOOKUP(LEFT('1) Import fichier Remi (coller)'!$A7,9),'Concordance client liv et fact'!$A:$H,7,FALSE)+0,'Clients R2'!$A:$CY,28,FALSE))),2)&UPPER(IF(ISERROR(VLOOKUP(LEFT('1) Import fichier Remi (coller)'!$A7,9),'Concordance client liv et fact'!$A:$H,8,FALSE))=TRUE,VLOOKUP(LEFT('1) Import fichier Remi (coller)'!$A7,9)+0,'Clients R2'!$A:$CY,29,FALSE),VLOOKUP(VLOOKUP(LEFT('1) Import fichier Remi (coller)'!$A7,9),'Concordance client liv et fact'!$A:$H,7,FALSE)+0,'Clients R2'!$A:$CY,29,FALSE)))) -> B 4040 | U7: =IF($A7="","",PROPER(IF(ISERROR(VLOOKUP(LEFT('1) Import fichier Remi (coller)'!$A7,9),'Concordance client liv et fact'!$A:$H,8,FALSE))=TRUE,VLOOKUP(LEFT('1) Import fichier Remi (coller)'!$A7,9)+0,'Clients R2'!$A:$CY,30,FALSE),VLOOKUP(VLOOKUP(LEFT('1) Import fichier Remi (coller)'!$A7,9),'Concordance client liv et fact'!$A:$H,7,FALSE)+0,'Clients R2'!$A:$CY,30,FALSE)))) -> Herstal | V7: =IF($A7="","",LEFT(UPPER(IF(ISERROR(VLOOKUP(LEFT('1) Import fichier Remi (coller)'!$A7,9),'Concordance client liv et fact'!$A:$H,8,FALSE))=TRUE,IF(VLOOKUP(LEFT('1) Import fichier Remi (coller)'!$A7,9)+0,'Clients R2'!$A:$CY,22,FALSE)=4,"NA",VLOOKUP(LEFT('1) Import fichier Remi (coller)'!$A7,9)+0,'Clients R2'!$A:$CY,3,FALSE)),IF(VLOOKUP(VLOOKUP(LEFT('1) Import fichier Remi (coller)'!$A7,9),'Concordance client liv et fact'!$A:$H,7,FALSE)+0,'Clients R2'!$A:$CY,22,FALSE)=4,"NA",VLOOKUP(VLOOKUP(LEFT('1) Import fichier Remi (coller)'!$A7,9),'Concordance client liv et fact'!$A:$H,7,FALSE)+0,'Clients R2'!$A:$CY,3,FALSE)))),2)) -> BE | X7: =IF($A7="","",IF(ISERROR(VLOOKUP(LEFT('1) Import fichier Remi (coller)'!$A7,9),'Concordance client liv et fact'!$A:$H,8,FALSE))=TRUE,VLOOKUP(LEFT('1) Import fichier Remi (coller)'!$A7,9)+0,'Clients R2'!$A:$CY,102,FALSE),VLOOKUP(VLOOKUP(LEFT('1) Import fichier Remi (coller)'!$A7,9),'Concordance client liv et fact'!$A:$H,7,FALSE)+0,'Clients R2'!$A:$CY,102,FALSE))) -> compta.ibs@ibgraf.com | Y7: CF11261601.PDF | Z7: GDUHOUX | AA7: =IF($A7="VE11","",IF(LEFT($H7,4)="7050","",IF('1) Import fichier Remi (coller)'!M7="","",'1) Import fichier Remi (coller)'!M7))) | AB7: =IF($A7="VE11","",IF(LEFT($H7,4)="7050","",IF('1) Import fichier Remi (coller)'!N7="","",'1) Import fichier Remi (coller)'!N7))) | AC7: =IF(A7="","",VLOOKUP(LEFT('1) Import fichier Remi (coller)'!A7,9)+0,'Concordance Client R2 BOB'!$B:$C,2,FALSE)) -> IBS
A8: =IF('1) Import fichier Remi (coller)'!D8="","",'1) Import fichier Remi (coller)'!D8) -> VE11 | B8: =IF(A8="","",YEAR('1) Import fichier Remi (coller)'!F8)) -> 2026 | C8: =IF(A8="","",MONTH('1) Import fichier Remi (coller)'!F8)) -> 9 | D8: =IF(A8="","",'1) Import fichier Remi (coller)'!F8) -> 46281 | E8: =IF(A8="","",'1) Import fichier Remi (coller)'!G8) -> 46281 | F8: =IF(A8="","",'1) Import fichier Remi (coller)'!E8) -> 11261512 | G8: =IF(A8="","",IF(ISERROR(VLOOKUP(LEFT('1) Import fichier Remi (coller)'!A8,9),'Concordance client liv et fact'!$A:$H,8,FALSE))=TRUE,'1) Import fichier Remi (coller)'!B8,VLOOKUP(LEFT('1) Import fichier Remi (coller)'!A8,9),'Concordance client liv et fact'!$A:$H,8,FALSE))) -> CBFISC | H8: =IF(A8="","",IF(ISERROR(VLOOKUP('1) Import fichier Remi (coller)'!K8&" - "&'1) Import fichier Remi (coller)'!L8,'Spécifique comptes'!$A:$G,1,FALSE))=TRUE,'1) Import fichier Remi (coller)'!V8,VLOOKUP('1) Import fichier Remi (coller)'!K8&" - "&'1) Import fichier Remi (coller)'!L8,'Spécifique comptes'!$A:$G,IF(LEFT('2) BOB compta (completer-forcer'!F8,2)="11",4,IF(LEFT('2) BOB compta (completer-forcer'!F8,2)="12",5,IF(LEFT('2) BOB compta (completer-forcer'!F8,2)="13",6,IF(LEFT('2) BOB compta (completer-forcer'!F8,2)="15",7,"Erreur Compte")))),FALSE))) -> 705099999 | I8: =IF(A8="","",IF(H8="70100000",'1) Import fichier Remi (coller)'!J8,'1) Import fichier Remi (coller)'!U8)) -> +++003/7261/51229+++ | J8: =IF(A8="","",'1) Import fichier Remi (coller)'!U8) -> +++003/7261/51229+++ | K8: =IF(A8="","",SUMIFS(N:N,A:A,A8,F:F,F8)+SUMIFS(O:O,A:A,A8,F:F,F8)) -> 28.74 | L8: =IF(A8="","",IF(LEFT(T8,1)="B","V","PRT")) -> V | M8: =IF(A8="","",'1) Import fichier Remi (coller)'!S8) -> 21 | N8: =IF($A8="","",IF(OR($A8="NCV",$A8="NC15"),-'1) Import fichier Remi (coller)'!R8,'1) Import fichier Remi (coller)'!R8)) -> 23.75 | O8: =IF($A8="","",IF(OR($A8="NCV",$A8="NC15"),-'1) Import fichier Remi (coller)'!T8,'1) Import fichier Remi (coller)'!T8)) -> 4.99 | R8: =IF($A8="","",IF(ISERROR(VLOOKUP(LEFT('1) Import fichier Remi (coller)'!$A8,9),'Concordance client liv et fact'!$A:$H,8,FALSE))=TRUE,VLOOKUP(LEFT('1) Import fichier Remi (coller)'!$A8,9)+0,'Clients R2'!$A:$CY,2,FALSE),VLOOKUP(VLOOKUP(LEFT('1) Import fichier Remi (coller)'!$A8,9),'Concordance client liv et fact'!$A:$H,7,FALSE)+0,'Clients R2'!$A:$CY,2,FALSE))) -> CB FISC | S8: =IF($A8="","",PROPER(IF(ISERROR(VLOOKUP(LEFT('1) Import fichier Remi (coller)'!$A8,9),'Concordance client liv et fact'!$A:$H,8,FALSE))=TRUE,VLOOKUP(LEFT('1) Import fichier Remi (coller)'!$A8,9)+0,'Clients R2'!$A:$CY,27,FALSE),VLOOKUP(VLOOKUP(LEFT('1) Import fichier Remi (coller)'!$A8,9),'Concordance client liv et fact'!$A:$H,7,FALSE)+0,'Clients R2'!$A:$CY,27,FALSE)))) -> Rue Affnay, 13 | T8: =IF($A8="","",LEFT(UPPER(IF(ISERROR(VLOOKUP(LEFT('1) Import fichier Remi (coller)'!$A8,9),'Concordance client liv et fact'!$A:$H,8,FALSE))=TRUE,VLOOKUP(LEFT('1) Import fichier Remi (coller)'!$A8,9)+0,'Clients R2'!$A:$CY,28,FALSE),VLOOKUP(VLOOKUP(LEFT('1) Import fichier Remi (coller)'!$A8,9),'Concordance client liv et fact'!$A:$H,7,FALSE)+0,'Clients R2'!$A:$CY,28,FALSE))),2)&UPPER(IF(ISERROR(VLOOKUP(LEFT('1) Import fichier Remi (coller)'!$A8,9),'Concordance client liv et fact'!$A:$H,8,FALSE))=TRUE,VLOOKUP(LEFT('1) Import fichier Remi (coller)'!$A8,9)+0,'Clients R2'!$A:$CY,29,FALSE),VLOOKUP(VLOOKUP(LEFT('1) Import fichier Remi (coller)'!$A8,9),'Concordance client liv et fact'!$A:$H,7,FALSE)+0,'Clients R2'!$A:$CY,29,FALSE)))) -> B 4608 | U8: =IF($A8="","",PROPER(IF(ISERROR(VLOOKUP(LEFT('1) Import fichier Remi (coller)'!$A8,9),'Concordance client liv et fact'!$A:$H,8,FALSE))=TRUE,VLOOKUP(LEFT('1) Import fichier Remi (coller)'!$A8,9)+0,'Clients R2'!$A:$CY,30,FALSE),VLOOKUP(VLOOKUP(LEFT('1) Import fichier Remi (coller)'!$A8,9),'Concordance client liv et fact'!$A:$H,7,FALSE)+0,'Clients R2'!$A:$CY,30,FALSE)))) -> Dalhem (Neufchateau) | V8: =IF($A8="","",LEFT(UPPER(IF(ISERROR(VLOOKUP(LEFT('1) Import fichier Remi (coller)'!$A8,9),'Concordance client liv et fact'!$A:$H,8,FALSE))=TRUE,IF(VLOOKUP(LEFT('1) Import fichier Remi (coller)'!$A8,9)+0,'Clients R2'!$A:$CY,22,FALSE)=4,"NA",VLOOKUP(LEFT('1) Import fichier Remi (coller)'!$A8,9)+0,'Clients R2'!$A:$CY,3,FALSE)),IF(VLOOKUP(VLOOKUP(LEFT('1) Import fichier Remi (coller)'!$A8,9),'Concordance client liv et fact'!$A:$H,7,FALSE)+0,'Clients R2'!$A:$CY,22,FALSE)=4,"NA",VLOOKUP(VLOOKUP(LEFT('1) Import fichier Remi (coller)'!$A8,9),'Concordance client liv et fact'!$A:$H,7,FALSE)+0,'Clients R2'!$A:$CY,3,FALSE)))),2)) -> BE | X8: =IF($A8="","",IF(ISERROR(VLOOKUP(LEFT('1) Import fichier Remi (coller)'!$A8,9),'Concordance client liv et fact'!$A:$H,8,FALSE))=TRUE,VLOOKUP(LEFT('1) Import fichier Remi (coller)'!$A8,9)+0,'Clients R2'!$A:$CY,102,FALSE),VLOOKUP(VLOOKUP(LEFT('1) Import fichier Remi (coller)'!$A8,9),'Concordance client liv et fact'!$A:$H,7,FALSE)+0,'Clients R2'!$A:$CY,102,FALSE))) -> info@cbfisc.be | Y8: CF11261601.PDF | Z8: =IF(A8="","",IF(OR(H8="705099999",H8="705001002"),VLOOKUP('1) Import fichier Remi (coller)'!J8,'Analytique personnel'!$A:$B,2,FALSE),"")) -> GDUHOUX | AA8: =IF($A8="VE11","",IF(LEFT($H8,4)="7050","",IF('1) Import fichier Remi (coller)'!M8="","",'1) Import fichier Remi (coller)'!M8))) | AB8: =IF($A8="VE11","",IF(LEFT($H8,4)="7050","",IF('1) Import fichier Remi (coller)'!N8="","",'1) Import fichier Remi (coller)'!N8))) | AC8: =IF(A8="","",VLOOKUP(LEFT('1) Import fichier Remi (coller)'!A8,9)+0,'Concordance Client R2 BOB'!$B:$C,2,FALSE)) -> CBFISC
A9: =IF('1) Import fichier Remi (coller)'!D9="","",'1) Import fichier Remi (coller)'!D9) -> VE11 | B9: =IF(A9="","",YEAR('1) Import fichier Remi (coller)'!F9)) -> 2026 | C9: =IF(A9="","",MONTH('1) Import fichier Remi (coller)'!F9)) -> 9 | D9: =IF(A9="","",'1) Import fichier Remi (coller)'!F9) -> 46281 | E9: =IF(A9="","",'1) Import fichier Remi (coller)'!G9) -> 46311 | F9: =IF(A9="","",'1) Import fichier Remi (coller)'!E9) -> 11261513 | G9: =IF(A9="","",IF(ISERROR(VLOOKUP(LEFT('1) Import fichier Remi (coller)'!A9,9),'Concordance client liv et fact'!$A:$H,8,FALSE))=TRUE,'1) Import fichier Remi (coller)'!B9,VLOOKUP(LEFT('1) Import fichier Remi (coller)'!A9,9),'Concordance client liv et fact'!$A:$H,8,FALSE))) -> COUTREZSA | H9: =IF(A9="","",IF(ISERROR(VLOOKUP('1) Import fichier Remi (coller)'!K9&" - "&'1) Import fichier Remi (coller)'!L9,'Spécifique comptes'!$A:$G,1,FALSE))=TRUE,'1) Import fichier Remi (coller)'!V9,VLOOKUP('1) Import fichier Remi (coller)'!K9&" - "&'1) Import fichier Remi (coller)'!L9,'Spécifique comptes'!$A:$G,IF(LEFT('2) BOB compta (completer-forcer'!F9,2)="11",4,IF(LEFT('2) BOB compta (completer-forcer'!F9,2)="12",5,IF(LEFT('2) BOB compta (completer-forcer'!F9,2)="13",6,IF(LEFT('2) BOB compta (completer-forcer'!F9,2)="15",7,"Erreur Compte")))),FALSE))) -> 705099999 | I9: =IF(A9="","",IF(H9="70100000",'1) Import fichier Remi (coller)'!J9,'1) Import fichier Remi (coller)'!U9)) -> +++003/7261/51330+++ | J9: =IF(A9="","",'1) Import fichier Remi (coller)'!U9) -> +++003/7261/51330+++ | K9: =IF(A9="","",SUMIFS(N:N,A:A,A9,F:F,F9)+SUMIFS(O:O,A:A,A9,F:F,F9)) -> 114.95 | L9: =IF(A9="","",IF(LEFT(T9,1)="B","V","PRT")) -> V | M9: =IF(A9="","",'1) Import fichier Remi (coller)'!S9) -> 21 | N9: =IF($A9="","",IF(OR($A9="NCV",$A9="NC15"),-'1) Import fichier Remi (coller)'!R9,'1) Import fichier Remi (coller)'!R9)) -> 95 | O9: =IF($A9="","",IF(OR($A9="NCV",$A9="NC15"),-'1) Import fichier Remi (coller)'!T9,'1) Import fichier Remi (coller)'!T9)) -> 19.95 | R9: =IF($A9="","",IF(ISERROR(VLOOKUP(LEFT('1) Import fichier Remi (coller)'!$A9,9),'Concordance client liv et fact'!$A:$H,8,FALSE))=TRUE,VLOOKUP(LEFT('1) Import fichier Remi (coller)'!$A9,9)+0,'Clients R2'!$A:$CY,2,FALSE),VLOOKUP(VLOOKUP(LEFT('1) Import fichier Remi (coller)'!$A9,9),'Concordance client liv et fact'!$A:$H,7,FALSE)+0,'Clients R2'!$A:$CY,2,FALSE))) -> ETS COUTREZ ET CIE SA | S9: =IF($A9="","",PROPER(IF(ISERROR(VLOOKUP(LEFT('1) Import fichier Remi (coller)'!$A9,9),'Concordance client liv et fact'!$A:$H,8,FALSE))=TRUE,VLOOKUP(LEFT('1) Import fichier Remi (coller)'!$A9,9)+0,'Clients R2'!$A:$CY,27,FALSE),VLOOKUP(VLOOKUP(LEFT('1) Import fichier Remi (coller)'!$A9,9),'Concordance client liv et fact'!$A:$H,7,FALSE)+0,'Clients R2'!$A:$CY,27,FALSE)))) -> Rue Louis Bleriot, 1 | T9: =IF($A9="","",LEFT(UPPER(IF(ISERROR(VLOOKUP(LEFT('1) Import fichier Remi (coller)'!$A9,9),'Concordance client liv et fact'!$A:$H,8,FALSE))=TRUE,VLOOKUP(LEFT('1) Import fichier Remi (coller)'!$A9,9)+0,'Clients R2'!$A:$CY,28,FALSE),VLOOKUP(VLOOKUP(LEFT('1) Import fichier Remi (coller)'!$A9,9),'Concordance client liv et fact'!$A:$H,7,FALSE)+0,'Clients R2'!$A:$CY,28,FALSE))),2)&UPPER(IF(ISERROR(VLOOKUP(LEFT('1) Import fichier Remi (coller)'!$A9,9),'Concordance client liv et fact'!$A:$H,8,FALSE))=TRUE,VLOOKUP(LEFT('1) Import fichier Remi (coller)'!$A9,9)+0,'Clients R2'!$A:$CY,29,FALSE),VLOOKUP(VLOOKUP(LEFT('1) Import fichier Remi (coller)'!$A9,9),'Concordance client liv et fact'!$A:$H,7,FALSE)+0,'Clients R2'!$A:$CY,29,FALSE)))) -> B 4460 | U9: =IF($A9="","",PROPER(IF(ISERROR(VLOOKUP(LEFT('1) Import fichier Remi (coller)'!$A9,9),'Concordance client liv et fact'!$A:$H,8,FALSE))=TRUE,VLOOKUP(LEFT('1) Import fichier Remi (coller)'!$A9,9)+0,'Clients R2'!$A:$CY,30,FALSE),VLOOKUP(VLOOKUP(LEFT('1) Import fichier Remi (coller)'!$A9,9),'Concordance client liv et fact'!$A:$H,7,FALSE)+0,'Clients R2'!$A:$CY,30,FALSE)))) -> Grace Hollogne | V9: =IF($A9="","",LEFT(UPPER(IF(ISERROR(VLOOKUP(LEFT('1) Import fichier Remi (coller)'!$A9,9),'Concordance client liv et fact'!$A:$H,8,FALSE))=TRUE,IF(VLOOKUP(LEFT('1) Import fichier Remi (coller)'!$A9,9)+0,'Clients R2'!$A:$CY,22,FALSE)=4,"NA",VLOOKUP(LEFT('1) Import fichier Remi (coller)'!$A9,9)+0,'Clients R2'!$A:$CY,3,FALSE)),IF(VLOOKUP(VLOOKUP(LEFT('1) Import fichier Remi (coller)'!$A9,9),'Concordance client liv et fact'!$A:$H,7,FALSE)+0,'Clients R2'!$A:$CY,22,FALSE)=4,"NA",VLOOKUP(VLOOKUP(LEFT('1) Import fichier Remi (coller)'!$A9,9),'Concordance client liv et fact'!$A:$H,7,FALSE)+0,'Clients R2'!$A:$CY,3,FALSE)))),2)) -> BE | X9: =IF($A9="","",IF(ISERROR(VLOOKUP(LEFT('1) Import fichier Remi (coller)'!$A9,9),'Concordance client liv et fact'!$A:$H,8,FALSE))=TRUE,VLOOKUP(LEFT('1) Import fichier Remi (coller)'!$A9,9)+0,'Clients R2'!$A:$CY,102,FALSE),VLOOKUP(VLOOKUP(LEFT('1) Import fichier Remi (coller)'!$A9,9),'Concordance client liv et fact'!$A:$H,7,FALSE)+0,'Clients R2'!$A:$CY,102,FALSE))) -> invoicing@coutrez.be | Y9: CF11261601.PDF | Z9: =IF(A9="","",IF(OR(H9="705099999",H9="705001002"),VLOOKUP('1) Import fichier Remi (coller)'!J9,'Analytique personnel'!$A:$B,2,FALSE),"")) -> BMELIN | AA9: =IF($A9="VE11","",IF(LEFT($H9,4)="7050","",IF('1) Import fichier Remi (coller)'!M9="","",'1) Import fichier Remi (coller)'!M9))) | AB9: =IF($A9="VE11","",IF(LEFT($H9,4)="7050","",IF('1) Import fichier Remi (coller)'!N9="","",'1) Import fichier Remi (coller)'!N9))) | AC9: =IF(A9="","",VLOOKUP(LEFT('1) Import fichier Remi (coller)'!A9,9)+0,'Concordance Client R2 BOB'!$B:$C,2,FALSE)) -> COUTREZSA
A10: =IF('1) Import fichier Remi (coller)'!D10="","",'1) Import fichier Remi (coller)'!D10) -> VE11 | B10: =IF(A10="","",YEAR('1) Import fichier Remi (coller)'!F10)) -> 2026 | C10: =IF(A10="","",MONTH('1) Import fichier Remi (coller)'!F10)) -> 9 | D10: =IF(A10="","",'1) Import fichier Remi (coller)'!F10) -> 46281 | E10: =IF(A10="","",'1) Import fichier Remi (coller)'!G10) -> 46281 | F10: =IF(A10="","",'1) Import fichier Remi (coller)'!E10) -> 11261514 | G10: =IF(A10="","",IF(ISERROR(VLOOKUP(LEFT('1) Import fichier Remi (coller)'!A10,9),'Concordance client liv et fact'!$A:$H,8,FALSE))=TRUE,'1) Import fichier Remi (coller)'!B10,VLOOKUP(LEFT('1) Import fichier Remi (coller)'!A10,9),'Concordance client liv et fact'!$A:$H,8,FALSE))) -> DEL003 | H10: =IF(A10="","",IF(ISERROR(VLOOKUP('1) Import fichier Remi (coller)'!K10&" - "&'1) Import fichier Remi (coller)'!L10,'Spécifique comptes'!$A:$G,1,FALSE))=TRUE,'1) Import fichier Remi (coller)'!V10,VLOOKUP('1) Import fichier Remi (coller)'!K10&" - "&'1) Import fichier Remi (coller)'!L10,'Spécifique comptes'!$A:$G,IF(LEFT('2) BOB compta (completer-forcer'!F10,2)="11",4,IF(LEFT('2) BOB compta (completer-forcer'!F10,2)="12",5,IF(LEFT('2) BOB compta (completer-forcer'!F10,2)="13",6,IF(LEFT('2) BOB compta (completer-forcer'!F10,2)="15",7,"Erreur Compte")))),FALSE))) -> 705099999 | I10: =IF(A10="","",IF(H10="70100000",'1) Import fichier Remi (coller)'!J10,'1) Import fichier Remi (coller)'!U10)) -> +++003/7261/51431+++ | J10: =IF(A10="","",'1) Import fichier Remi (coller)'!U10) -> +++003/7261/51431+++ | K10: =IF(A10="","",SUMIFS(N:N,A:A,A10,F:F,F10)+SUMIFS(O:O,A:A,A10,F:F,F10)) -> 205.46 | L10: =IF(A10="","",IF(LEFT(T10,1)="B","V","PRT")) -> V | M10: =IF(A10="","",'1) Import fichier Remi (coller)'!S10) -> 21 | N10: =IF($A10="","",IF(OR($A10="NCV",$A10="NC15"),-'1) Import fichier Remi (coller)'!R10,'1) Import fichier Remi (coller)'!R10)) -> 47.5 | O10: =IF($A10="","",IF(OR($A10="NCV",$A10="NC15"),-'1) Import fichier Remi (coller)'!T10,'1) Import fichier Remi (coller)'!T10)) -> 9.98 | R10: =IF($A10="","",IF(ISERROR(VLOOKUP(LEFT('1) Import fichier Remi (coller)'!$A10,9),'Concordance client liv et fact'!$A:$H,8,FALSE))=TRUE,VLOOKUP(LEFT('1) Import fichier Remi (coller)'!$A10,9)+0,'Clients R2'!$A:$CY,2,FALSE),VLOOKUP(VLOOKUP(LEFT('1) Import fichier Remi (coller)'!$A10,9),'Concordance client liv et fact'!$A:$H,7,FALSE)+0,'Clients R2'!$A:$CY,2,FALSE))) -> DELHEZ COMBUSTIBLES | S10: =IF($A10="","",PROPER(IF(ISERROR(VLOOKUP(LEFT('1) Import fichier Remi (coller)'!$A10,9),'Concordance client liv et fact'!$A:$H,8,FALSE))=TRUE,VLOOKUP(LEFT('1) Import fichier Remi (coller)'!$A10,9)+0,'Clients R2'!$A:$CY,27,FALSE),VLOOKUP(VLOOKUP(LEFT('1) Import fichier Remi (coller)'!$A10,9),'Concordance client liv et fact'!$A:$H,7,FALSE)+0,'Clients R2'!$A:$CY,27,FALSE)))) -> Route Du Chateau, 4 | T10: =IF($A10="","",LEFT(UPPER(IF(ISERROR(VLOOKUP(LEFT('1) Import fichier Remi (coller)'!$A10,9),'Concordance client liv et fact'!$A:$H,8,FALSE))=TRUE,VLOOKUP(LEFT('1) Import fichier Remi (coller)'!$A10,9)+0,'Clients R2'!$A:$CY,28,FALSE),VLOOKUP(VLOOKUP(LEFT('1) Import fichier Remi (coller)'!$A10,9),'Concordance client liv et fact'!$A:$H,7,FALSE)+0,'Clients R2'!$A:$CY,28,FALSE))),2)&UPPER(IF(ISERROR(VLOOKUP(LEFT('1) Import fichier Remi (coller)'!$A10,9),'Concordance client liv et fact'!$A:$H,8,FALSE))=TRUE,VLOOKUP(LEFT('1) Import fichier Remi (coller)'!$A10,9)+0,'Clients R2'!$A:$CY,29,FALSE),VLOOKUP(VLOOKUP(LEFT('1) Import fichier Remi (coller)'!$A10,9),'Concordance client liv et fact'!$A:$H,7,FALSE)+0,'Clients R2'!$A:$CY,29,FALSE)))) -> B 4877 | U10: =IF($A10="","",PROPER(IF(ISERROR(VLOOKUP(LEFT('1) Import fichier Remi (coller)'!$A10,9),'Concordance client liv et fact'!$A:$H,8,FALSE))=TRUE,VLOOKUP(LEFT('1) Import fichier Remi (coller)'!$A10,9)+0,'Clients R2'!$A:$CY,30,FALSE),VLOOKUP(VLOOKUP(LEFT('1) Import fichier Remi (coller)'!$A10,9),'Concordance client liv et fact'!$A:$H,7,FALSE)+0,'Clients R2'!$A:$CY,30,FALSE)))) -> Olne | V10: =IF($A10="","",LEFT(UPPER(IF(ISERROR(VLOOKUP(LEFT('1) Import fichier Remi (coller)'!$A10,9),'Concordance client liv et fact'!$A:$H,8,FALSE))=TRUE,IF(VLOOKUP(LEFT('1) Import fichier Remi (coller)'!$A10,9)+0,'Clients R2'!$A:$CY,22,FALSE)=4,"NA",VLOOKUP(LEFT('1) Import fichier Remi (coller)'!$A10,9)+0,'Clients R2'!$A:$CY,3,FALSE)),IF(VLOOKUP(VLOOKUP(LEFT('1) Import fichier Remi (coller)'!$A10,9),'Concordance client liv et fact'!$A:$H,7,FALSE)+0,'Clients R2'!$A:$CY,22,FALSE)=4,"NA",VLOOKUP(VLOOKUP(LEFT('1) Import fichier Remi (coller)'!$A10,9),'Concordance client liv et fact'!$A:$H,7,FALSE)+0,'Clients R2'!$A:$CY,3,FALSE)))),2)) -> BE | X10: =IF($A10="","",IF(ISERROR(VLOOKUP(LEFT('1) Import fichier Remi (coller)'!$A10,9),'Concordance client liv et fact'!$A:$H,8,FALSE))=TRUE,VLOOKUP(LEFT('1) Import fichier Remi (coller)'!$A10,9)+0,'Clients R2'!$A:$CY,102,FALSE),VLOOKUP(VLOOKUP(LEFT('1) Import fichier Remi (coller)'!$A10,9),'Concordance client liv et fact'!$A:$H,7,FALSE)+0,'Clients R2'!$A:$CY,102,FALSE))) -> info@delhez-combustibles.be | Y10: CF11261601.PDF | Z10: =IF(A10="","",IF(OR(H10="705099999",H10="705001002"),VLOOKUP('1) Import fichier Remi (coller)'!J10,'Analytique personnel'!$A:$B,2,FALSE),"")) -> MFONTAINE | AA10: =IF($A10="VE11","",IF(LEFT($H10,4)="7050","",IF('1) Import fichier Remi (coller)'!M10="","",'1) Import fichier Remi (coller)'!M10))) | AB10: =IF($A10="VE11","",IF(LEFT($H10,4)="7050","",IF('1) Import fichier Remi (coller)'!N10="","",'1) Import fichier Remi (coller)'!N10))) | AC10: =IF(A10="","",VLOOKUP(LEFT('1) Import fichier Remi (coller)'!A10,9)+0,'Concordance Client R2 BOB'!$B:$C,2,FALSE)) -> DEL003
A11: =IF('1) Import fichier Remi (coller)'!D11="","",'1) Import fichier Remi (coller)'!D11) -> VE11 | B11: =IF(A11="","",YEAR('1) Import fichier Remi (coller)'!F11)) -> 2026 | C11: =IF(A11="","",MONTH('1) Import fichier Remi (coller)'!F11)) -> 9 | D11: =IF(A11="","",'1) Import fichier Remi (coller)'!F11) -> 46281 | E11: =IF(A11="","",'1) Import fichier Remi (coller)'!G11) -> 46281 | F11: =IF(A11="","",'1) Import fichier Remi (coller)'!E11) -> 11261514 | G11: =IF(A11="","",IF(ISERROR(VLOOKUP(LEFT('1) Import fichier Remi (coller)'!A11,9),'Concordance client liv et fact'!$A:$H,8,FALSE))=TRUE,'1) Import fichier Remi (coller)'!B11,VLOOKUP(LEFT('1) Import fichier Remi (coller)'!A11,9),'Concordance client liv et fact'!$A:$H,8,FALSE))) -> DEL003 | H11: =IF(A11="","",IF(ISERROR(VLOOKUP('1) Import fichier Remi (coller)'!K11&" - "&'1) Import fichier Remi (coller)'!L11,'Spécifique comptes'!$A:$G,1,FALSE))=TRUE,'1) Import fichier Remi (coller)'!V11,VLOOKUP('1) Import fichier Remi (coller)'!K11&" - "&'1) Import fichier Remi (coller)'!L11,'Spécifique comptes'!$A:$G,IF(LEFT('2) BOB compta (completer-forcer'!F11,2)="11",4,IF(LEFT('2) BOB compta (completer-forcer'!F11,2)="12",5,IF(LEFT('2) BOB compta (completer-forcer'!F11,2)="13",6,IF(LEFT('2) BOB compta (completer-forcer'!F11,2)="15",7,"Erreur Compte")))),FALSE))) -> 705099999 | I11: =IF(A11="","",IF(H11="70100000",'1) Import fichier Remi (coller)'!J11,'1) Import fichier Remi (coller)'!U11)) -> +++003/7261/51431+++ | J11: =IF(A11="","",'1) Import fichier Remi (coller)'!U11) -> +++003/7261/51431+++ | K11: =IF(A11="","",SUMIFS(N:N,A:A,A11,F:F,F11)+SUMIFS(O:O,A:A,A11,F:F,F11)) -> 205.46 | L11: =IF(A11="","",IF(LEFT(T11,1)="B","V","PRT")) -> V | M11: =IF(A11="","",'1) Import fichier Remi (coller)'!S11) -> 21 | N11: =IF($A11="","",IF(OR($A11="NCV",$A11="NC15"),-'1) Import fichier Remi (coller)'!R11,'1) Import fichier Remi (coller)'!R11)) -> 47.5 | O11: =IF($A11="","",IF(OR($A11="NCV",$A11="NC15"),-'1) Import fichier Remi (coller)'!T11,'1) Import fichier Remi (coller)'!T11)) -> 9.98 | R11: =IF($A11="","",IF(ISERROR(VLOOKUP(LEFT('1) Import fichier Remi (coller)'!$A11,9),'Concordance client liv et fact'!$A:$H,8,FALSE))=TRUE,VLOOKUP(LEFT('1) Import fichier Remi (coller)'!$A11,9)+0,'Clients R2'!$A:$CY,2,FALSE),VLOOKUP(VLOOKUP(LEFT('1) Import fichier Remi (coller)'!$A11,9),'Concordance client liv et fact'!$A:$H,7,FALSE)+0,'Clients R2'!$A:$CY,2,FALSE))) -> DELHEZ COMBUSTIBLES | S11: =IF($A11="","",PROPER(IF(ISERROR(VLOOKUP(LEFT('1) Import fichier Remi (coller)'!$A11,9),'Concordance client liv et fact'!$A:$H,8,FALSE))=TRUE,VLOOKUP(LEFT('1) Import fichier Remi (coller)'!$A11,9)+0,'Clients R2'!$A:$CY,27,FALSE),VLOOKUP(VLOOKUP(LEFT('1) Import fichier Remi (coller)'!$A11,9),'Concordance client liv et fact'!$A:$H,7,FALSE)+0,'Clients R2'!$A:$CY,27,FALSE)))) -> Route Du Chateau, 4 | T11: =IF($A11="","",LEFT(UPPER(IF(ISERROR(VLOOKUP(LEFT('1) Import fichier Remi (coller)'!$A11,9),'Concordance client liv et fact'!$A:$H,8,FALSE))=TRUE,VLOOKUP(LEFT('1) Import fichier Remi (coller)'!$A11,9)+0,'Clients R2'!$A:$CY,28,FALSE),VLOOKUP(VLOOKUP(LEFT('1) Import fichier Remi (coller)'!$A11,9),'Concordance client liv et fact'!$A:$H,7,FALSE)+0,'Clients R2'!$A:$CY,28,FALSE))),2)&UPPER(IF(ISERROR(VLOOKUP(LEFT('1) Import fichier Remi (coller)'!$A11,9),'Concordance client liv et fact'!$A:$H,8,FALSE))=TRUE,VLOOKUP(LEFT('1) Import fichier Remi (coller)'!$A11,9)+0,'Clients R2'!$A:$CY,29,FALSE),VLOOKUP(VLOOKUP(LEFT('1) Import fichier Remi (coller)'!$A11,9),'Concordance client liv et fact'!$A:$H,7,FALSE)+0,'Clients R2'!$A:$CY,29,FALSE)))) -> B 4877 | U11: =IF($A11="","",PROPER(IF(ISERROR(VLOOKUP(LEFT('1) Import fichier Remi (coller)'!$A11,9),'Concordance client liv et fact'!$A:$H,8,FALSE))=TRUE,VLOOKUP(LEFT('1) Import fichier Remi (coller)'!$A11,9)+0,'Clients R2'!$A:$CY,30,FALSE),VLOOKUP(VLOOKUP(LEFT('1) Import fichier Remi (coller)'!$A11,9),'Concordance client liv et fact'!$A:$H,7,FALSE)+0,'Clients R2'!$A:$CY,30,FALSE)))) -> Olne | V11: =IF($A11="","",LEFT(UPPER(IF(ISERROR(VLOOKUP(LEFT('1) Import fichier Remi (coller)'!$A11,9),'Concordance client liv et fact'!$A:$H,8,FALSE))=TRUE,IF(VLOOKUP(LEFT('1) Import fichier Remi (coller)'!$A11,9)+0,'Clients R2'!$A:$CY,22,FALSE)=4,"NA",VLOOKUP(LEFT('1) Import fichier Remi (coller)'!$A11,9)+0,'Clients R2'!$A:$CY,3,FALSE)),IF(VLOOKUP(VLOOKUP(LEFT('1) Import fichier Remi (coller)'!$A11,9),'Concordance client liv et fact'!$A:$H,7,FALSE)+0,'Clients R2'!$A:$CY,22,FALSE)=4,"NA",VLOOKUP(VLOOKUP(LEFT('1) Import fichier Remi (coller)'!$A11,9),'Concordance client liv et fact'!$A:$H,7,FALSE)+0,'Clients R2'!$A:$CY,3,FALSE)))),2)) -> BE | X11: =IF($A11="","",IF(ISERROR(VLOOKUP(LEFT('1) Import fichier Remi (coller)'!$A11,9),'Concordance client liv et fact'!$A:$H,8,FALSE))=TRUE,VLOOKUP(LEFT('1) Import fichier Remi (coller)'!$A11,9)+0,'Clients R2'!$A:$CY,102,FALSE),VLOOKUP(VLOOKUP(LEFT('1) Import fichier Remi (coller)'!$A11,9),'Concordance client liv et fact'!$A:$H,7,FALSE)+0,'Clients R2'!$A:$CY,102,FALSE))) -> info@delhez-combustibles.be | Y11: CF11261601.PDF | Z11: =IF(A11="","",IF(OR(H11="705099999",H11="705001002"),VLOOKUP('1) Import fichier Remi (coller)'!J11,'Analytique personnel'!$A:$B,2,FALSE),"")) -> GDUHOUX | AA11: =IF($A11="VE11","",IF(LEFT($H11,4)="7050","",IF('1) Import fichier Remi (coller)'!M11="","",'1) Import fichier Remi (coller)'!M11))) | AB11: =IF($A11="VE11","",IF(LEFT($H11,4)="7050","",IF('1) Import fichier Remi (coller)'!N11="","",'1) Import fichier Remi (coller)'!N11))) | AC11: =IF(A11="","",VLOOKUP(LEFT('1) Import fichier Remi (coller)'!A11,9)+0,'Concordance Client R2 BOB'!$B:$C,2,FALSE)) -> DEL003
A12: =IF('1) Import fichier Remi (coller)'!D12="","",'1) Import fichier Remi (coller)'!D12) -> VE11 | B12: =IF(A12="","",YEAR('1) Import fichier Remi (coller)'!F12)) -> 2026 | C12: =IF(A12="","",MONTH('1) Import fichier Remi (coller)'!F12)) -> 9 | D12: =IF(A12="","",'1) Import fichier Remi (coller)'!F12) -> 46281 | E12: =IF(A12="","",'1) Import fichier Remi (coller)'!G12) -> 46281 | F12: =IF(A12="","",'1) Import fichier Remi (coller)'!E12) -> 11261514 | G12: =IF(A12="","",IF(ISERROR(VLOOKUP(LEFT('1) Import fichier Remi (coller)'!A12,9),'Concordance client liv et fact'!$A:$H,8,FALSE))=TRUE,'1) Import fichier Remi (coller)'!B12,VLOOKUP(LEFT('1) Import fichier Remi (coller)'!A12,9),'Concordance client liv et fact'!$A:$H,8,FALSE))) -> DEL003 | H12: =IF(A12="","",IF(ISERROR(VLOOKUP('1) Import fichier Remi (coller)'!K12&" - "&'1) Import fichier Remi (coller)'!L12,'Spécifique comptes'!$A:$G,1,FALSE))=TRUE,'1) Import fichier Remi (coller)'!V12,VLOOKUP('1) Import fichier Remi (coller)'!K12&" - "&'1) Import fichier Remi (coller)'!L12,'Spécifique comptes'!$A:$G,IF(LEFT('2) BOB compta (completer-forcer'!F12,2)="11",4,IF(LEFT('2) BOB compta (completer-forcer'!F12,2)="12",5,IF(LEFT('2) BOB compta (completer-forcer'!F12,2)="13",6,IF(LEFT('2) BOB compta (completer-forcer'!F12,2)="15",7,"Erreur Compte")))),FALSE))) -> 705001002 | I12: =IF(A12="","",IF(H12="70100000",'1) Import fichier Remi (coller)'!J12,'1) Import fichier Remi (coller)'!U12)) -> +++003/7261/51431+++ | J12: =IF(A12="","",'1) Import fichier Remi (coller)'!U12) -> +++003/7261/51431+++ | K12: =IF(A12="","",SUMIFS(N:N,A:A,A12,F:F,F12)+SUMIFS(O:O,A:A,A12,F:F,F12)) -> 205.46 | L12: =IF(A12="","",IF(LEFT(T12,1)="B","V","PRT")) -> V | M12: =IF(A12="","",'1) Import fichier Remi (coller)'!S12) -> 21 | N12: =IF($A12="","",IF(OR($A12="NCV",$A12="NC15"),-'1) Import fichier Remi (coller)'!R12,'1) Import fichier Remi (coller)'!R12)) -> 74.8 | O12: =IF($A12="","",IF(OR($A12="NCV",$A12="NC15"),-'1) Import fichier Remi (coller)'!T12,'1) Import fichier Remi (coller)'!T12)) -> 15.7 | R12: =IF($A12="","",IF(ISERROR(VLOOKUP(LEFT('1) Import fichier Remi (coller)'!$A12,9),'Concordance client liv et fact'!$A:$H,8,FALSE))=TRUE,VLOOKUP(LEFT('1) Import fichier Remi (coller)'!$A12,9)+0,'Clients R2'!$A:$CY,2,FALSE),VLOOKUP(VLOOKUP(LEFT('1) Import fichier Remi (coller)'!$A12,9),'Concordance client liv et fact'!$A:$H,7,FALSE)+0,'Clients R2'!$A:$CY,2,FALSE))) -> DELHEZ COMBUSTIBLES | S12: =IF($A12="","",PROPER(IF(ISERROR(VLOOKUP(LEFT('1) Import fichier Remi (coller)'!$A12,9),'Concordance client liv et fact'!$A:$H,8,FALSE))=TRUE,VLOOKUP(LEFT('1) Import fichier Remi (coller)'!$A12,9)+0,'Clients R2'!$A:$CY,27,FALSE),VLOOKUP(VLOOKUP(LEFT('1) Import fichier Remi (coller)'!$A12,9),'Concordance client liv et fact'!$A:$H,7,FALSE)+0,'Clients R2'!$A:$CY,27,FALSE)))) -> Route Du Chateau, 4 | T12: =IF($A12="","",LEFT(UPPER(IF(ISERROR(VLOOKUP(LEFT('1) Import fichier Remi (coller)'!$A12,9),'Concordance client liv et fact'!$A:$H,8,FALSE))=TRUE,VLOOKUP(LEFT('1) Import fichier Remi (coller)'!$A12,9)+0,'Clients R2'!$A:$CY,28,FALSE),VLOOKUP(VLOOKUP(LEFT('1) Import fichier Remi (coller)'!$A12,9),'Concordance client liv et fact'!$A:$H,7,FALSE)+0,'Clients R2'!$A:$CY,28,FALSE))),2)&UPPER(IF(ISERROR(VLOOKUP(LEFT('1) Import fichier Remi (coller)'!$A12,9),'Concordance client liv et fact'!$A:$H,8,FALSE))=TRUE,VLOOKUP(LEFT('1) Import fichier Remi (coller)'!$A12,9)+0,'Clients R2'!$A:$CY,29,FALSE),VLOOKUP(VLOOKUP(LEFT('1) Import fichier Remi (coller)'!$A12,9),'Concordance client liv et fact'!$A:$H,7,FALSE)+0,'Clients R2'!$A:$CY,29,FALSE)))) -> B 4877 | U12: =IF($A12="","",PROPER(IF(ISERROR(VLOOKUP(LEFT('1) Import fichier Remi (coller)'!$A12,9),'Concordance client liv et fact'!$A:$H,8,FALSE))=TRUE,VLOOKUP(LEFT('1) Import fichier Remi (coller)'!$A12,9)+0,'Clients R2'!$A:$CY,30,FALSE),VLOOKUP(VLOOKUP(LEFT('1) Import fichier Remi (coller)'!$A12,9),'Concordance client liv et fact'!$A:$H,7,FALSE)+0,'Clients R2'!$A:$CY,30,FALSE)))) -> Olne | V12: =IF($A12="","",LEFT(UPPER(IF(ISERROR(VLOOKUP(LEFT('1) Import fichier Remi (coller)'!$A12,9),'Concordance client liv et fact'!$A:$H,8,FALSE))=TRUE,IF(VLOOKUP(LEFT('1) Import fichier Remi (coller)'!$A12,9)+0,'Clients R2'!$A:$CY,22,FALSE)=4,"NA",VLOOKUP(LEFT('1) Import fichier Remi (coller)'!$A12,9)+0,'Clients R2'!$A:$CY,3,FALSE)),IF(VLOOKUP(VLOOKUP(LEFT('1) Import fichier Remi (coller)'!$A12,9),'Concordance client liv et fact'!$A:$H,7,FALSE)+0,'Clients R2'!$A:$CY,22,FALSE)=4,"NA",VLOOKUP(VLOOKUP(LEFT('1) Import fichier Remi (coller)'!$A12,9),'Concordance client liv et fact'!$A:$H,7,FALSE)+0,'Clients R2'!$A:$CY,3,FALSE)))),2)) -> BE | X12: =IF($A12="","",IF(ISERROR(VLOOKUP(LEFT('1) Import fichier Remi (coller)'!$A12,9),'Concordance client liv et fact'!$A:$H,8,FALSE))=TRUE,VLOOKUP(LEFT('1) Import fichier Remi (coller)'!$A12,9)+0,'Clients R2'!$A:$CY,102,FALSE),VLOOKUP(VLOOKUP(LEFT('1) Import fichier Remi (coller)'!$A12,9),'Concordance client liv et fact'!$A:$H,7,FALSE)+0,'Clients R2'!$A:$CY,102,FALSE))) -> info@delhez-combustibles.be | Y12: CF11261601.PDF | Z12: GDUHOUX | AA12: =IF($A12="VE11","",IF(LEFT($H12,4)="7050","",IF('1) Import fichier Remi (coller)'!M12="","",'1) Import fichier Remi (coller)'!M12))) | AB12: =IF($A12="VE11","",IF(LEFT($H12,4)="7050","",IF('1) Import fichier Remi (coller)'!N12="","",'1) Import fichier Remi (coller)'!N12))) | AC12: =IF(A12="","",VLOOKUP(LEFT('1) Import fichier Remi (coller)'!A12,9)+0,'Concordance Client R2 BOB'!$B:$C,2,FALSE)) -> DEL003
A13: =IF('1) Import fichier Remi (coller)'!D13="","",'1) Import fichier Remi (coller)'!D13) -> VE11 | B13: =IF(A13="","",YEAR('1) Import fichier Remi (coller)'!F13)) -> 2026 | C13: =IF(A13="","",MONTH('1) Import fichier Remi (coller)'!F13)) -> 9 | D13: =IF(A13="","",'1) Import fichier Remi (coller)'!F13) -> 46281 | E13: =IF(A13="","",'1) Import fichier Remi (coller)'!G13) -> 46281 | F13: =IF(A13="","",'1) Import fichier Remi (coller)'!E13) -> 11261515 | G13: =IF(A13="","",IF(ISERROR(VLOOKUP(LEFT('1) Import fichier Remi (coller)'!A13,9),'Concordance client liv et fact'!$A:$H,8,FALSE))=TRUE,'1) Import fichier Remi (coller)'!B13,VLOOKUP(LEFT('1) Import fichier Remi (coller)'!A13,9),'Concordance client liv et fact'!$A:$H,8,FALSE))) -> EUROBOIS | H13: =IF(A13="","",IF(ISERROR(VLOOKUP('1) Import fichier Remi (coller)'!K13&" - "&'1) Import fichier Remi (coller)'!L13,'Spécifique comptes'!$A:$G,1,FALSE))=TRUE,'1) Import fichier Remi (coller)'!V13,VLOOKUP('1) Import fichier Remi (coller)'!K13&" - "&'1) Import fichier Remi (coller)'!L13,'Spécifique comptes'!$A:$G,IF(LEFT('2) BOB compta (completer-forcer'!F13,2)="11",4,IF(LEFT('2) BOB compta (completer-forcer'!F13,2)="12",5,IF(LEFT('2) BOB compta (completer-forcer'!F13,2)="13",6,IF(LEFT('2) BOB compta (completer-forcer'!F13,2)="15",7,"Erreur Compte")))),FALSE))) -> 705099999 | I13: =IF(A13="","",IF(H13="70100000",'1) Import fichier Remi (coller)'!J13,'1) Import fichier Remi (coller)'!U13)) -> +++003/7261/51532+++ | J13: =IF(A13="","",'1) Import fichier Remi (coller)'!U13) -> +++003/7261/51532+++ | K13: =IF(A13="","",SUMIFS(N:N,A:A,A13,F:F,F13)+SUMIFS(O:O,A:A,A13,F:F,F13)) -> 28.74 | L13: =IF(A13="","",IF(LEFT(T13,1)="B","V","PRT")) -> V | M13: =IF(A13="","",'1) Import fichier Remi (coller)'!S13) -> 21 | N13: =IF($A13="","",IF(OR($A13="NCV",$A13="NC15"),-'1) Import fichier Remi (coller)'!R13,'1) Import fichier Remi (coller)'!R13)) -> 23.75 | O13: =IF($A13="","",IF(OR($A13="NCV",$A13="NC15"),-'1) Import fichier Remi (coller)'!T13,'1) Import fichier Remi (coller)'!T13)) -> 4.99 | R13: =IF($A13="","",IF(ISERROR(VLOOKUP(LEFT('1) Import fichier Remi (coller)'!$A13,9),'Concordance client liv et fact'!$A:$H,8,FALSE))=TRUE,VLOOKUP(LEFT('1) Import fichier Remi (coller)'!$A13,9)+0,'Clients R2'!$A:$CY,2,FALSE),VLOOKUP(VLOOKUP(LEFT('1) Import fichier Remi (coller)'!$A13,9),'Concordance client liv et fact'!$A:$H,7,FALSE)+0,'Clients R2'!$A:$CY,2,FALSE))) -> EUROBOIS SA | S13: =IF($A13="","",PROPER(IF(ISERROR(VLOOKUP(LEFT('1) Import fichier Remi (coller)'!$A13,9),'Concordance client liv et fact'!$A:$H,8,FALSE))=TRUE,VLOOKUP(LEFT('1) Import fichier Remi (coller)'!$A13,9)+0,'Clients R2'!$A:$CY,27,FALSE),VLOOKUP(VLOOKUP(LEFT('1) Import fichier Remi (coller)'!$A13,9),'Concordance client liv et fact'!$A:$H,7,FALSE)+0,'Clients R2'!$A:$CY,27,FALSE)))) -> Prolongement Rue De L'Abbaye 30 | T13: =IF($A13="","",LEFT(UPPER(IF(ISERROR(VLOOKUP(LEFT('1) Import fichier Remi (coller)'!$A13,9),'Concordance client liv et fact'!$A:$H,8,FALSE))=TRUE,VLOOKUP(LEFT('1) Import fichier Remi (coller)'!$A13,9)+0,'Clients R2'!$A:$CY,28,FALSE),VLOOKUP(VLOOKUP(LEFT('1) Import fichier Remi (coller)'!$A13,9),'Concordance client liv et fact'!$A:$H,7,FALSE)+0,'Clients R2'!$A:$CY,28,FALSE))),2)&UPPER(IF(ISERROR(VLOOKUP(LEFT('1) Import fichier Remi (coller)'!$A13,9),'Concordance client liv et fact'!$A:$H,8,FALSE))=TRUE,VLOOKUP(LEFT('1) Import fichier Remi (coller)'!$A13,9)+0,'Clients R2'!$A:$CY,29,FALSE),VLOOKUP(VLOOKUP(LEFT('1) Import fichier Remi (coller)'!$A13,9),'Concordance client liv et fact'!$A:$H,7,FALSE)+0,'Clients R2'!$A:$CY,29,FALSE)))) -> B 4040 | U13: =IF($A13="","",PROPER(IF(ISERROR(VLOOKUP(LEFT('1) Import fichier Remi (coller)'!$A13,9),'Concordance client liv et fact'!$A:$H,8,FALSE))=TRUE,VLOOKUP(LEFT('1) Import fichier Remi (coller)'!$A13,9)+0,'Clients R2'!$A:$CY,30,FALSE),VLOOKUP(VLOOKUP(LEFT('1) Import fichier Remi (coller)'!$A13,9),'Concordance client liv et fact'!$A:$H,7,FALSE)+0,'Clients R2'!$A:$CY,30,FALSE)))) -> Herstal | V13: =IF($A13="","",LEFT(UPPER(IF(ISERROR(VLOOKUP(LEFT('1) Import fichier Remi (coller)'!$A13,9),'Concordance client liv et fact'!$A:$H,8,FALSE))=TRUE,IF(VLOOKUP(LEFT('1) Import fichier Remi (coller)'!$A13,9)+0,'Clients R2'!$A:$CY,22,FALSE)=4,"NA",VLOOKUP(LEFT('1) Import fichier Remi (coller)'!$A13,9)+0,'Clients R2'!$A:$CY,3,FALSE)),IF(VLOOKUP(VLOOKUP(LEFT('1) Import fichier Remi (coller)'!$A13,9),'Concordance client liv et fact'!$A:$H,7,FALSE)+0,'Clients R2'!$A:$CY,22,FALSE)=4,"NA",VLOOKUP(VLOOKUP(LEFT('1) Import fichier Remi (coller)'!$A13,9),'Concordance client liv et fact'!$A:$H,7,FALSE)+0,'Clients R2'!$A:$CY,3,FALSE)))),2)) -> BE | X13: =IF($A13="","",IF(ISERROR(VLOOKUP(LEFT('1) Import fichier Remi (coller)'!$A13,9),'Concordance client liv et fact'!$A:$H,8,FALSE))=TRUE,VLOOKUP(LEFT('1) Import fichier Remi (coller)'!$A13,9)+0,'Clients R2'!$A:$CY,102,FALSE),VLOOKUP(VLOOKUP(LEFT('1) Import fichier Remi (coller)'!$A13,9),'Concordance client liv et fact'!$A:$H,7,FALSE)+0,'Clients R2'!$A:$CY,102,FALSE))) -> eurobois@skynet.be | Y13: CF11261601.PDF | Z13: =IF(A13="","",IF(OR(H13="705099999",H13="705001002"),VLOOKUP('1) Import fichier Remi (coller)'!J13,'Analytique personnel'!$A:$B,2,FALSE),"")) -> GDUHOUX | AA13: =IF($A13="VE11","",IF(LEFT($H13,4)="7050","",IF('1) Import fichier Remi (coller)'!M13="","",'1) Import fichier Remi (coller)'!M13))) | AB13: =IF($A13="VE11","",IF(LEFT($H13,4)="7050","",IF('1) Import fichier Remi (coller)'!N13="","",'1) Import fichier Remi (coller)'!N13))) | AC13: =IF(A13="","",VLOOKUP(LEFT('1) Import fichier Remi (coller)'!A13,9)+0,'Concordance Client R2 BOB'!$B:$C,2,FALSE)) -> EUROBOIS
A14: =IF('1) Import fichier Remi (coller)'!D14="","",'1) Import fichier Remi (coller)'!D14) -> VE11 | B14: =IF(A14="","",YEAR('1) Import fichier Remi (coller)'!F14)) -> 2026 | C14: =IF(A14="","",MONTH('1) Import fichier Remi (coller)'!F14)) -> 9 | D14: =IF(A14="","",'1) Import fichier Remi (coller)'!F14) -> 46281 | E14: =IF(A14="","",'1) Import fichier Remi (coller)'!G14) -> 46311 | F14: =IF(A14="","",'1) Import fichier Remi (coller)'!E14) -> 11261516 | G14: =IF(A14="","",IF(ISERROR(VLOOKUP(LEFT('1) Import fichier Remi (coller)'!A14,9),'Concordance client liv et fact'!$A:$H,8,FALSE))=TRUE,'1) Import fichier Remi (coller)'!B14,VLOOKUP(LEFT('1) Import fichier Remi (coller)'!A14,9),'Concordance client liv et fact'!$A:$H,8,FALSE))) -> UPI000 | H14: =IF(A14="","",IF(ISERROR(VLOOKUP('1) Import fichier Remi (coller)'!K14&" - "&'1) Import fichier Remi (coller)'!L14,'Spécifique comptes'!$A:$G,1,FALSE))=TRUE,'1) Import fichier Remi (coller)'!V14,VLOOKUP('1) Import fichier Remi (coller)'!K14&" - "&'1) Import fichier Remi (coller)'!L14,'Spécifique comptes'!$A:$G,IF(LEFT('2) BOB compta (completer-forcer'!F14,2)="11",4,IF(LEFT('2) BOB compta (completer-forcer'!F14,2)="12",5,IF(LEFT('2) BOB compta (completer-forcer'!F14,2)="13",6,IF(LEFT('2) BOB compta (completer-forcer'!F14,2)="15",7,"Erreur Compte")))),FALSE))) -> 704119000 | I14: =IF(A14="","",IF(H14="70100000",'1) Import fichier Remi (coller)'!J14,'1) Import fichier Remi (coller)'!U14)) -> +++003/7261/51633+++ | J14: =IF(A14="","",'1) Import fichier Remi (coller)'!U14) -> +++003/7261/51633+++ | K14: =IF(A14="","",SUMIFS(N:N,A:A,A14,F:F,F14)+SUMIFS(O:O,A:A,A14,F:F,F14)) -> 72.6 | L14: =IF(A14="","",IF(LEFT(T14,1)="B","V","PRT")) -> V | M14: =IF(A14="","",'1) Import fichier Remi (coller)'!S14) -> 21 | N14: =IF($A14="","",IF(OR($A14="NCV",$A14="NC15"),-'1) Import fichier Remi (coller)'!R14,'1) Import fichier Remi (coller)'!R14)) -> 60 | O14: =IF($A14="","",IF(OR($A14="NCV",$A14="NC15"),-'1) Import fichier Remi (coller)'!T14,'1) Import fichier Remi (coller)'!T14)) -> 12.6 | R14: =IF($A14="","",IF(ISERROR(VLOOKUP(LEFT('1) Import fichier Remi (coller)'!$A14,9),'Concordance client liv et fact'!$A:$H,8,FALSE))=TRUE,VLOOKUP(LEFT('1) Import fichier Remi (coller)'!$A14,9)+0,'Clients R2'!$A:$CY,2,FALSE),VLOOKUP(VLOOKUP(LEFT('1) Import fichier Remi (coller)'!$A14,9),'Concordance client liv et fact'!$A:$H,7,FALSE)+0,'Clients R2'!$A:$CY,2,FALSE))) -> UPIGNAC SA | S14: =IF($A14="","",PROPER(IF(ISERROR(VLOOKUP(LEFT('1) Import fichier Remi (coller)'!$A14,9),'Concordance client liv et fact'!$A:$H,8,FALSE))=TRUE,VLOOKUP(LEFT('1) Import fichier Remi (coller)'!$A14,9)+0,'Clients R2'!$A:$CY,27,FALSE),VLOOKUP(VLOOKUP(LEFT('1) Import fichier Remi (coller)'!$A14,9),'Concordance client liv et fact'!$A:$H,7,FALSE)+0,'Clients R2'!$A:$CY,27,FALSE)))) -> Rue De Frise 97 | T14: =IF($A14="","",LEFT(UPPER(IF(ISERROR(VLOOKUP(LEFT('1) Import fichier Remi (coller)'!$A14,9),'Concordance client liv et fact'!$A:$H,8,FALSE))=TRUE,VLOOKUP(LEFT('1) Import fichier Remi (coller)'!$A14,9)+0,'Clients R2'!$A:$CY,28,FALSE),VLOOKUP(VLOOKUP(LEFT('1) Import fichier Remi (coller)'!$A14,9),'Concordance client liv et fact'!$A:$H,7,FALSE)+0,'Clients R2'!$A:$CY,28,FALSE))),2)&UPPER(IF(ISERROR(VLOOKUP(LEFT('1) Import fichier Remi (coller)'!$A14,9),'Concordance client liv et fact'!$A:$H,8,FALSE))=TRUE,VLOOKUP(LEFT('1) Import fichier Remi (coller)'!$A14,9)+0,'Clients R2'!$A:$CY,29,FALSE),VLOOKUP(VLOOKUP(LEFT('1) Import fichier Remi (coller)'!$A14,9),'Concordance client liv et fact'!$A:$H,7,FALSE)+0,'Clients R2'!$A:$CY,29,FALSE)))) -> B 5310 | U14: =IF($A14="","",PROPER(IF(ISERROR(VLOOKUP(LEFT('1) Import fichier Remi (coller)'!$A14,9),'Concordance client liv et fact'!$A:$H,8,FALSE))=TRUE,VLOOKUP(LEFT('1) Import fichier Remi (coller)'!$A14,9)+0,'Clients R2'!$A:$CY,30,FALSE),VLOOKUP(VLOOKUP(LEFT('1) Import fichier Remi (coller)'!$A14,9),'Concordance client liv et fact'!$A:$H,7,FALSE)+0,'Clients R2'!$A:$CY,30,FALSE)))) -> Upigny | V14: =IF($A14="","",LEFT(UPPER(IF(ISERROR(VLOOKUP(LEFT('1) Import fichier Remi (coller)'!$A14,9),'Concordance client liv et fact'!$A:$H,8,FALSE))=TRUE,IF(VLOOKUP(LEFT('1) Import fichier Remi (coller)'!$A14,9)+0,'Clients R2'!$A:$CY,22,FALSE)=4,"NA",VLOOKUP(LEFT('1) Import fichier Remi (coller)'!$A14,9)+0,'Clients R2'!$A:$CY,3,FALSE)),IF(VLOOKUP(VLOOKUP(LEFT('1) Import fichier Remi (coller)'!$A14,9),'Concordance client liv et fact'!$A:$H,7,FALSE)+0,'Clients R2'!$A:$CY,22,FALSE)=4,"NA",VLOOKUP(VLOOKUP(LEFT('1) Import fichier Remi (coller)'!$A14,9),'Concordance client liv et fact'!$A:$H,7,FALSE)+0,'Clients R2'!$A:$CY,3,FALSE)))),2)) -> BE | X14: =IF($A14="","",IF(ISERROR(VLOOKUP(LEFT('1) Import fichier Remi (coller)'!$A14,9),'Concordance client liv et fact'!$A:$H,8,FALSE))=TRUE,VLOOKUP(LEFT('1) Import fichier Remi (coller)'!$A14,9)+0,'Clients R2'!$A:$CY,102,FALSE),VLOOKUP(VLOOKUP(LEFT('1) Import fichier Remi (coller)'!$A14,9),'Concordance client liv et fact'!$A:$H,7,FALSE)+0,'Clients R2'!$A:$CY,102,FALSE))) -> ap@upignac.be | Y14: CF11261601.PDF | Z14: =IF(A14="","",IF(OR(H14="705099999",H14="705001002"),VLOOKUP('1) Import fichier Remi (coller)'!J14,'Analytique personnel'!$A:$B,2,FALSE),"")) | AA14: =IF($A14="VE11","",IF(LEFT($H14,4)="7050","",IF('1) Import fichier Remi (coller)'!M14="","",'1) Import fichier Remi (coller)'!M14))) | AB14: =IF($A14="VE11","",IF(LEFT($H14,4)="7050","",IF('1) Import fichier Remi (coller)'!N14="","",'1) Import fichier Remi (coller)'!N14))) | AC14: =IF(A14="","",VLOOKUP(LEFT('1) Import fichier Remi (coller)'!A14,9)+0,'Concordance Client R2 BOB'!$B:$C,2,FALSE)) -> UPI000
A15: =IF('1) Import fichier Remi (coller)'!D15="","",'1) Import fichier Remi (coller)'!D15) -> VE11 | B15: =IF(A15="","",YEAR('1) Import fichier Remi (coller)'!F15)) -> 2026 | C15: =IF(A15="","",MONTH('1) Import fichier Remi (coller)'!F15)) -> 9 | D15: =IF(A15="","",'1) Import fichier Remi (coller)'!F15) -> 46281 | E15: =IF(A15="","",'1) Import fichier Remi (coller)'!G15) -> 46281 | F15: =IF(A15="","",'1) Import fichier Remi (coller)'!E15) -> 11261517 | G15: =IF(A15="","",IF(ISERROR(VLOOKUP(LEFT('1) Import fichier Remi (coller)'!A15,9),'Concordance client liv et fact'!$A:$H,8,FALSE))=TRUE,'1) Import fichier Remi (coller)'!B15,VLOOKUP(LEFT('1) Import fichier Remi (coller)'!A15,9),'Concordance client liv et fact'!$A:$H,8,FALSE))) -> COFIDENA | H15: =IF(A15="","",IF(ISERROR(VLOOKUP('1) Import fichier Remi (coller)'!K15&" - "&'1) Import fichier Remi (coller)'!L15,'Spécifique comptes'!$A:$G,1,FALSE))=TRUE,'1) Import fichier Remi (coller)'!V15,VLOOKUP('1) Import fichier Remi (coller)'!K15&" - "&'1) Import fichier Remi (coller)'!L15,'Spécifique comptes'!$A:$G,IF(LEFT('2) BOB compta (completer-forcer'!F15,2)="11",4,IF(LEFT('2) BOB compta (completer-forcer'!F15,2)="12",5,IF(LEFT('2) BOB compta (completer-forcer'!F15,2)="13",6,IF(LEFT('2) BOB compta (completer-forcer'!F15,2)="15",7,"Erreur Compte")))),FALSE))) -> 705099999 | I15: =IF(A15="","",IF(H15="70100000",'1) Import fichier Remi (coller)'!J15,'1) Import fichier Remi (coller)'!U15)) -> +++003/7261/51734+++ | J15: =IF(A15="","",'1) Import fichier Remi (coller)'!U15) -> +++003/7261/51734+++ | K15: =IF(A15="","",SUMIFS(N:N,A:A,A15,F:F,F15)+SUMIFS(O:O,A:A,A15,F:F,F15)) -> 86.21 | L15: =IF(A15="","",IF(LEFT(T15,1)="B","V","PRT")) -> V | M15: =IF(A15="","",'1) Import fichier Remi (coller)'!S15) -> 21 | N15: =IF($A15="","",IF(OR($A15="NCV",$A15="NC15"),-'1) Import fichier Remi (coller)'!R15,'1) Import fichier Remi (coller)'!R15)) -> 23.75 | O15: =IF($A15="","",IF(OR($A15="NCV",$A15="NC15"),-'1) Import fichier Remi (coller)'!T15,'1) Import fichier Remi (coller)'!T15)) -> 4.99 | R15: =IF($A15="","",IF(ISERROR(VLOOKUP(LEFT('1) Import fichier Remi (coller)'!$A15,9),'Concordance client liv et fact'!$A:$H,8,FALSE))=TRUE,VLOOKUP(LEFT('1) Import fichier Remi (coller)'!$A15,9)+0,'Clients R2'!$A:$CY,2,FALSE),VLOOKUP(VLOOKUP(LEFT('1) Import fichier Remi (coller)'!$A15,9),'Concordance client liv et fact'!$A:$H,7,FALSE)+0,'Clients R2'!$A:$CY,2,FALSE))) -> COFIDENA SPRL | S15: =IF($A15="","",PROPER(IF(ISERROR(VLOOKUP(LEFT('1) Import fichier Remi (coller)'!$A15,9),'Concordance client liv et fact'!$A:$H,8,FALSE))=TRUE,VLOOKUP(LEFT('1) Import fichier Remi (coller)'!$A15,9)+0,'Clients R2'!$A:$CY,27,FALSE),VLOOKUP(VLOOKUP(LEFT('1) Import fichier Remi (coller)'!$A15,9),'Concordance client liv et fact'!$A:$H,7,FALSE)+0,'Clients R2'!$A:$CY,27,FALSE)))) -> Allee Des Mesanges, 3 | T15: =IF($A15="","",LEFT(UPPER(IF(ISERROR(VLOOKUP(LEFT('1) Import fichier Remi (coller)'!$A15,9),'Concordance client liv et fact'!$A:$H,8,FALSE))=TRUE,VLOOKUP(LEFT('1) Import fichier Remi (coller)'!$A15,9)+0,'Clients R2'!$A:$CY,28,FALSE),VLOOKUP(VLOOKUP(LEFT('1) Import fichier Remi (coller)'!$A15,9),'Concordance client liv et fact'!$A:$H,7,FALSE)+0,'Clients R2'!$A:$CY,28,FALSE))),2)&UPPER(IF(ISERROR(VLOOKUP(LEFT('1) Import fichier Remi (coller)'!$A15,9),'Concordance client liv et fact'!$A:$H,8,FALSE))=TRUE,VLOOKUP(LEFT('1) Import fichier Remi (coller)'!$A15,9)+0,'Clients R2'!$A:$CY,29,FALSE),VLOOKUP(VLOOKUP(LEFT('1) Import fichier Remi (coller)'!$A15,9),'Concordance client liv et fact'!$A:$H,7,FALSE)+0,'Clients R2'!$A:$CY,29,FALSE)))) -> B 4600 | U15: =IF($A15="","",PROPER(IF(ISERROR(VLOOKUP(LEFT('1) Import fichier Remi (coller)'!$A15,9),'Concordance client liv et fact'!$A:$H,8,FALSE))=TRUE,VLOOKUP(LEFT('1) Import fichier Remi (coller)'!$A15,9)+0,'Clients R2'!$A:$CY,30,FALSE),VLOOKUP(VLOOKUP(LEFT('1) Import fichier Remi (coller)'!$A15,9),'Concordance client liv et fact'!$A:$H,7,FALSE)+0,'Clients R2'!$A:$CY,30,FALSE)))) -> Vise | V15: =IF($A15="","",LEFT(UPPER(IF(ISERROR(VLOOKUP(LEFT('1) Import fichier Remi (coller)'!$A15,9),'Concordance client liv et fact'!$A:$H,8,FALSE))=TRUE,IF(VLOOKUP(LEFT('1) Import fichier Remi (coller)'!$A15,9)+0,'Clients R2'!$A:$CY,22,FALSE)=4,"NA",VLOOKUP(LEFT('1) Import fichier Remi (coller)'!$A15,9)+0,'Clients R2'!$A:$CY,3,FALSE)),IF(VLOOKUP(VLOOKUP(LEFT('1) Import fichier Remi (coller)'!$A15,9),'Concordance client liv et fact'!$A:$H,7,FALSE)+0,'Clients R2'!$A:$CY,22,FALSE)=4,"NA",VLOOKUP(VLOOKUP(LEFT('1) Import fichier Remi (coller)'!$A15,9),'Concordance client liv et fact'!$A:$H,7,FALSE)+0,'Clients R2'!$A:$CY,3,FALSE)))),2)) -> BE | X15: =IF($A15="","",IF(ISERROR(VLOOKUP(LEFT('1) Import fichier Remi (coller)'!$A15,9),'Concordance client liv et fact'!$A:$H,8,FALSE))=TRUE,VLOOKUP(LEFT('1) Import fichier Remi (coller)'!$A15,9)+0,'Clients R2'!$A:$CY,102,FALSE),VLOOKUP(VLOOKUP(LEFT('1) Import fichier Remi (coller)'!$A15,9),'Concordance client liv et fact'!$A:$H,7,FALSE)+0,'Clients R2'!$A:$CY,102,FALSE))) -> cofidena@skynet.be | Y15: CF11261601.PDF | Z15: =IF(A15="","",IF(OR(H15="705099999",H15="705001002"),VLOOKUP('1) Import fichier Remi (coller)'!J15,'Analytique personnel'!$A:$B,2,FALSE),"")) -> GDUHOUX | AA15: =IF($A15="VE11","",IF(LEFT($H15,4)="7050","",IF('1) Import fichier Remi (coller)'!M15="","",'1) Import fichier Remi (coller)'!M15))) | AB15: =IF($A15="VE11","",IF(LEFT($H15,4)="7050","",IF('1) Import fichier Remi (coller)'!N15="","",'1) Import fichier Remi (coller)'!N15))) | AC15: =IF(A15="","",VLOOKUP(LEFT('1) Import fichier Remi (coller)'!A15,9)+0,'Concordance Client R2 BOB'!$B:$C,2,FALSE)) -> COFIDENA
A16: =IF('1) Import fichier Remi (coller)'!D16="","",'1) Import fichier Remi (coller)'!D16) -> VE11 | B16: =IF(A16="","",YEAR('1) Import fichier Remi (coller)'!F16)) -> 2026 | C16: =IF(A16="","",MONTH('1) Import fichier Remi (coller)'!F16)) -> 9 | D16: =IF(A16="","",'1) Import fichier Remi (coller)'!F16) -> 46281 | E16: =IF(A16="","",'1) Import fichier Remi (coller)'!G16) -> 46281 | F16: =IF(A16="","",'1) Import fichier Remi (coller)'!E16) -> 11261517 | G16: =IF(A16="","",IF(ISERROR(VLOOKUP(LEFT('1) Import fichier Remi (coller)'!A16,9),'Concordance client liv et fact'!$A:$H,8,FALSE))=TRUE,'1) Import fichier Remi (coller)'!B16,VLOOKUP(LEFT('1) Import fichier Remi (coller)'!A16,9),'Concordance client liv et fact'!$A:$H,8,FALSE))) -> COFIDENA | H16: =IF(A16="","",IF(ISERROR(VLOOKUP('1) Import fichier Remi (coller)'!K16&" - "&'1) Import fichier Remi (coller)'!L16,'Spécifique comptes'!$A:$G,1,FALSE))=TRUE,'1) Import fichier Remi (coller)'!V16,VLOOKUP('1) Import fichier Remi (coller)'!K16&" - "&'1) Import fichier Remi (coller)'!L16,'Spécifique comptes'!$A:$G,IF(LEFT('2) BOB compta (completer-forcer'!F16,2)="11",4,IF(LEFT('2) BOB compta (completer-forcer'!F16,2)="12",5,IF(LEFT('2) BOB compta (completer-forcer'!F16,2)="13",6,IF(LEFT('2) BOB compta (completer-forcer'!F16,2)="15",7,"Erreur Compte")))),FALSE))) -> 705099999 | I16: =IF(A16="","",IF(H16="70100000",'1) Import fichier Remi (coller)'!J16,'1) Import fichier Remi (coller)'!U16)) -> +++003/7261/51734+++ | J16: =IF(A16="","",'1) Import fichier Remi (coller)'!U16) -> +++003/7261/51734+++ | K16: =IF(A16="","",SUMIFS(N:N,A:A,A16,F:F,F16)+SUMIFS(O:O,A:A,A16,F:F,F16)) -> 86.21 | L16: =IF(A16="","",IF(LEFT(T16,1)="B","V","PRT")) -> V | M16: =IF(A16="","",'1) Import fichier Remi (coller)'!S16) -> 21 | N16: =IF($A16="","",IF(OR($A16="NCV",$A16="NC15"),-'1) Import fichier Remi (coller)'!R16,'1) Import fichier Remi (coller)'!R16)) -> 47.5 | O16: =IF($A16="","",IF(OR($A16="NCV",$A16="NC15"),-'1) Import fichier Remi (coller)'!T16,'1) Import fichier Remi (coller)'!T16)) -> 9.97 | R16: =IF($A16="","",IF(ISERROR(VLOOKUP(LEFT('1) Import fichier Remi (coller)'!$A16,9),'Concordance client liv et fact'!$A:$H,8,FALSE))=TRUE,VLOOKUP(LEFT('1) Import fichier Remi (coller)'!$A16,9)+0,'Clients R2'!$A:$CY,2,FALSE),VLOOKUP(VLOOKUP(LEFT('1) Import fichier Remi (coller)'!$A16,9),'Concordance client liv et fact'!$A:$H,7,FALSE)+0,'Clients R2'!$A:$CY,2,FALSE))) -> COFIDENA SPRL | S16: =IF($A16="","",PROPER(IF(ISERROR(VLOOKUP(LEFT('1) Import fichier Remi (coller)'!$A16,9),'Concordance client liv et fact'!$A:$H,8,FALSE))=TRUE,VLOOKUP(LEFT('1) Import fichier Remi (coller)'!$A16,9)+0,'Clients R2'!$A:$CY,27,FALSE),VLOOKUP(VLOOKUP(LEFT('1) Import fichier Remi (coller)'!$A16,9),'Concordance client liv et fact'!$A:$H,7,FALSE)+0,'Clients R2'!$A:$CY,27,FALSE)))) -> Allee Des Mesanges, 3 | T16: =IF($A16="","",LEFT(UPPER(IF(ISERROR(VLOOKUP(LEFT('1) Import fichier Remi (coller)'!$A16,9),'Concordance client liv et fact'!$A:$H,8,FALSE))=TRUE,VLOOKUP(LEFT('1) Import fichier Remi (coller)'!$A16,9)+0,'Clients R2'!$A:$CY,28,FALSE),VLOOKUP(VLOOKUP(LEFT('1) Import fichier Remi (coller)'!$A16,9),'Concordance client liv et fact'!$A:$H,7,FALSE)+0,'Clients R2'!$A:$CY,28,FALSE))),2)&UPPER(IF(ISERROR(VLOOKUP(LEFT('1) Import fichier Remi (coller)'!$A16,9),'Concordance client liv et fact'!$A:$H,8,FALSE))=TRUE,VLOOKUP(LEFT('1) Import fichier Remi (coller)'!$A16,9)+0,'Clients R2'!$A:$CY,29,FALSE),VLOOKUP(VLOOKUP(LEFT('1) Import fichier Remi (coller)'!$A16,9),'Concordance client liv et fact'!$A:$H,7,FALSE)+0,'Clients R2'!$A:$CY,29,FALSE)))) -> B 4600 | U16: =IF($A16="","",PROPER(IF(ISERROR(VLOOKUP(LEFT('1) Import fichier Remi (coller)'!$A16,9),'Concordance client liv et fact'!$A:$H,8,FALSE))=TRUE,VLOOKUP(LEFT('1) Import fichier Remi (coller)'!$A16,9)+0,'Clients R2'!$A:$CY,30,FALSE),VLOOKUP(VLOOKUP(LEFT('1) Import fichier Remi (coller)'!$A16,9),'Concordance client liv et fact'!$A:$H,7,FALSE)+0,'Clients R2'!$A:$CY,30,FALSE)))) -> Vise | V16: =IF($A16="","",LEFT(UPPER(IF(ISERROR(VLOOKUP(LEFT('1) Import fichier Remi (coller)'!$A16,9),'Concordance client liv et fact'!$A:$H,8,FALSE))=TRUE,IF(VLOOKUP(LEFT('1) Import fichier Remi (coller)'!$A16,9)+0,'Clients R2'!$A:$CY,22,FALSE)=4,"NA",VLOOKUP(LEFT('1) Import fichier Remi (coller)'!$A16,9)+0,'Clients R2'!$A:$CY,3,FALSE)),IF(VLOOKUP(VLOOKUP(LEFT('1) Import fichier Remi (coller)'!$A16,9),'Concordance client liv et fact'!$A:$H,7,FALSE)+0,'Clients R2'!$A:$CY,22,FALSE)=4,"NA",VLOOKUP(VLOOKUP(LEFT('1) Import fichier Remi (coller)'!$A16,9),'Concordance client liv et fact'!$A:$H,7,FALSE)+0,'Clients R2'!$A:$CY,3,FALSE)))),2)) -> BE | X16: =IF($A16="","",IF(ISERROR(VLOOKUP(LEFT('1) Import fichier Remi (coller)'!$A16,9),'Concordance client liv et fact'!$A:$H,8,FALSE))=TRUE,VLOOKUP(LEFT('1) Import fichier Remi (coller)'!$A16,9)+0,'Clients R2'!$A:$CY,102,FALSE),VLOOKUP(VLOOKUP(LEFT('1) Import fichier Remi (coller)'!$A16,9),'Concordance client liv et fact'!$A:$H,7,FALSE)+0,'Clients R2'!$A:$CY,102,FALSE))) -> cofidena@skynet.be | Y16: CF11261601.PDF | Z16: =IF(A16="","",IF(OR(H16="705099999",H16="705001002"),VLOOKUP('1) Import fichier Remi (coller)'!J16,'Analytique personnel'!$A:$B,2,FALSE),"")) -> GDUHOUX | AA16: =IF($A16="VE11","",IF(LEFT($H16,4)="7050","",IF('1) Import fichier Remi (coller)'!M16="","",'1) Import fichier Remi (coller)'!M16))) | AB16: =IF($A16="VE11","",IF(LEFT($H16,4)="7050","",IF('1) Import fichier Remi (coller)'!N16="","",'1) Import fichier Remi (coller)'!N16))) | AC16: =IF(A16="","",VLOOKUP(LEFT('1) Import fichier Remi (coller)'!A16,9)+0,'Concordance Client R2 BOB'!$B:$C,2,FALSE)) -> COFIDENA
A17: =IF('1) Import fichier Remi (coller)'!D17="","",'1) Import fichier Remi (coller)'!D17) -> VE11 | B17: =IF(A17="","",YEAR('1) Import fichier Remi (coller)'!F17)) -> 2026 | C17: =IF(A17="","",MONTH('1) Import fichier Remi (coller)'!F17)) -> 9 | D17: =IF(A17="","",'1) Import fichier Remi (coller)'!F17) -> 46281 | E17: =IF(A17="","",'1) Import fichier Remi (coller)'!G17) -> 46281 | F17: =IF(A17="","",'1) Import fichier Remi (coller)'!E17) -> 11261518 | G17: =IF(A17="","",IF(ISERROR(VLOOKUP(LEFT('1) Import fichier Remi (coller)'!A17,9),'Concordance client liv et fact'!$A:$H,8,FALSE))=TRUE,'1) Import fichier Remi (coller)'!B17,VLOOKUP(LEFT('1) Import fichier Remi (coller)'!A17,9),'Concordance client liv et fact'!$A:$H,8,FALSE))) -> HMC | H17: =IF(A17="","",IF(ISERROR(VLOOKUP('1) Import fichier Remi (coller)'!K17&" - "&'1) Import fichier Remi (coller)'!L17,'Spécifique comptes'!$A:$G,1,FALSE))=TRUE,'1) Import fichier Remi (coller)'!V17,VLOOKUP('1) Import fichier Remi (coller)'!K17&" - "&'1) Import fichier Remi (coller)'!L17,'Spécifique comptes'!$A:$G,IF(LEFT('2) BOB compta (completer-forcer'!F17,2)="11",4,IF(LEFT('2) BOB compta (completer-forcer'!F17,2)="12",5,IF(LEFT('2) BOB compta (completer-forcer'!F17,2)="13",6,IF(LEFT('2) BOB compta (completer-forcer'!F17,2)="15",7,"Erreur Compte")))),FALSE))) -> 705099999 | I17: =IF(A17="","",IF(H17="70100000",'1) Import fichier Remi (coller)'!J17,'1) Import fichier Remi (coller)'!U17)) -> +++003/7261/51835+++ | J17: =IF(A17="","",'1) Import fichier Remi (coller)'!U17) -> +++003/7261/51835+++ | K17: =IF(A17="","",SUMIFS(N:N,A:A,A17,F:F,F17)+SUMIFS(O:O,A:A,A17,F:F,F17)) -> 57.48 | L17: =IF(A17="","",IF(LEFT(T17,1)="B","V","PRT")) -> V | M17: =IF(A17="","",'1) Import fichier Remi (coller)'!S17) -> 21 | N17: =IF($A17="","",IF(OR($A17="NCV",$A17="NC15"),-'1) Import fichier Remi (coller)'!R17,'1) Import fichier Remi (coller)'!R17)) -> 23.75 | O17: =IF($A17="","",IF(OR($A17="NCV",$A17="NC15"),-'1) Import fichier Remi (coller)'!T17,'1) Import fichier Remi (coller)'!T17)) -> 4.99 | R17: =IF($A17="","",IF(ISERROR(VLOOKUP(LEFT('1) Import fichier Remi (coller)'!$A17,9),'Concordance client liv et fact'!$A:$H,8,FALSE))=TRUE,VLOOKUP(LEFT('1) Import fichier Remi (coller)'!$A17,9)+0,'Clients R2'!$A:$CY,2,FALSE),VLOOKUP(VLOOKUP(LEFT('1) Import fichier Remi (coller)'!$A17,9),'Concordance client liv et fact'!$A:$H,7,FALSE)+0,'Clients R2'!$A:$CY,2,FALSE))) -> HMC BELGIUM SPRL | S17: =IF($A17="","",PROPER(IF(ISERROR(VLOOKUP(LEFT('1) Import fichier Remi (coller)'!$A17,9),'Concordance client liv et fact'!$A:$H,8,FALSE))=TRUE,VLOOKUP(LEFT('1) Import fichier Remi (coller)'!$A17,9)+0,'Clients R2'!$A:$CY,27,FALSE),VLOOKUP(VLOOKUP(LEFT('1) Import fichier Remi (coller)'!$A17,9),'Concordance client liv et fact'!$A:$H,7,FALSE)+0,'Clients R2'!$A:$CY,27,FALSE)))) -> Rue De Gaillarmont, 95 | T17: =IF($A17="","",LEFT(UPPER(IF(ISERROR(VLOOKUP(LEFT('1) Import fichier Remi (coller)'!$A17,9),'Concordance client liv et fact'!$A:$H,8,FALSE))=TRUE,VLOOKUP(LEFT('1) Import fichier Remi (coller)'!$A17,9)+0,'Clients R2'!$A:$CY,28,FALSE),VLOOKUP(VLOOKUP(LEFT('1) Import fichier Remi (coller)'!$A17,9),'Concordance client liv et fact'!$A:$H,7,FALSE)+0,'Clients R2'!$A:$CY,28,FALSE))),2)&UPPER(IF(ISERROR(VLOOKUP(LEFT('1) Import fichier Remi (coller)'!$A17,9),'Concordance client liv et fact'!$A:$H,8,FALSE))=TRUE,VLOOKUP(LEFT('1) Import fichier Remi (coller)'!$A17,9)+0,'Clients R2'!$A:$CY,29,FALSE),VLOOKUP(VLOOKUP(LEFT('1) Import fichier Remi (coller)'!$A17,9),'Concordance client liv et fact'!$A:$H,7,FALSE)+0,'Clients R2'!$A:$CY,29,FALSE)))) -> B 4032 | U17: =IF($A17="","",PROPER(IF(ISERROR(VLOOKUP(LEFT('1) Import fichier Remi (coller)'!$A17,9),'Concordance client liv et fact'!$A:$H,8,FALSE))=TRUE,VLOOKUP(LEFT('1) Import fichier Remi (coller)'!$A17,9)+0,'Clients R2'!$A:$CY,30,FALSE),VLOOKUP(VLOOKUP(LEFT('1) Import fichier Remi (coller)'!$A17,9),'Concordance client liv et fact'!$A:$H,7,FALSE)+0,'Clients R2'!$A:$CY,30,FALSE)))) -> Liege | V17: =IF($A17="","",LEFT(UPPER(IF(ISERROR(VLOOKUP(LEFT('1) Import fichier Remi (coller)'!$A17,9),'Concordance client liv et fact'!$A:$H,8,FALSE))=TRUE,IF(VLOOKUP(LEFT('1) Import fichier Remi (coller)'!$A17,9)+0,'Clients R2'!$A:$CY,22,FALSE)=4,"NA",VLOOKUP(LEFT('1) Import fichier Remi (coller)'!$A17,9)+0,'Clients R2'!$A:$CY,3,FALSE)),IF(VLOOKUP(VLOOKUP(LEFT('1) Import fichier Remi (coller)'!$A17,9),'Concordance client liv et fact'!$A:$H,7,FALSE)+0,'Clients R2'!$A:$CY,22,FALSE)=4,"NA",VLOOKUP(VLOOKUP(LEFT('1) Import fichier Remi (coller)'!$A17,9),'Concordance client liv et fact'!$A:$H,7,FALSE)+0,'Clients R2'!$A:$CY,3,FALSE)))),2)) -> BE | X17: =IF($A17="","",IF(ISERROR(VLOOKUP(LEFT('1) Import fichier Remi (coller)'!$A17,9),'Concordance client liv et fact'!$A:$H,8,FALSE))=TRUE,VLOOKUP(LEFT('1) Import fichier Remi (coller)'!$A17,9)+0,'Clients R2'!$A:$CY,102,FALSE),VLOOKUP(VLOOKUP(LEFT('1) Import fichier Remi (coller)'!$A17,9),'Concordance client liv et fact'!$A:$H,7,FALSE)+0,'Clients R2'!$A:$CY,102,FALSE))) -> direction@hmcbelgium.com | Y17: CF11261601.PDF | Z17: =IF(A17="","",IF(OR(H17="705099999",H17="705001002"),VLOOKUP('1) Import fichier Remi (coller)'!J17,'Analytique personnel'!$A:$B,2,FALSE),"")) -> GDUHOUX | AA17: =IF($A17="VE11","",IF(LEFT($H17,4)="7050","",IF('1) Import fichier Remi (coller)'!M17="","",'1) Import fichier Remi (coller)'!M17))) | AB17: =IF($A17="VE11","",IF(LEFT($H17,4)="7050","",IF('1) Import fichier Remi (coller)'!N17="","",'1) Import fichier Remi (coller)'!N17))) | AC17: =IF(A17="","",VLOOKUP(LEFT('1) Import fichier Remi (coller)'!A17,9)+0,'Concordance Client R2 BOB'!$B:$C,2,FALSE)) -> HMC
A18: =IF('1) Import fichier Remi (coller)'!D18="","",'1) Import fichier Remi (coller)'!D18) -> VE11 | B18: =IF(A18="","",YEAR('1) Import fichier Remi (coller)'!F18)) -> 2026 | C18: =IF(A18="","",MONTH('1) Import fichier Remi (coller)'!F18)) -> 9 | D18: =IF(A18="","",'1) Import fichier Remi (coller)'!F18) -> 46281 | E18: =IF(A18="","",'1) Import fichier Remi (coller)'!G18) -> 46281 | F18: =IF(A18="","",'1) Import fichier Remi (coller)'!E18) -> 11261518 | G18: =IF(A18="","",IF(ISERROR(VLOOKUP(LEFT('1) Import fichier Remi (coller)'!A18,9),'Concordance client liv et fact'!$A:$H,8,FALSE))=TRUE,'1) Import fichier Remi (coller)'!B18,VLOOKUP(LEFT('1) Import fichier Remi (coller)'!A18,9),'Concordance client liv et fact'!$A:$H,8,FALSE))) -> HMC | H18: =IF(A18="","",IF(ISERROR(VLOOKUP('1) Import fichier Remi (coller)'!K18&" - "&'1) Import fichier Remi (coller)'!L18,'Spécifique comptes'!$A:$G,1,FALSE))=TRUE,'1) Import fichier Remi (coller)'!V18,VLOOKUP('1) Import fichier Remi (coller)'!K18&" - "&'1) Import fichier Remi (coller)'!L18,'Spécifique comptes'!$A:$G,IF(LEFT('2) BOB compta (completer-forcer'!F18,2)="11",4,IF(LEFT('2) BOB compta (completer-forcer'!F18,2)="12",5,IF(LEFT('2) BOB compta (completer-forcer'!F18,2)="13",6,IF(LEFT('2) BOB compta (completer-forcer'!F18,2)="15",7,"Erreur Compte")))),FALSE))) -> 705099999 | I18: =IF(A18="","",IF(H18="70100000",'1) Import fichier Remi (coller)'!J18,'1) Import fichier Remi (coller)'!U18)) -> +++003/7261/51835+++ | J18: =IF(A18="","",'1) Import fichier Remi (coller)'!U18) -> +++003/7261/51835+++ | K18: =IF(A18="","",SUMIFS(N:N,A:A,A18,F:F,F18)+SUMIFS(O:O,A:A,A18,F:F,F18)) -> 57.48 | L18: =IF(A18="","",IF(LEFT(T18,1)="B","V","PRT")) -> V | M18: =IF(A18="","",'1) Import fichier Remi (coller)'!S18) -> 21 | N18: =IF($A18="","",IF(OR($A18="NCV",$A18="NC15"),-'1) Import fichier Remi (coller)'!R18,'1) Import fichier Remi (coller)'!R18)) -> 23.75 | O18: =IF($A18="","",IF(OR($A18="NCV",$A18="NC15"),-'1) Import fichier Remi (coller)'!T18,'1) Import fichier Remi (coller)'!T18)) -> 4.99 | R18: =IF($A18="","",IF(ISERROR(VLOOKUP(LEFT('1) Import fichier Remi (coller)'!$A18,9),'Concordance client liv et fact'!$A:$H,8,FALSE))=TRUE,VLOOKUP(LEFT('1) Import fichier Remi (coller)'!$A18,9)+0,'Clients R2'!$A:$CY,2,FALSE),VLOOKUP(VLOOKUP(LEFT('1) Import fichier Remi (coller)'!$A18,9),'Concordance client liv et fact'!$A:$H,7,FALSE)+0,'Clients R2'!$A:$CY,2,FALSE))) -> HMC BELGIUM SPRL | S18: =IF($A18="","",PROPER(IF(ISERROR(VLOOKUP(LEFT('1) Import fichier Remi (coller)'!$A18,9),'Concordance client liv et fact'!$A:$H,8,FALSE))=TRUE,VLOOKUP(LEFT('1) Import fichier Remi (coller)'!$A18,9)+0,'Clients R2'!$A:$CY,27,FALSE),VLOOKUP(VLOOKUP(LEFT('1) Import fichier Remi (coller)'!$A18,9),'Concordance client liv et fact'!$A:$H,7,FALSE)+0,'Clients R2'!$A:$CY,27,FALSE)))) -> Rue De Gaillarmont, 95 | T18: =IF($A18="","",LEFT(UPPER(IF(ISERROR(VLOOKUP(LEFT('1) Import fichier Remi (coller)'!$A18,9),'Concordance client liv et fact'!$A:$H,8,FALSE))=TRUE,VLOOKUP(LEFT('1) Import fichier Remi (coller)'!$A18,9)+0,'Clients R2'!$A:$CY,28,FALSE),VLOOKUP(VLOOKUP(LEFT('1) Import fichier Remi (coller)'!$A18,9),'Concordance client liv et fact'!$A:$H,7,FALSE)+0,'Clients R2'!$A:$CY,28,FALSE))),2)&UPPER(IF(ISERROR(VLOOKUP(LEFT('1) Import fichier Remi (coller)'!$A18,9),'Concordance client liv et fact'!$A:$H,8,FALSE))=TRUE,VLOOKUP(LEFT('1) Import fichier Remi (coller)'!$A18,9)+0,'Clients R2'!$A:$CY,29,FALSE),VLOOKUP(VLOOKUP(LEFT('1) Import fichier Remi (coller)'!$A18,9),'Concordance client liv et fact'!$A:$H,7,FALSE)+0,'Clients R2'!$A:$CY,29,FALSE)))) -> B 4032 | U18: =IF($A18="","",PROPER(IF(ISERROR(VLOOKUP(LEFT('1) Import fichier Remi (coller)'!$A18,9),'Concordance client liv et fact'!$A:$H,8,FALSE))=TRUE,VLOOKUP(LEFT('1) Import fichier Remi (coller)'!$A18,9)+0,'Clients R2'!$A:$CY,30,FALSE),VLOOKUP(VLOOKUP(LEFT('1) Import fichier Remi (coller)'!$A18,9),'Concordance client liv et fact'!$A:$H,7,FALSE)+0,'Clients R2'!$A:$CY,30,FALSE)))) -> Liege | V18: =IF($A18="","",LEFT(UPPER(IF(ISERROR(VLOOKUP(LEFT('1) Import fichier Remi (coller)'!$A18,9),'Concordance client liv et fact'!$A:$H,8,FALSE))=TRUE,IF(VLOOKUP(LEFT('1) Import fichier Remi (coller)'!$A18,9)+0,'Clients R2'!$A:$CY,22,FALSE)=4,"NA",VLOOKUP(LEFT('1) Import fichier Remi (coller)'!$A18,9)+0,'Clients R2'!$A:$CY,3,FALSE)),IF(VLOOKUP(VLOOKUP(LEFT('1) Import fichier Remi (coller)'!$A18,9),'Concordance client liv et fact'!$A:$H,7,FALSE)+0,'Clients R2'!$A:$CY,22,FALSE)=4,"NA",VLOOKUP(VLOOKUP(LEFT('1) Import fichier Remi (coller)'!$A18,9),'Concordance client liv et fact'!$A:$H,7,FALSE)+0,'Clients R2'!$A:$CY,3,FALSE)))),2)) -> BE | X18: =IF($A18="","",IF(ISERROR(VLOOKUP(LEFT('1) Import fichier Remi (coller)'!$A18,9),'Concordance client liv et fact'!$A:$H,8,FALSE))=TRUE,VLOOKUP(LEFT('1) Import fichier Remi (coller)'!$A18,9)+0,'Clients R2'!$A:$CY,102,FALSE),VLOOKUP(VLOOKUP(LEFT('1) Import fichier Remi (coller)'!$A18,9),'Concordance client liv et fact'!$A:$H,7,FALSE)+0,'Clients R2'!$A:$CY,102,FALSE))) -> direction@hmcbelgium.com | Y18: CF11261601.PDF | Z18: =IF(A18="","",IF(OR(H18="705099999",H18="705001002"),VLOOKUP('1) Import fichier Remi (coller)'!J18,'Analytique personnel'!$A:$B,2,FALSE),"")) -> GDUHOUX | AA18: =IF($A18="VE11","",IF(LEFT($H18,4)="7050","",IF('1) Import fichier Remi (coller)'!M18="","",'1) Import fichier Remi (coller)'!M18))) | AB18: =IF($A18="VE11","",IF(LEFT($H18,4)="7050","",IF('1) Import fichier Remi (coller)'!N18="","",'1) Import fichier Remi (coller)'!N18))) | AC18: =IF(A18="","",VLOOKUP(LEFT('1) Import fichier Remi (coller)'!A18,9)+0,'Concordance Client R2 BOB'!$B:$C,2,FALSE)) -> HMC
A19: =IF('1) Import fichier Remi (coller)'!D19="","",'1) Import fichier Remi (coller)'!D19) -> VE11 | B19: =IF(A19="","",YEAR('1) Import fichier Remi (coller)'!F19)) -> 2026 | C19: =IF(A19="","",MONTH('1) Import fichier Remi (coller)'!F19)) -> 9 | D19: =IF(A19="","",'1) Import fichier Remi (coller)'!F19) -> 46281 | E19: =IF(A19="","",'1) Import fichier Remi (coller)'!G19) -> 46281 | F19: =IF(A19="","",'1) Import fichier Remi (coller)'!E19) -> 11261519 | G19: =IF(A19="","",IF(ISERROR(VLOOKUP(LEFT('1) Import fichier Remi (coller)'!A19,9),'Concordance client liv et fact'!$A:$H,8,FALSE))=TRUE,'1) Import fichier Remi (coller)'!B19,VLOOKUP(LEFT('1) Import fichier Remi (coller)'!A19,9),'Concordance client liv et fact'!$A:$H,8,FALSE))) -> DIGITALLIF | H19: =IF(A19="","",IF(ISERROR(VLOOKUP('1) Import fichier Remi (coller)'!K19&" - "&'1) Import fichier Remi (coller)'!L19,'Spécifique comptes'!$A:$G,1,FALSE))=TRUE,'1) Import fichier Remi (coller)'!V19,VLOOKUP('1) Import fichier Remi (coller)'!K19&" - "&'1) Import fichier Remi (coller)'!L19,'Spécifique comptes'!$A:$G,IF(LEFT('2) BOB compta (completer-forcer'!F19,2)="11",4,IF(LEFT('2) BOB compta (completer-forcer'!F19,2)="12",5,IF(LEFT('2) BOB compta (completer-forcer'!F19,2)="13",6,IF(LEFT('2) BOB compta (completer-forcer'!F19,2)="15",7,"Erreur Compte")))),FALSE))) -> 705002000 | I19: =IF(A19="","",IF(H19="70100000",'1) Import fichier Remi (coller)'!J19,'1) Import fichier Remi (coller)'!U19)) -> +++003/7261/51936+++ | J19: =IF(A19="","",'1) Import fichier Remi (coller)'!U19) -> +++003/7261/51936+++ | K19: =IF(A19="","",SUMIFS(N:N,A:A,A19,F:F,F19)+SUMIFS(O:O,A:A,A19,F:F,F19)) -> 268.62 | L19: =IF(A19="","",IF(LEFT(T19,1)="B","V","PRT")) -> V | M19: =IF(A19="","",'1) Import fichier Remi (coller)'!S19) -> 21 | N19: =IF($A19="","",IF(OR($A19="NCV",$A19="NC15"),-'1) Import fichier Remi (coller)'!R19,'1) Import fichier Remi (coller)'!R19)) -> 18 | O19: =IF($A19="","",IF(OR($A19="NCV",$A19="NC15"),-'1) Import fichier Remi (coller)'!T19,'1) Import fichier Remi (coller)'!T19)) -> 3.78 | R19: =IF($A19="","",IF(ISERROR(VLOOKUP(LEFT('1) Import fichier Remi (coller)'!$A19,9),'Concordance client liv et fact'!$A:$H,8,FALSE))=TRUE,VLOOKUP(LEFT('1) Import fichier Remi (coller)'!$A19,9)+0,'Clients R2'!$A:$CY,2,FALSE),VLOOKUP(VLOOKUP(LEFT('1) Import fichier Remi (coller)'!$A19,9),'Concordance client liv et fact'!$A:$H,7,FALSE)+0,'Clients R2'!$A:$CY,2,FALSE))) -> DIGITAL LIFE | S19: =IF($A19="","",PROPER(IF(ISERROR(VLOOKUP(LEFT('1) Import fichier Remi (coller)'!$A19,9),'Concordance client liv et fact'!$A:$H,8,FALSE))=TRUE,VLOOKUP(LEFT('1) Import fichier Remi (coller)'!$A19,9)+0,'Clients R2'!$A:$CY,27,FALSE),VLOOKUP(VLOOKUP(LEFT('1) Import fichier Remi (coller)'!$A19,9),'Concordance client liv et fact'!$A:$H,7,FALSE)+0,'Clients R2'!$A:$CY,27,FALSE)))) -> Avenue Pasteur, 6 - Bat H | T19: =IF($A19="","",LEFT(UPPER(IF(ISERROR(VLOOKUP(LEFT('1) Import fichier Remi (coller)'!$A19,9),'Concordance client liv et fact'!$A:$H,8,FALSE))=TRUE,VLOOKUP(LEFT('1) Import fichier Remi (coller)'!$A19,9)+0,'Clients R2'!$A:$CY,28,FALSE),VLOOKUP(VLOOKUP(LEFT('1) Import fichier Remi (coller)'!$A19,9),'Concordance client liv et fact'!$A:$H,7,FALSE)+0,'Clients R2'!$A:$CY,28,FALSE))),2)&UPPER(IF(ISERROR(VLOOKUP(LEFT('1) Import fichier Remi (coller)'!$A19,9),'Concordance client liv et fact'!$A:$H,8,FALSE))=TRUE,VLOOKUP(LEFT('1) Import fichier Remi (coller)'!$A19,9)+0,'Clients R2'!$A:$CY,29,FALSE),VLOOKUP(VLOOKUP(LEFT('1) Import fichier Remi (coller)'!$A19,9),'Concordance client liv et fact'!$A:$H,7,FALSE)+0,'Clients R2'!$A:$CY,29,FALSE)))) -> B 1300 | U19: =IF($A19="","",PROPER(IF(ISERROR(VLOOKUP(LEFT('1) Import fichier Remi (coller)'!$A19,9),'Concordance client liv et fact'!$A:$H,8,FALSE))=TRUE,VLOOKUP(LEFT('1) Import fichier Remi (coller)'!$A19,9)+0,'Clients R2'!$A:$CY,30,FALSE),VLOOKUP(VLOOKUP(LEFT('1) Import fichier Remi (coller)'!$A19,9),'Concordance client liv et fact'!$A:$H,7,FALSE)+0,'Clients R2'!$A:$CY,30,FALSE)))) -> Wavre | V19: =IF($A19="","",LEFT(UPPER(IF(ISERROR(VLOOKUP(LEFT('1) Import fichier Remi (coller)'!$A19,9),'Concordance client liv et fact'!$A:$H,8,FALSE))=TRUE,IF(VLOOKUP(LEFT('1) Import fichier Remi (coller)'!$A19,9)+0,'Clients R2'!$A:$CY,22,FALSE)=4,"NA",VLOOKUP(LEFT('1) Import fichier Remi (coller)'!$A19,9)+0,'Clients R2'!$A:$CY,3,FALSE)),IF(VLOOKUP(VLOOKUP(LEFT('1) Import fichier Remi (coller)'!$A19,9),'Concordance client liv et fact'!$A:$H,7,FALSE)+0,'Clients R2'!$A:$CY,22,FALSE)=4,"NA",VLOOKUP(VLOOKUP(LEFT('1) Import fichier Remi (coller)'!$A19,9),'Concordance client liv et fact'!$A:$H,7,FALSE)+0,'Clients R2'!$A:$CY,3,FALSE)))),2)) -> BE | X19: =IF($A19="","",IF(ISERROR(VLOOKUP(LEFT('1) Import fichier Remi (coller)'!$A19,9),'Concordance client liv et fact'!$A:$H,8,FALSE))=TRUE,VLOOKUP(LEFT('1) Import fichier Remi (coller)'!$A19,9)+0,'Clients R2'!$A:$CY,102,FALSE),VLOOKUP(VLOOKUP(LEFT('1) Import fichier Remi (coller)'!$A19,9),'Concordance client liv et fact'!$A:$H,7,FALSE)+0,'Clients R2'!$A:$CY,102,FALSE))) -> compta@digital-life.be | Y19: CF11261601.PDF | Z19: GDUHOUX | AA19: =IF($A19="VE11","",IF(LEFT($H19,4)="7050","",IF('1) Import fichier Remi (coller)'!M19="","",'1) Import fichier Remi (coller)'!M19))) | AB19: =IF($A19="VE11","",IF(LEFT($H19,4)="7050","",IF('1) Import fichier Remi (coller)'!N19="","",'1) Import fichier Remi (coller)'!N19))) | AC19: =IF(A19="","",VLOOKUP(LEFT('1) Import fichier Remi (coller)'!A19,9)+0,'Concordance Client R2 BOB'!$B:$C,2,FALSE)) -> DIGITALLIF
A20: =IF('1) Import fichier Remi (coller)'!D20="","",'1) Import fichier Remi (coller)'!D20) -> VE11 | B20: =IF(A20="","",YEAR('1) Import fichier Remi (coller)'!F20)) -> 2026 | C20: =IF(A20="","",MONTH('1) Import fichier Remi (coller)'!F20)) -> 9 | D20: =IF(A20="","",'1) Import fichier Remi (coller)'!F20) -> 46281 | E20: =IF(A20="","",'1) Import fichier Remi (coller)'!G20) -> 46281 | F20: =IF(A20="","",'1) Import fichier Remi (coller)'!E20) -> 11261519 | G20: =IF(A20="","",IF(ISERROR(VLOOKUP(LEFT('1) Import fichier Remi (coller)'!A20,9),'Concordance client liv et fact'!$A:$H,8,FALSE))=TRUE,'1) Import fichier Remi (coller)'!B20,VLOOKUP(LEFT('1) Import fichier Remi (coller)'!A20,9),'Concordance client liv et fact'!$A:$H,8,FALSE))) -> DIGITALLIF | H20: =IF(A20="","",IF(ISERROR(VLOOKUP('1) Import fichier Remi (coller)'!K20&" - "&'1) Import fichier Remi (coller)'!L20,'Spécifique comptes'!$A:$G,1,FALSE))=TRUE,'1) Import fichier Remi (coller)'!V20,VLOOKUP('1) Import fichier Remi (coller)'!K20&" - "&'1) Import fichier Remi (coller)'!L20,'Spécifique comptes'!$A:$G,IF(LEFT('2) BOB compta (completer-forcer'!F20,2)="11",4,IF(LEFT('2) BOB compta (completer-forcer'!F20,2)="12",5,IF(LEFT('2) BOB compta (completer-forcer'!F20,2)="13",6,IF(LEFT('2) BOB compta (completer-forcer'!F20,2)="15",7,"Erreur Compte")))),FALSE))) -> 705002000 | I20: =IF(A20="","",IF(H20="70100000",'1) Import fichier Remi (coller)'!J20,'1) Import fichier Remi (coller)'!U20)) -> +++003/7261/51936+++ | J20: =IF(A20="","",'1) Import fichier Remi (coller)'!U20) -> +++003/7261/51936+++ | K20: =IF(A20="","",SUMIFS(N:N,A:A,A20,F:F,F20)+SUMIFS(O:O,A:A,A20,F:F,F20)) -> 268.62 | L20: =IF(A20="","",IF(LEFT(T20,1)="B","V","PRT")) -> V | M20: =IF(A20="","",'1) Import fichier Remi (coller)'!S20) -> 21 | N20: =IF($A20="","",IF(OR($A20="NCV",$A20="NC15"),-'1) Import fichier Remi (coller)'!R20,'1) Import fichier Remi (coller)'!R20)) -> 144 | O20: =IF($A20="","",IF(OR($A20="NCV",$A20="NC15"),-'1) Import fichier Remi (coller)'!T20,'1) Import fichier Remi (coller)'!T20)) -> 30.24 | R20: =IF($A20="","",IF(ISERROR(VLOOKUP(LEFT('1) Import fichier Remi (coller)'!$A20,9),'Concordance client liv et fact'!$A:$H,8,FALSE))=TRUE,VLOOKUP(LEFT('1) Import fichier Remi (coller)'!$A20,9)+0,'Clients R2'!$A:$CY,2,FALSE),VLOOKUP(VLOOKUP(LEFT('1) Import fichier Remi (coller)'!$A20,9),'Concordance client liv et fact'!$A:$H,7,FALSE)+0,'Clients R2'!$A:$CY,2,FALSE))) -> DIGITAL LIFE | S20: =IF($A20="","",PROPER(IF(ISERROR(VLOOKUP(LEFT('1) Import fichier Remi (coller)'!$A20,9),'Concordance client liv et fact'!$A:$H,8,FALSE))=TRUE,VLOOKUP(LEFT('1) Import fichier Remi (coller)'!$A20,9)+0,'Clients R2'!$A:$CY,27,FALSE),VLOOKUP(VLOOKUP(LEFT('1) Import fichier Remi (coller)'!$A20,9),'Concordance client liv et fact'!$A:$H,7,FALSE)+0,'Clients R2'!$A:$CY,27,FALSE)))) -> Avenue Pasteur, 6 - Bat H | T20: =IF($A20="","",LEFT(UPPER(IF(ISERROR(VLOOKUP(LEFT('1) Import fichier Remi (coller)'!$A20,9),'Concordance client liv et fact'!$A:$H,8,FALSE))=TRUE,VLOOKUP(LEFT('1) Import fichier Remi (coller)'!$A20,9)+0,'Clients R2'!$A:$CY,28,FALSE),VLOOKUP(VLOOKUP(LEFT('1) Import fichier Remi (coller)'!$A20,9),'Concordance client liv et fact'!$A:$H,7,FALSE)+0,'Clients R2'!$A:$CY,28,FALSE))),2)&UPPER(IF(ISERROR(VLOOKUP(LEFT('1) Import fichier Remi (coller)'!$A20,9),'Concordance client liv et fact'!$A:$H,8,FALSE))=TRUE,VLOOKUP(LEFT('1) Import fichier Remi (coller)'!$A20,9)+0,'Clients R2'!$A:$CY,29,FALSE),VLOOKUP(VLOOKUP(LEFT('1) Import fichier Remi (coller)'!$A20,9),'Concordance client liv et fact'!$A:$H,7,FALSE)+0,'Clients R2'!$A:$CY,29,FALSE)))) -> B 1300 | U20: =IF($A20="","",PROPER(IF(ISERROR(VLOOKUP(LEFT('1) Import fichier Remi (coller)'!$A20,9),'Concordance client liv et fact'!$A:$H,8,FALSE))=TRUE,VLOOKUP(LEFT('1) Import fichier Remi (coller)'!$A20,9)+0,'Clients R2'!$A:$CY,30,FALSE),VLOOKUP(VLOOKUP(LEFT('1) Import fichier Remi (coller)'!$A20,9),'Concordance client liv et fact'!$A:$H,7,FALSE)+0,'Clients R2'!$A:$CY,30,FALSE)))) -> Wavre | V20: =IF($A20="","",LEFT(UPPER(IF(ISERROR(VLOOKUP(LEFT('1) Import fichier Remi (coller)'!$A20,9),'Concordance client liv et fact'!$A:$H,8,FALSE))=TRUE,IF(VLOOKUP(LEFT('1) Import fichier Remi (coller)'!$A20,9)+0,'Clients R2'!$A:$CY,22,FALSE)=4,"NA",VLOOKUP(LEFT('1) Import fichier Remi (coller)'!$A20,9)+0,'Clients R2'!$A:$CY,3,FALSE)),IF(VLOOKUP(VLOOKUP(LEFT('1) Import fichier Remi (coller)'!$A20,9),'Concordance client liv et fact'!$A:$H,7,FALSE)+0,'Clients R2'!$A:$CY,22,FALSE)=4,"NA",VLOOKUP(VLOOKUP(LEFT('1) Import fichier Remi (coller)'!$A20,9),'Concordance client liv et fact'!$A:$H,7,FALSE)+0,'Clients R2'!$A:$CY,3,FALSE)))),2)) -> BE | X20: =IF($A20="","",IF(ISERROR(VLOOKUP(LEFT('1) Import fichier Remi (coller)'!$A20,9),'Concordance client liv et fact'!$A:$H,8,FALSE))=TRUE,VLOOKUP(LEFT('1) Import fichier Remi (coller)'!$A20,9)+0,'Clients R2'!$A:$CY,102,FALSE),VLOOKUP(VLOOKUP(LEFT('1) Import fichier Remi (coller)'!$A20,9),'Concordance client liv et fact'!$A:$H,7,FALSE)+0,'Clients R2'!$A:$CY,102,FALSE))) -> compta@digital-life.be | Y20: CF11261601.PDF | Z20: FSIMON | AA20: =IF($A20="VE11","",IF(LEFT($H20,4)="7050","",IF('1) Import fichier Remi (coller)'!M20="","",'1) Import fichier Remi (coller)'!M20))) | AB20: =IF($A20="VE11","",IF(LEFT($H20,4)="7050","",IF('1) Import fichier Remi (coller)'!N20="","",'1) Import fichier Remi (coller)'!N20))) | AC20: =IF(A20="","",VLOOKUP(LEFT('1) Import fichier Remi (coller)'!A20,9)+0,'Concordance Client R2 BOB'!$B:$C,2,FALSE)) -> DIGITALLIF
A21: =IF('1) Import fichier Remi (coller)'!D21="","",'1) Import fichier Remi (coller)'!D21) -> VE11 | B21: =IF(A21="","",YEAR('1) Import fichier Remi (coller)'!F21)) -> 2026 | C21: =IF(A21="","",MONTH('1) Import fichier Remi (coller)'!F21)) -> 9 | D21: =IF(A21="","",'1) Import fichier Remi (coller)'!F21) -> 46281 | E21: =IF(A21="","",'1) Import fichier Remi (coller)'!G21) -> 46281 | F21: =IF(A21="","",'1) Import fichier Remi (coller)'!E21) -> 11261519 | G21: =IF(A21="","",IF(ISERROR(VLOOKUP(LEFT('1) Import fichier Remi (coller)'!A21,9),'Concordance client liv et fact'!$A:$H,8,FALSE))=TRUE,'1) Import fichier Remi (coller)'!B21,VLOOKUP(LEFT('1) Import fichier Remi (coller)'!A21,9),'Concordance client liv et fact'!$A:$H,8,FALSE))) -> DIGITALLIF | H21: =IF(A21="","",IF(ISERROR(VLOOKUP('1) Import fichier Remi (coller)'!K21&" - "&'1) Import fichier Remi (coller)'!L21,'Spécifique comptes'!$A:$G,1,FALSE))=TRUE,'1) Import fichier Remi (coller)'!V21,VLOOKUP('1) Import fichier Remi (coller)'!K21&" - "&'1) Import fichier Remi (coller)'!L21,'Spécifique comptes'!$A:$G,IF(LEFT('2) BOB compta (completer-forcer'!F21,2)="11",4,IF(LEFT('2) BOB compta (completer-forcer'!F21,2)="12",5,IF(LEFT('2) BOB compta (completer-forcer'!F21,2)="13",6,IF(LEFT('2) BOB compta (completer-forcer'!F21,2)="15",7,"Erreur Compte")))),FALSE))) -> 704119000 | I21: =IF(A21="","",IF(H21="70100000",'1) Import fichier Remi (coller)'!J21,'1) Import fichier Remi (coller)'!U21)) -> +++003/7261/51936+++ | J21: =IF(A21="","",'1) Import fichier Remi (coller)'!U21) -> +++003/7261/51936+++ | K21: =IF(A21="","",SUMIFS(N:N,A:A,A21,F:F,F21)+SUMIFS(O:O,A:A,A21,F:F,F21)) -> 268.62 | L21: =IF(A21="","",IF(LEFT(T21,1)="B","V","PRT")) -> V | M21: =IF(A21="","",'1) Import fichier Remi (coller)'!S21) -> 21 | N21: =IF($A21="","",IF(OR($A21="NCV",$A21="NC15"),-'1) Import fichier Remi (coller)'!R21,'1) Import fichier Remi (coller)'!R21)) -> 60 | O21: =IF($A21="","",IF(OR($A21="NCV",$A21="NC15"),-'1) Import fichier Remi (coller)'!T21,'1) Import fichier Remi (coller)'!T21)) -> 12.6 | R21: =IF($A21="","",IF(ISERROR(VLOOKUP(LEFT('1) Import fichier Remi (coller)'!$A21,9),'Concordance client liv et fact'!$A:$H,8,FALSE))=TRUE,VLOOKUP(LEFT('1) Import fichier Remi (coller)'!$A21,9)+0,'Clients R2'!$A:$CY,2,FALSE),VLOOKUP(VLOOKUP(LEFT('1) Import fichier Remi (coller)'!$A21,9),'Concordance client liv et fact'!$A:$H,7,FALSE)+0,'Clients R2'!$A:$CY,2,FALSE))) -> DIGITAL LIFE | S21: =IF($A21="","",PROPER(IF(ISERROR(VLOOKUP(LEFT('1) Import fichier Remi (coller)'!$A21,9),'Concordance client liv et fact'!$A:$H,8,FALSE))=TRUE,VLOOKUP(LEFT('1) Import fichier Remi (coller)'!$A21,9)+0,'Clients R2'!$A:$CY,27,FALSE),VLOOKUP(VLOOKUP(LEFT('1) Import fichier Remi (coller)'!$A21,9),'Concordance client liv et fact'!$A:$H,7,FALSE)+0,'Clients R2'!$A:$CY,27,FALSE)))) -> Avenue Pasteur, 6 - Bat H | T21: =IF($A21="","",LEFT(UPPER(IF(ISERROR(VLOOKUP(LEFT('1) Import fichier Remi (coller)'!$A21,9),'Concordance client liv et fact'!$A:$H,8,FALSE))=TRUE,VLOOKUP(LEFT('1) Import fichier Remi (coller)'!$A21,9)+0,'Clients R2'!$A:$CY,28,FALSE),VLOOKUP(VLOOKUP(LEFT('1) Import fichier Remi (coller)'!$A21,9),'Concordance client liv et fact'!$A:$H,7,FALSE)+0,'Clients R2'!$A:$CY,28,FALSE))),2)&UPPER(IF(ISERROR(VLOOKUP(LEFT('1) Import fichier Remi (coller)'!$A21,9),'Concordance client liv et fact'!$A:$H,8,FALSE))=TRUE,VLOOKUP(LEFT('1) Import fichier Remi (coller)'!$A21,9)+0,'Clients R2'!$A:$CY,29,FALSE),VLOOKUP(VLOOKUP(LEFT('1) Import fichier Remi (coller)'!$A21,9),'Concordance client liv et fact'!$A:$H,7,FALSE)+0,'Clients R2'!$A:$CY,29,FALSE)))) -> B 1300 | U21: =IF($A21="","",PROPER(IF(ISERROR(VLOOKUP(LEFT('1) Import fichier Remi (coller)'!$A21,9),'Concordance client liv et fact'!$A:$H,8,FALSE))=TRUE,VLOOKUP(LEFT('1) Import fichier Remi (coller)'!$A21,9)+0,'Clients R2'!$A:$CY,30,FALSE),VLOOKUP(VLOOKUP(LEFT('1) Import fichier Remi (coller)'!$A21,9),'Concordance client liv et fact'!$A:$H,7,FALSE)+0,'Clients R2'!$A:$CY,30,FALSE)))) -> Wavre | V21: =IF($A21="","",LEFT(UPPER(IF(ISERROR(VLOOKUP(LEFT('1) Import fichier Remi (coller)'!$A21,9),'Concordance client liv et fact'!$A:$H,8,FALSE))=TRUE,IF(VLOOKUP(LEFT('1) Import fichier Remi (coller)'!$A21,9)+0,'Clients R2'!$A:$CY,22,FALSE)=4,"NA",VLOOKUP(LEFT('1) Import fichier Remi (coller)'!$A21,9)+0,'Clients R2'!$A:$CY,3,FALSE)),IF(VLOOKUP(VLOOKUP(LEFT('1) Import fichier Remi (coller)'!$A21,9),'Concordance client liv et fact'!$A:$H,7,FALSE)+0,'Clients R2'!$A:$CY,22,FALSE)=4,"NA",VLOOKUP(VLOOKUP(LEFT('1) Import fichier Remi (coller)'!$A21,9),'Concordance client liv et fact'!$A:$H,7,FALSE)+0,'Clients R2'!$A:$CY,3,FALSE)))),2)) -> BE | X21: =IF($A21="","",IF(ISERROR(VLOOKUP(LEFT('1) Import fichier Remi (coller)'!$A21,9),'Concordance client liv et fact'!$A:$H,8,FALSE))=TRUE,VLOOKUP(LEFT('1) Import fichier Remi (coller)'!$A21,9)+0,'Clients R2'!$A:$CY,102,FALSE),VLOOKUP(VLOOKUP(LEFT('1) Import fichier Remi (coller)'!$A21,9),'Concordance client liv et fact'!$A:$H,7,FALSE)+0,'Clients R2'!$A:$CY,102,FALSE))) -> compta@digital-life.be | Y21: CF11261601.PDF | Z21: =IF(A21="","",IF(OR(H21="705099999",H21="705001002"),VLOOKUP('1) Import fichier Remi (coller)'!J21,'Analytique personnel'!$A:$B,2,FALSE),"")) | AA21: =IF($A21="VE11","",IF(LEFT($H21,4)="7050","",IF('1) Import fichier Remi (coller)'!M21="","",'1) Import fichier Remi (coller)'!M21))) | AB21: =IF($A21="VE11","",IF(LEFT($H21,4)="7050","",IF('1) Import fichier Remi (coller)'!N21="","",'1) Import fichier Remi (coller)'!N21))) | AC21: =IF(A21="","",VLOOKUP(LEFT('1) Import fichier Remi (coller)'!A21,9)+0,'Concordance Client R2 BOB'!$B:$C,2,FALSE)) -> DIGITALLIF
A22: =IF('1) Import fichier Remi (coller)'!D22="","",'1) Import fichier Remi (coller)'!D22) -> VE11 | B22: =IF(A22="","",YEAR('1) Import fichier Remi (coller)'!F22)) -> 2026 | C22: =IF(A22="","",MONTH('1) Import fichier Remi (coller)'!F22)) -> 9 | D22: =IF(A22="","",'1) Import fichier Remi (coller)'!F22) -> 46281 | E22: =IF(A22="","",'1) Import fichier Remi (coller)'!G22) -> 46281 | F22: =IF(A22="","",'1) Import fichier Remi (coller)'!E22) -> 11261520 | G22: =IF(A22="","",IF(ISERROR(VLOOKUP(LEFT('1) Import fichier Remi (coller)'!A22,9),'Concordance client liv et fact'!$A:$H,8,FALSE))=TRUE,'1) Import fichier Remi (coller)'!B22,VLOOKUP(LEFT('1) Import fichier Remi (coller)'!A22,9),'Concordance client liv et fact'!$A:$H,8,FALSE))) -> HERVEVAND | H22: =IF(A22="","",IF(ISERROR(VLOOKUP('1) Import fichier Remi (coller)'!K22&" - "&'1) Import fichier Remi (coller)'!L22,'Spécifique comptes'!$A:$G,1,FALSE))=TRUE,'1) Import fichier Remi (coller)'!V22,VLOOKUP('1) Import fichier Remi (coller)'!K22&" - "&'1) Import fichier Remi (coller)'!L22,'Spécifique comptes'!$A:$G,IF(LEFT('2) BOB compta (completer-forcer'!F22,2)="11",4,IF(LEFT('2) BOB compta (completer-forcer'!F22,2)="12",5,IF(LEFT('2) BOB compta (completer-forcer'!F22,2)="13",6,IF(LEFT('2) BOB compta (completer-forcer'!F22,2)="15",7,"Erreur Compte")))),FALSE))) -> 705099999 | I22: =IF(A22="","",IF(H22="70100000",'1) Import fichier Remi (coller)'!J22,'1) Import fichier Remi (coller)'!U22)) -> +++003/7261/52037+++ | J22: =IF(A22="","",'1) Import fichier Remi (coller)'!U22) -> +++003/7261/52037+++ | K22: =IF(A22="","",SUMIFS(N:N,A:A,A22,F:F,F22)+SUMIFS(O:O,A:A,A22,F:F,F22)) -> 28.74 | L22: =IF(A22="","",IF(LEFT(T22,1)="B","V","PRT")) -> V | M22: =IF(A22="","",'1) Import fichier Remi (coller)'!S22) -> 21 | N22: =IF($A22="","",IF(OR($A22="NCV",$A22="NC15"),-'1) Import fichier Remi (coller)'!R22,'1) Import fichier Remi (coller)'!R22)) -> 23.75 | O22: =IF($A22="","",IF(OR($A22="NCV",$A22="NC15"),-'1) Import fichier Remi (coller)'!T22,'1) Import fichier Remi (coller)'!T22)) -> 4.99 | R22: =IF($A22="","",IF(ISERROR(VLOOKUP(LEFT('1) Import fichier Remi (coller)'!$A22,9),'Concordance client liv et fact'!$A:$H,8,FALSE))=TRUE,VLOOKUP(LEFT('1) Import fichier Remi (coller)'!$A22,9)+0,'Clients R2'!$A:$CY,2,FALSE),VLOOKUP(VLOOKUP(LEFT('1) Import fichier Remi (coller)'!$A22,9),'Concordance client liv et fact'!$A:$H,7,FALSE)+0,'Clients R2'!$A:$CY,2,FALSE))) -> HERVE VANDEN HAUTE | S22: =IF($A22="","",PROPER(IF(ISERROR(VLOOKUP(LEFT('1) Import fichier Remi (coller)'!$A22,9),'Concordance client liv et fact'!$A:$H,8,FALSE))=TRUE,VLOOKUP(LEFT('1) Import fichier Remi (coller)'!$A22,9)+0,'Clients R2'!$A:$CY,27,FALSE),VLOOKUP(VLOOKUP(LEFT('1) Import fichier Remi (coller)'!$A22,9),'Concordance client liv et fact'!$A:$H,7,FALSE)+0,'Clients R2'!$A:$CY,27,FALSE)))) -> Rue Emmanuel Lutte 13 | T22: =IF($A22="","",LEFT(UPPER(IF(ISERROR(VLOOKUP(LEFT('1) Import fichier Remi (coller)'!$A22,9),'Concordance client liv et fact'!$A:$H,8,FALSE))=TRUE,VLOOKUP(LEFT('1) Import fichier Remi (coller)'!$A22,9)+0,'Clients R2'!$A:$CY,28,FALSE),VLOOKUP(VLOOKUP(LEFT('1) Import fichier Remi (coller)'!$A22,9),'Concordance client liv et fact'!$A:$H,7,FALSE)+0,'Clients R2'!$A:$CY,28,FALSE))),2)&UPPER(IF(ISERROR(VLOOKUP(LEFT('1) Import fichier Remi (coller)'!$A22,9),'Concordance client liv et fact'!$A:$H,8,FALSE))=TRUE,VLOOKUP(LEFT('1) Import fichier Remi (coller)'!$A22,9)+0,'Clients R2'!$A:$CY,29,FALSE),VLOOKUP(VLOOKUP(LEFT('1) Import fichier Remi (coller)'!$A22,9),'Concordance client liv et fact'!$A:$H,7,FALSE)+0,'Clients R2'!$A:$CY,29,FALSE)))) -> B 1470 | U22: =IF($A22="","",PROPER(IF(ISERROR(VLOOKUP(LEFT('1) Import fichier Remi (coller)'!$A22,9),'Concordance client liv et fact'!$A:$H,8,FALSE))=TRUE,VLOOKUP(LEFT('1) Import fichier Remi (coller)'!$A22,9)+0,'Clients R2'!$A:$CY,30,FALSE),VLOOKUP(VLOOKUP(LEFT('1) Import fichier Remi (coller)'!$A22,9),'Concordance client liv et fact'!$A:$H,7,FALSE)+0,'Clients R2'!$A:$CY,30,FALSE)))) -> Genappe | V22: =IF($A22="","",LEFT(UPPER(IF(ISERROR(VLOOKUP(LEFT('1) Import fichier Remi (coller)'!$A22,9),'Concordance client liv et fact'!$A:$H,8,FALSE))=TRUE,IF(VLOOKUP(LEFT('1) Import fichier Remi (coller)'!$A22,9)+0,'Clients R2'!$A:$CY,22,FALSE)=4,"NA",VLOOKUP(LEFT('1) Import fichier Remi (coller)'!$A22,9)+0,'Clients R2'!$A:$CY,3,FALSE)),IF(VLOOKUP(VLOOKUP(LEFT('1) Import fichier Remi (coller)'!$A22,9),'Concordance client liv et fact'!$A:$H,7,FALSE)+0,'Clients R2'!$A:$CY,22,FALSE)=4,"NA",VLOOKUP(VLOOKUP(LEFT('1) Import fichier Remi (coller)'!$A22,9),'Concordance client liv et fact'!$A:$H,7,FALSE)+0,'Clients R2'!$A:$CY,3,FALSE)))),2)) -> BE | X22: =IF($A22="","",IF(ISERROR(VLOOKUP(LEFT('1) Import fichier Remi (coller)'!$A22,9),'Concordance client liv et fact'!$A:$H,8,FALSE))=TRUE,VLOOKUP(LEFT('1) Import fichier Remi (coller)'!$A22,9)+0,'Clients R2'!$A:$CY,102,FALSE),VLOOKUP(VLOOKUP(LEFT('1) Import fichier Remi (coller)'!$A22,9),'Concordance client liv et fact'!$A:$H,7,FALSE)+0,'Clients R2'!$A:$CY,102,FALSE))) -> HERVE.VANDENHAUTE@HVH.ARCHI | Y22: CF11261601.PDF | Z22: =IF(A22="","",IF(OR(H22="705099999",H22="705001002"),VLOOKUP('1) Import fichier Remi (coller)'!J22,'Analytique personnel'!$A:$B,2,FALSE),"")) -> GDUHOUX | AA22: =IF($A22="VE11","",IF(LEFT($H22,4)="7050","",IF('1) Import fichier Remi (coller)'!M22="","",'1) Import fichier Remi (coller)'!M22))) | AB22: =IF($A22="VE11","",IF(LEFT($H22,4)="7050","",IF('1) Import fichier Remi (coller)'!N22="","",'1) Import fichier Remi (coller)'!N22))) | AC22: =IF(A22="","",VLOOKUP(LEFT('1) Import fichier Remi (coller)'!A22,9)+0,'Concordance Client R2 BOB'!$B:$C,2,FALSE)) -> HERVEVAND
A23: =IF('1) Import fichier Remi (coller)'!D23="","",'1) Import fichier Remi (coller)'!D23) -> VE11 | B23: =IF(A23="","",YEAR('1) Import fichier Remi (coller)'!F23)) -> 2026 | C23: =IF(A23="","",MONTH('1) Import fichier Remi (coller)'!F23)) -> 9 | D23: =IF(A23="","",'1) Import fichier Remi (coller)'!F23) -> 46281 | E23: =IF(A23="","",'1) Import fichier Remi (coller)'!G23) -> 46281 | F23: =IF(A23="","",'1) Import fichier Remi (coller)'!E23) -> 11261521 | G23: =IF(A23="","",IF(ISERROR(VLOOKUP(LEFT('1) Import fichier Remi (coller)'!A23,9),'Concordance client liv et fact'!$A:$H,8,FALSE))=TRUE,'1) Import fichier Remi (coller)'!B23,VLOOKUP(LEFT('1) Import fichier Remi (coller)'!A23,9),'Concordance client liv et fact'!$A:$H,8,FALSE))) -> METAUXEM | H23: =IF(A23="","",IF(ISERROR(VLOOKUP('1) Import fichier Remi (coller)'!K23&" - "&'1) Import fichier Remi (coller)'!L23,'Spécifique comptes'!$A:$G,1,FALSE))=TRUE,'1) Import fichier Remi (coller)'!V23,VLOOKUP('1) Import fichier Remi (coller)'!K23&" - "&'1) Import fichier Remi (coller)'!L23,'Spécifique comptes'!$A:$G,IF(LEFT('2) BOB compta (completer-forcer'!F23,2)="11",4,IF(LEFT('2) BOB compta (completer-forcer'!F23,2)="12",5,IF(LEFT('2) BOB compta (completer-forcer'!F23,2)="13",6,IF(LEFT('2) BOB compta (completer-forcer'!F23,2)="15",7,"Erreur Compte")))),FALSE))) -> 705099999 | I23: =IF(A23="","",IF(H23="70100000",'1) Import fichier Remi (coller)'!J23,'1) Import fichier Remi (coller)'!U23)) -> +++003/7261/52138+++ | J23: =IF(A23="","",'1) Import fichier Remi (coller)'!U23) -> +++003/7261/52138+++ | K23: =IF(A23="","",SUMIFS(N:N,A:A,A23,F:F,F23)+SUMIFS(O:O,A:A,A23,F:F,F23)) -> 804.65 | L23: =IF(A23="","",IF(LEFT(T23,1)="B","V","PRT")) -> V | M23: =IF(A23="","",'1) Import fichier Remi (coller)'!S23) -> 21 | N23: =IF($A23="","",IF(OR($A23="NCV",$A23="NC15"),-'1) Import fichier Remi (coller)'!R23,'1) Import fichier Remi (coller)'!R23)) -> 285 | O23: =IF($A23="","",IF(OR($A23="NCV",$A23="NC15"),-'1) Import fichier Remi (coller)'!T23,'1) Import fichier Remi (coller)'!T23)) -> 59.85 | R23: =IF($A23="","",IF(ISERROR(VLOOKUP(LEFT('1) Import fichier Remi (coller)'!$A23,9),'Concordance client liv et fact'!$A:$H,8,FALSE))=TRUE,VLOOKUP(LEFT('1) Import fichier Remi (coller)'!$A23,9)+0,'Clients R2'!$A:$CY,2,FALSE),VLOOKUP(VLOOKUP(LEFT('1) Import fichier Remi (coller)'!$A23,9),'Concordance client liv et fact'!$A:$H,7,FALSE)+0,'Clients R2'!$A:$CY,2,FALSE))) -> MEBF MECA SA | S23: =IF($A23="","",PROPER(IF(ISERROR(VLOOKUP(LEFT('1) Import fichier Remi (coller)'!$A23,9),'Concordance client liv et fact'!$A:$H,8,FALSE))=TRUE,VLOOKUP(LEFT('1) Import fichier Remi (coller)'!$A23,9)+0,'Clients R2'!$A:$CY,27,FALSE),VLOOKUP(VLOOKUP(LEFT('1) Import fichier Remi (coller)'!$A23,9),'Concordance client liv et fact'!$A:$H,7,FALSE)+0,'Clients R2'!$A:$CY,27,FALSE)))) -> Rue Haute Marexhe, 176 | T23: =IF($A23="","",LEFT(UPPER(IF(ISERROR(VLOOKUP(LEFT('1) Import fichier Remi (coller)'!$A23,9),'Concordance client liv et fact'!$A:$H,8,FALSE))=TRUE,VLOOKUP(LEFT('1) Import fichier Remi (coller)'!$A23,9)+0,'Clients R2'!$A:$CY,28,FALSE),VLOOKUP(VLOOKUP(LEFT('1) Import fichier Remi (coller)'!$A23,9),'Concordance client liv et fact'!$A:$H,7,FALSE)+0,'Clients R2'!$A:$CY,28,FALSE))),2)&UPPER(IF(ISERROR(VLOOKUP(LEFT('1) Import fichier Remi (coller)'!$A23,9),'Concordance client liv et fact'!$A:$H,8,FALSE))=TRUE,VLOOKUP(LEFT('1) Import fichier Remi (coller)'!$A23,9)+0,'Clients R2'!$A:$CY,29,FALSE),VLOOKUP(VLOOKUP(LEFT('1) Import fichier Remi (coller)'!$A23,9),'Concordance client liv et fact'!$A:$H,7,FALSE)+0,'Clients R2'!$A:$CY,29,FALSE)))) -> B 4040 | U23: =IF($A23="","",PROPER(IF(ISERROR(VLOOKUP(LEFT('1) Import fichier Remi (coller)'!$A23,9),'Concordance client liv et fact'!$A:$H,8,FALSE))=TRUE,VLOOKUP(LEFT('1) Import fichier Remi (coller)'!$A23,9)+0,'Clients R2'!$A:$CY,30,FALSE),VLOOKUP(VLOOKUP(LEFT('1) Import fichier Remi (coller)'!$A23,9),'Concordance client liv et fact'!$A:$H,7,FALSE)+0,'Clients R2'!$A:$CY,30,FALSE)))) -> Herstal | V23: =IF($A23="","",LEFT(UPPER(IF(ISERROR(VLOOKUP(LEFT('1) Import fichier Remi (coller)'!$A23,9),'Concordance client liv et fact'!$A:$H,8,FALSE))=TRUE,IF(VLOOKUP(LEFT('1) Import fichier Remi (coller)'!$A23,9)+0,'Clients R2'!$A:$CY,22,FALSE)=4,"NA",VLOOKUP(LEFT('1) Import fichier Remi (coller)'!$A23,9)+0,'Clients R2'!$A:$CY,3,FALSE)),IF(VLOOKUP(VLOOKUP(LEFT('1) Import fichier Remi (coller)'!$A23,9),'Concordance client liv et fact'!$A:$H,7,FALSE)+0,'Clients R2'!$A:$CY,22,FALSE)=4,"NA",VLOOKUP(VLOOKUP(LEFT('1) Import fichier Remi (coller)'!$A23,9),'Concordance client liv et fact'!$A:$H,7,FALSE)+0,'Clients R2'!$A:$CY,3,FALSE)))),2)) -> BE | X23: =IF($A23="","",IF(ISERROR(VLOOKUP(LEFT('1) Import fichier Remi (coller)'!$A23,9),'Concordance client liv et fact'!$A:$H,8,FALSE))=TRUE,VLOOKUP(LEFT('1) Import fichier Remi (coller)'!$A23,9)+0,'Clients R2'!$A:$CY,102,FALSE),VLOOKUP(VLOOKUP(LEFT('1) Import fichier Remi (coller)'!$A23,9),'Concordance client liv et fact'!$A:$H,7,FALSE)+0,'Clients R2'!$A:$CY,102,FALSE))) -> invoice@mebf.be | Y23: CF11261601.PDF | Z23: =IF(A23="","",IF(OR(H23="705099999",H23="705001002"),VLOOKUP('1) Import fichier Remi (coller)'!J23,'Analytique personnel'!$A:$B,2,FALSE),"")) -> GDUHOUX | AA23: =IF($A23="VE11","",IF(LEFT($H23,4)="7050","",IF('1) Import fichier Remi (coller)'!M23="","",'1) Import fichier Remi (coller)'!M23))) | AB23: =IF($A23="VE11","",IF(LEFT($H23,4)="7050","",IF('1) Import fichier Remi (coller)'!N23="","",'1) Import fichier Remi (coller)'!N23))) | AC23: =IF(A23="","",VLOOKUP(LEFT('1) Import fichier Remi (coller)'!A23,9)+0,'Concordance Client R2 BOB'!$B:$C,2,FALSE)) -> METAUXEM
A24: =IF('1) Import fichier Remi (coller)'!D24="","",'1) Import fichier Remi (coller)'!D24) -> VE11 | B24: =IF(A24="","",YEAR('1) Import fichier Remi (coller)'!F24)) -> 2026 | C24: =IF(A24="","",MONTH('1) Import fichier Remi (coller)'!F24)) -> 9 | D24: =IF(A24="","",'1) Import fichier Remi (coller)'!F24) -> 46281 | E24: =IF(A24="","",'1) Import fichier Remi (coller)'!G24) -> 46281 | F24: =IF(A24="","",'1) Import fichier Remi (coller)'!E24) -> 11261521 | G24: =IF(A24="","",IF(ISERROR(VLOOKUP(LEFT('1) Import fichier Remi (coller)'!A24,9),'Concordance client liv et fact'!$A:$H,8,FALSE))=TRUE,'1) Import fichier Remi (coller)'!B24,VLOOKUP(LEFT('1) Import fichier Remi (coller)'!A24,9),'Concordance client liv et fact'!$A:$H,8,FALSE))) -> METAUXEM | H24: =IF(A24="","",IF(ISERROR(VLOOKUP('1) Import fichier Remi (coller)'!K24&" - "&'1) Import fichier Remi (coller)'!L24,'Spécifique comptes'!$A:$G,1,FALSE))=TRUE,'1) Import fichier Remi (coller)'!V24,VLOOKUP('1) Import fichier Remi (coller)'!K24&" - "&'1) Import fichier Remi (coller)'!L24,'Spécifique comptes'!$A:$G,IF(LEFT('2) BOB compta (completer-forcer'!F24,2)="11",4,IF(LEFT('2) BOB compta (completer-forcer'!F24,2)="12",5,IF(LEFT('2) BOB compta (completer-forcer'!F24,2)="13",6,IF(LEFT('2) BOB compta (completer-forcer'!F24,2)="15",7,"Erreur Compte")))),FALSE))) -> 705099999 | I24: =IF(A24="","",IF(H24="70100000",'1) Import fichier Remi (coller)'!J24,'1) Import fichier Remi (coller)'!U24)) -> +++003/7261/52138+++ | J24: =IF(A24="","",'1) Import fichier Remi (coller)'!U24) -> +++003/7261/52138+++ | K24: =IF(A24="","",SUMIFS(N:N,A:A,A24,F:F,F24)+SUMIFS(O:O,A:A,A24,F:F,F24)) -> 804.65 | L24: =IF(A24="","",IF(LEFT(T24,1)="B","V","PRT")) -> V | M24: =IF(A24="","",'1) Import fichier Remi (coller)'!S24) -> 21 | N24: =IF($A24="","",IF(OR($A24="NCV",$A24="NC15"),-'1) Import fichier Remi (coller)'!R24,'1) Import fichier Remi (coller)'!R24)) -> 380 | O24: =IF($A24="","",IF(OR($A24="NCV",$A24="NC15"),-'1) Import fichier Remi (coller)'!T24,'1) Import fichier Remi (coller)'!T24)) -> 79.8 | R24: =IF($A24="","",IF(ISERROR(VLOOKUP(LEFT('1) Import fichier Remi (coller)'!$A24,9),'Concordance client liv et fact'!$A:$H,8,FALSE))=TRUE,VLOOKUP(LEFT('1) Import fichier Remi (coller)'!$A24,9)+0,'Clients R2'!$A:$CY,2,FALSE),VLOOKUP(VLOOKUP(LEFT('1) Import fichier Remi (coller)'!$A24,9),'Concordance client liv et fact'!$A:$H,7,FALSE)+0,'Clients R2'!$A:$CY,2,FALSE))) -> MEBF MECA SA | S24: =IF($A24="","",PROPER(IF(ISERROR(VLOOKUP(LEFT('1) Import fichier Remi (coller)'!$A24,9),'Concordance client liv et fact'!$A:$H,8,FALSE))=TRUE,VLOOKUP(LEFT('1) Import fichier Remi (coller)'!$A24,9)+0,'Clients R2'!$A:$CY,27,FALSE),VLOOKUP(VLOOKUP(LEFT('1) Import fichier Remi (coller)'!$A24,9),'Concordance client liv et fact'!$A:$H,7,FALSE)+0,'Clients R2'!$A:$CY,27,FALSE)))) -> Rue Haute Marexhe, 176 | T24: =IF($A24="","",LEFT(UPPER(IF(ISERROR(VLOOKUP(LEFT('1) Import fichier Remi (coller)'!$A24,9),'Concordance client liv et fact'!$A:$H,8,FALSE))=TRUE,VLOOKUP(LEFT('1) Import fichier Remi (coller)'!$A24,9)+0,'Clients R2'!$A:$CY,28,FALSE),VLOOKUP(VLOOKUP(LEFT('1) Import fichier Remi (coller)'!$A24,9),'Concordance client liv et fact'!$A:$H,7,FALSE)+0,'Clients R2'!$A:$CY,28,FALSE))),2)&UPPER(IF(ISERROR(VLOOKUP(LEFT('1) Import fichier Remi (coller)'!$A24,9),'Concordance client liv et fact'!$A:$H,8,FALSE))=TRUE,VLOOKUP(LEFT('1) Import fichier Remi (coller)'!$A24,9)+0,'Clients R2'!$A:$CY,29,FALSE),VLOOKUP(VLOOKUP(LEFT('1) Import fichier Remi (coller)'!$A24,9),'Concordance client liv et fact'!$A:$H,7,FALSE)+0,'Clients R2'!$A:$CY,29,FALSE)))) -> B 4040 | U24: =IF($A24="","",PROPER(IF(ISERROR(VLOOKUP(LEFT('1) Import fichier Remi (coller)'!$A24,9),'Concordance client liv et fact'!$A:$H,8,FALSE))=TRUE,VLOOKUP(LEFT('1) Import fichier Remi (coller)'!$A24,9)+0,'Clients R2'!$A:$CY,30,FALSE),VLOOKUP(VLOOKUP(LEFT('1) Import fichier Remi (coller)'!$A24,9),'Concordance client liv et fact'!$A:$H,7,FALSE)+0,'Clients R2'!$A:$CY,30,FALSE)))) -> Herstal | V24: =IF($A24="","",LEFT(UPPER(IF(ISERROR(VLOOKUP(LEFT('1) Import fichier Remi (coller)'!$A24,9),'Concordance client liv et fact'!$A:$H,8,FALSE))=TRUE,IF(VLOOKUP(LEFT('1) Import fichier Remi (coller)'!$A24,9)+0,'Clients R2'!$A:$CY,22,FALSE)=4,"NA",VLOOKUP(LEFT('1) Import fichier Remi (coller)'!$A24,9)+0,'Clients R2'!$A:$CY,3,FALSE)),IF(VLOOKUP(VLOOKUP(LEFT('1) Import fichier Remi (coller)'!$A24,9),'Concordance client liv et fact'!$A:$H,7,FALSE)+0,'Clients R2'!$A:$CY,22,FALSE)=4,"NA",VLOOKUP(VLOOKUP(LEFT('1) Import fichier Remi (coller)'!$A24,9),'Concordance client liv et fact'!$A:$H,7,FALSE)+0,'Clients R2'!$A:$CY,3,FALSE)))),2)) -> BE | X24: =IF($A24="","",IF(ISERROR(VLOOKUP(LEFT('1) Import fichier Remi (coller)'!$A24,9),'Concordance client liv et fact'!$A:$H,8,FALSE))=TRUE,VLOOKUP(LEFT('1) Import fichier Remi (coller)'!$A24,9)+0,'Clients R2'!$A:$CY,102,FALSE),VLOOKUP(VLOOKUP(LEFT('1) Import fichier Remi (coller)'!$A24,9),'Concordance client liv et fact'!$A:$H,7,FALSE)+0,'Clients R2'!$A:$CY,102,FALSE))) -> invoice@mebf.be | Y24: CF11261601.PDF | Z24: =IF(A24="","",IF(OR(H24="705099999",H24="705001002"),VLOOKUP('1) Import fichier Remi (coller)'!J24,'Analytique personnel'!$A:$B,2,FALSE),"")) -> GDUHOUX | AA24: =IF($A24="VE11","",IF(LEFT($H24,4)="7050","",IF('1) Import fichier Remi (coller)'!M24="","",'1) Import fichier Remi (coller)'!M24))) | AB24: =IF($A24="VE11","",IF(LEFT($H24,4)="7050","",IF('1) Import fichier Remi (coller)'!N24="","",'1) Import fichier Remi (coller)'!N24))) | AC24: =IF(A24="","",VLOOKUP(LEFT('1) Import fichier Remi (coller)'!A24,9)+0,'Concordance Client R2 BOB'!$B:$C,2,FALSE)) -> METAUXEM
A25: =IF('1) Import fichier Remi (coller)'!D25="","",'1) Import fichier Remi (coller)'!D25) -> VE11 | B25: =IF(A25="","",YEAR('1) Import fichier Remi (coller)'!F25)) -> 2026 | C25: =IF(A25="","",MONTH('1) Import fichier Remi (coller)'!F25)) -> 9 | D25: =IF(A25="","",'1) Import fichier Remi (coller)'!F25) -> 46281 | E25: =IF(A25="","",'1) Import fichier Remi (coller)'!G25) -> 46281 | F25: =IF(A25="","",'1) Import fichier Remi (coller)'!E25) -> 11261522 | G25: =IF(A25="","",IF(ISERROR(VLOOKUP(LEFT('1) Import fichier Remi (coller)'!A25,9),'Concordance client liv et fact'!$A:$H,8,FALSE))=TRUE,'1) Import fichier Remi (coller)'!B25,VLOOKUP(LEFT('1) Import fichier Remi (coller)'!A25,9),'Concordance client liv et fact'!$A:$H,8,FALSE))) -> METAUXEM | H25: =IF(A25="","",IF(ISERROR(VLOOKUP('1) Import fichier Remi (coller)'!K25&" - "&'1) Import fichier Remi (coller)'!L25,'Spécifique comptes'!$A:$G,1,FALSE))=TRUE,'1) Import fichier Remi (coller)'!V25,VLOOKUP('1) Import fichier Remi (coller)'!K25&" - "&'1) Import fichier Remi (coller)'!L25,'Spécifique comptes'!$A:$G,IF(LEFT('2) BOB compta (completer-forcer'!F25,2)="11",4,IF(LEFT('2) BOB compta (completer-forcer'!F25,2)="12",5,IF(LEFT('2) BOB compta (completer-forcer'!F25,2)="13",6,IF(LEFT('2) BOB compta (completer-forcer'!F25,2)="15",7,"Erreur Compte")))),FALSE))) -> 704100000 | I25: =IF(A25="","",IF(H25="70100000",'1) Import fichier Remi (coller)'!J25,'1) Import fichier Remi (coller)'!U25)) -> +++003/7261/52239+++ | J25: =IF(A25="","",'1) Import fichier Remi (coller)'!U25) -> +++003/7261/52239+++ | K25: =IF(A25="","",SUMIFS(N:N,A:A,A25,F:F,F25)+SUMIFS(O:O,A:A,A25,F:F,F25)) -> 4082.02 | L25: =IF(A25="","",IF(LEFT(T25,1)="B","V","PRT")) -> V | M25: =IF(A25="","",'1) Import fichier Remi (coller)'!S25) -> 21 | N25: =IF($A25="","",IF(OR($A25="NCV",$A25="NC15"),-'1) Import fichier Remi (coller)'!R25,'1) Import fichier Remi (coller)'!R25)) -> 2190.64 | O25: =IF($A25="","",IF(OR($A25="NCV",$A25="NC15"),-'1) Import fichier Remi (coller)'!T25,'1) Import fichier Remi (coller)'!T25)) -> 460.03 | R25: =IF($A25="","",IF(ISERROR(VLOOKUP(LEFT('1) Import fichier Remi (coller)'!$A25,9),'Concordance client liv et fact'!$A:$H,8,FALSE))=TRUE,VLOOKUP(LEFT('1) Import fichier Remi (coller)'!$A25,9)+0,'Clients R2'!$A:$CY,2,FALSE),VLOOKUP(VLOOKUP(LEFT('1) Import fichier Remi (coller)'!$A25,9),'Concordance client liv et fact'!$A:$H,7,FALSE)+0,'Clients R2'!$A:$CY,2,FALSE))) -> MEBF MECA SA | S25: =IF($A25="","",PROPER(IF(ISERROR(VLOOKUP(LEFT('1) Import fichier Remi (coller)'!$A25,9),'Concordance client liv et fact'!$A:$H,8,FALSE))=TRUE,VLOOKUP(LEFT('1) Import fichier Remi (coller)'!$A25,9)+0,'Clients R2'!$A:$CY,27,FALSE),VLOOKUP(VLOOKUP(LEFT('1) Import fichier Remi (coller)'!$A25,9),'Concordance client liv et fact'!$A:$H,7,FALSE)+0,'Clients R2'!$A:$CY,27,FALSE)))) -> Rue Haute Marexhe, 176 | T25: =IF($A25="","",LEFT(UPPER(IF(ISERROR(VLOOKUP(LEFT('1) Import fichier Remi (coller)'!$A25,9),'Concordance client liv et fact'!$A:$H,8,FALSE))=TRUE,VLOOKUP(LEFT('1) Import fichier Remi (coller)'!$A25,9)+0,'Clients R2'!$A:$CY,28,FALSE),VLOOKUP(VLOOKUP(LEFT('1) Import fichier Remi (coller)'!$A25,9),'Concordance client liv et fact'!$A:$H,7,FALSE)+0,'Clients R2'!$A:$CY,28,FALSE))),2)&UPPER(IF(ISERROR(VLOOKUP(LEFT('1) Import fichier Remi (coller)'!$A25,9),'Concordance client liv et fact'!$A:$H,8,FALSE))=TRUE,VLOOKUP(LEFT('1) Import fichier Remi (coller)'!$A25,9)+0,'Clients R2'!$A:$CY,29,FALSE),VLOOKUP(VLOOKUP(LEFT('1) Import fichier Remi (coller)'!$A25,9),'Concordance client liv et fact'!$A:$H,7,FALSE)+0,'Clients R2'!$A:$CY,29,FALSE)))) -> B 4040 | U25: =IF($A25="","",PROPER(IF(ISERROR(VLOOKUP(LEFT('1) Import fichier Remi (coller)'!$A25,9),'Concordance client liv et fact'!$A:$H,8,FALSE))=TRUE,VLOOKUP(LEFT('1) Import fichier Remi (coller)'!$A25,9)+0,'Clients R2'!$A:$CY,30,FALSE),VLOOKUP(VLOOKUP(LEFT('1) Import fichier Remi (coller)'!$A25,9),'Concordance client liv et fact'!$A:$H,7,FALSE)+0,'Clients R2'!$A:$CY,30,FALSE)))) -> Herstal | V25: =IF($A25="","",LEFT(UPPER(IF(ISERROR(VLOOKUP(LEFT('1) Import fichier Remi (coller)'!$A25,9),'Concordance client liv et fact'!$A:$H,8,FALSE))=TRUE,IF(VLOOKUP(LEFT('1) Import fichier Remi (coller)'!$A25,9)+0,'Clients R2'!$A:$CY,22,FALSE)=4,"NA",VLOOKUP(LEFT('1) Import fichier Remi (coller)'!$A25,9)+0,'Clients R2'!$A:$CY,3,FALSE)),IF(VLOOKUP(VLOOKUP(LEFT('1) Import fichier Remi (coller)'!$A25,9),'Concordance client liv et fact'!$A:$H,7,FALSE)+0,'Clients R2'!$A:$CY,22,FALSE)=4,"NA",VLOOKUP(VLOOKUP(LEFT('1) Import fichier Remi (coller)'!$A25,9),'Concordance client liv et fact'!$A:$H,7,FALSE)+0,'Clients R2'!$A:$CY,3,FALSE)))),2)) -> BE | X25: =IF($A25="","",IF(ISERROR(VLOOKUP(LEFT('1) Import fichier Remi (coller)'!$A25,9),'Concordance client liv et fact'!$A:$H,8,FALSE))=TRUE,VLOOKUP(LEFT('1) Import fichier Remi (coller)'!$A25,9)+0,'Clients R2'!$A:$CY,102,FALSE),VLOOKUP(VLOOKUP(LEFT('1) Import fichier Remi (coller)'!$A25,9),'Concordance client liv et fact'!$A:$H,7,FALSE)+0,'Clients R2'!$A:$CY,102,FALSE))) -> invoice@mebf.be | Y25: CF11261601.PDF | Z25: =IF(A25="","",IF(OR(H25="705099999",H25="705001002"),VLOOKUP('1) Import fichier Remi (coller)'!J25,'Analytique personnel'!$A:$B,2,FALSE),"")) | AA25: =IF($A25="VE11","",IF(LEFT($H25,4)="7050","",IF('1) Import fichier Remi (coller)'!M25="","",'1) Import fichier Remi (coller)'!M25))) | AB25: =IF($A25="VE11","",IF(LEFT($H25,4)="7050","",IF('1) Import fichier Remi (coller)'!N25="","",'1) Import fichier Remi (coller)'!N25))) | AC25: =IF(A25="","",VLOOKUP(LEFT('1) Import fichier Remi (coller)'!A25,9)+0,'Concordance Client R2 BOB'!$B:$C,2,FALSE)) -> METAUXEM
A26: =IF('1) Import fichier Remi (coller)'!D26="","",'1) Import fichier Remi (coller)'!D26) -> VE11 | B26: =IF(A26="","",YEAR('1) Import fichier Remi (coller)'!F26)) -> 2026 | C26: =IF(A26="","",MONTH('1) Import fichier Remi (coller)'!F26)) -> 9 | D26: =IF(A26="","",'1) Import fichier Remi (coller)'!F26) -> 46281 | E26: =IF(A26="","",'1) Import fichier Remi (coller)'!G26) -> 46281 | F26: =IF(A26="","",'1) Import fichier Remi (coller)'!E26) -> 11261522 | G26: =IF(A26="","",IF(ISERROR(VLOOKUP(LEFT('1) Import fichier Remi (coller)'!A26,9),'Concordance client liv et fact'!$A:$H,8,FALSE))=TRUE,'1) Import fichier Remi (coller)'!B26,VLOOKUP(LEFT('1) Import fichier Remi (coller)'!A26,9),'Concordance client liv et fact'!$A:$H,8,FALSE))) -> METAUXEM | H26: =IF(A26="","",IF(ISERROR(VLOOKUP('1) Import fichier Remi (coller)'!K26&" - "&'1) Import fichier Remi (coller)'!L26,'Spécifique comptes'!$A:$G,1,FALSE))=TRUE,'1) Import fichier Remi (coller)'!V26,VLOOKUP('1) Import fichier Remi (coller)'!K26&" - "&'1) Import fichier Remi (coller)'!L26,'Spécifique comptes'!$A:$G,IF(LEFT('2) BOB compta (completer-forcer'!F26,2)="11",4,IF(LEFT('2) BOB compta (completer-forcer'!F26,2)="12",5,IF(LEFT('2) BOB compta (completer-forcer'!F26,2)="13",6,IF(LEFT('2) BOB compta (completer-forcer'!F26,2)="15",7,"Erreur Compte")))),FALSE))) -> 704100000 | I26: =IF(A26="","",IF(H26="70100000",'1) Import fichier Remi (coller)'!J26,'1) Import fichier Remi (coller)'!U26)) -> +++003/7261/52239+++ | J26: =IF(A26="","",'1) Import fichier Remi (coller)'!U26) -> +++003/7261/52239+++ | K26: =IF(A26="","",SUMIFS(N:N,A:A,A26,F:F,F26)+SUMIFS(O:O,A:A,A26,F:F,F26)) -> 4082.02 | L26: =IF(A26="","",IF(LEFT(T26,1)="B","V","PRT")) -> V | M26: =IF(A26="","",'1) Import fichier Remi (coller)'!S26) -> 21 | N26: =IF($A26="","",IF(OR($A26="NCV",$A26="NC15"),-'1) Import fichier Remi (coller)'!R26,'1) Import fichier Remi (coller)'!R26)) -> 247.52 | O26: =IF($A26="","",IF(OR($A26="NCV",$A26="NC15"),-'1) Import fichier Remi (coller)'!T26,'1) Import fichier Remi (coller)'!T26)) -> 51.98 | R26: =IF($A26="","",IF(ISERROR(VLOOKUP(LEFT('1) Import fichier Remi (coller)'!$A26,9),'Concordance client liv et fact'!$A:$H,8,FALSE))=TRUE,VLOOKUP(LEFT('1) Import fichier Remi (coller)'!$A26,9)+0,'Clients R2'!$A:$CY,2,FALSE),VLOOKUP(VLOOKUP(LEFT('1) Import fichier Remi (coller)'!$A26,9),'Concordance client liv et fact'!$A:$H,7,FALSE)+0,'Clients R2'!$A:$CY,2,FALSE))) -> MEBF MECA SA | S26: =IF($A26="","",PROPER(IF(ISERROR(VLOOKUP(LEFT('1) Import fichier Remi (coller)'!$A26,9),'Concordance client liv et fact'!$A:$H,8,FALSE))=TRUE,VLOOKUP(LEFT('1) Import fichier Remi (coller)'!$A26,9)+0,'Clients R2'!$A:$CY,27,FALSE),VLOOKUP(VLOOKUP(LEFT('1) Import fichier Remi (coller)'!$A26,9),'Concordance client liv et fact'!$A:$H,7,FALSE)+0,'Clients R2'!$A:$CY,27,FALSE)))) -> Rue Haute Marexhe, 176 | T26: =IF($A26="","",LEFT(UPPER(IF(ISERROR(VLOOKUP(LEFT('1) Import fichier Remi (coller)'!$A26,9),'Concordance client liv et fact'!$A:$H,8,FALSE))=TRUE,VLOOKUP(LEFT('1) Import fichier Remi (coller)'!$A26,9)+0,'Clients R2'!$A:$CY,28,FALSE),VLOOKUP(VLOOKUP(LEFT('1) Import fichier Remi (coller)'!$A26,9),'Concordance client liv et fact'!$A:$H,7,FALSE)+0,'Clients R2'!$A:$CY,28,FALSE))),2)&UPPER(IF(ISERROR(VLOOKUP(LEFT('1) Import fichier Remi (coller)'!$A26,9),'Concordance client liv et fact'!$A:$H,8,FALSE))=TRUE,VLOOKUP(LEFT('1) Import fichier Remi (coller)'!$A26,9)+0,'Clients R2'!$A:$CY,29,FALSE),VLOOKUP(VLOOKUP(LEFT('1) Import fichier Remi (coller)'!$A26,9),'Concordance client liv et fact'!$A:$H,7,FALSE)+0,'Clients R2'!$A:$CY,29,FALSE)))) -> B 4040 | U26: =IF($A26="","",PROPER(IF(ISERROR(VLOOKUP(LEFT('1) Import fichier Remi (coller)'!$A26,9),'Concordance client liv et fact'!$A:$H,8,FALSE))=TRUE,VLOOKUP(LEFT('1) Import fichier Remi (coller)'!$A26,9)+0,'Clients R2'!$A:$CY,30,FALSE),VLOOKUP(VLOOKUP(LEFT('1) Import fichier Remi (coller)'!$A26,9),'Concordance client liv et fact'!$A:$H,7,FALSE)+0,'Clients R2'!$A:$CY,30,FALSE)))) -> Herstal | V26: =IF($A26="","",LEFT(UPPER(IF(ISERROR(VLOOKUP(LEFT('1) Import fichier Remi (coller)'!$A26,9),'Concordance client liv et fact'!$A:$H,8,FALSE))=TRUE,IF(VLOOKUP(LEFT('1) Import fichier Remi (coller)'!$A26,9)+0,'Clients R2'!$A:$CY,22,FALSE)=4,"NA",VLOOKUP(LEFT('1) Import fichier Remi (coller)'!$A26,9)+0,'Clients R2'!$A:$CY,3,FALSE)),IF(VLOOKUP(VLOOKUP(LEFT('1) Import fichier Remi (coller)'!$A26,9),'Concordance client liv et fact'!$A:$H,7,FALSE)+0,'Clients R2'!$A:$CY,22,FALSE)=4,"NA",VLOOKUP(VLOOKUP(LEFT('1) Import fichier Remi (coller)'!$A26,9),'Concordance client liv et fact'!$A:$H,7,FALSE)+0,'Clients R2'!$A:$CY,3,FALSE)))),2)) -> BE | X26: =IF($A26="","",IF(ISERROR(VLOOKUP(LEFT('1) Import fichier Remi (coller)'!$A26,9),'Concordance client liv et fact'!$A:$H,8,FALSE))=TRUE,VLOOKUP(LEFT('1) Import fichier Remi (coller)'!$A26,9)+0,'Clients R2'!$A:$CY,102,FALSE),VLOOKUP(VLOOKUP(LEFT('1) Import fichier Remi (coller)'!$A26,9),'Concordance client liv et fact'!$A:$H,7,FALSE)+0,'Clients R2'!$A:$CY,102,FALSE))) -> invoice@mebf.be | Y26: CF11261601.PDF | Z26: =IF(A26="","",IF(OR(H26="705099999",H26="705001002"),VLOOKUP('1) Import fichier Remi (coller)'!J26,'Analytique personnel'!$A:$B,2,FALSE),"")) | AA26: =IF($A26="VE11","",IF(LEFT($H26,4)="7050","",IF('1) Import fichier Remi (coller)'!M26="","",'1) Import fichier Remi (coller)'!M26))) | AB26: =IF($A26="VE11","",IF(LEFT($H26,4)="7050","",IF('1) Import fichier Remi (coller)'!N26="","",'1) Import fichier Remi (coller)'!N26))) | AC26: =IF(A26="","",VLOOKUP(LEFT('1) Import fichier Remi (coller)'!A26,9)+0,'Concordance Client R2 BOB'!$B:$C,2,FALSE)) -> METAUXEM
A27: =IF('1) Import fichier Remi (coller)'!D27="","",'1) Import fichier Remi (coller)'!D27) -> VE11 | B27: =IF(A27="","",YEAR('1) Import fichier Remi (coller)'!F27)) -> 2026 | C27: =IF(A27="","",MONTH('1) Import fichier Remi (coller)'!F27)) -> 9 | D27: =IF(A27="","",'1) Import fichier Remi (coller)'!F27) -> 46281 | E27: =IF(A27="","",'1) Import fichier Remi (coller)'!G27) -> 46281 | F27: =IF(A27="","",'1) Import fichier Remi (coller)'!E27) -> 11261522 | G27: =IF(A27="","",IF(ISERROR(VLOOKUP(LEFT('1) Import fichier Remi (coller)'!A27,9),'Concordance client liv et fact'!$A:$H,8,FALSE))=TRUE,'1) Import fichier Remi (coller)'!B27,VLOOKUP(LEFT('1) Import fichier Remi (coller)'!A27,9),'Concordance client liv et fact'!$A:$H,8,FALSE))) -> METAUXEM | H27: =IF(A27="","",IF(ISERROR(VLOOKUP('1) Import fichier Remi (coller)'!K27&" - "&'1) Import fichier Remi (coller)'!L27,'Spécifique comptes'!$A:$G,1,FALSE))=TRUE,'1) Import fichier Remi (coller)'!V27,VLOOKUP('1) Import fichier Remi (coller)'!K27&" - "&'1) Import fichier Remi (coller)'!L27,'Spécifique comptes'!$A:$G,IF(LEFT('2) BOB compta (completer-forcer'!F27,2)="11",4,IF(LEFT('2) BOB compta (completer-forcer'!F27,2)="12",5,IF(LEFT('2) BOB compta (completer-forcer'!F27,2)="13",6,IF(LEFT('2) BOB compta (completer-forcer'!F27,2)="15",7,"Erreur Compte")))),FALSE))) -> 704100001 | I27: =IF(A27="","",IF(H27="70100000",'1) Import fichier Remi (coller)'!J27,'1) Import fichier Remi (coller)'!U27)) -> +++003/7261/52239+++ | J27: =IF(A27="","",'1) Import fichier Remi (coller)'!U27) -> +++003/7261/52239+++ | K27: =IF(A27="","",SUMIFS(N:N,A:A,A27,F:F,F27)+SUMIFS(O:O,A:A,A27,F:F,F27)) -> 4082.02 | L27: =IF(A27="","",IF(LEFT(T27,1)="B","V","PRT")) -> V | M27: =IF(A27="","",'1) Import fichier Remi (coller)'!S27) -> 21 | N27: =IF($A27="","",IF(OR($A27="NCV",$A27="NC15"),-'1) Import fichier Remi (coller)'!R27,'1) Import fichier Remi (coller)'!R27)) -> 0.4 | O27: =IF($A27="","",IF(OR($A27="NCV",$A27="NC15"),-'1) Import fichier Remi (coller)'!T27,'1) Import fichier Remi (coller)'!T27)) -> 0.08 | R27: =IF($A27="","",IF(ISERROR(VLOOKUP(LEFT('1) Import fichier Remi (coller)'!$A27,9),'Concordance client liv et fact'!$A:$H,8,FALSE))=TRUE,VLOOKUP(LEFT('1) Import fichier Remi (coller)'!$A27,9)+0,'Clients R2'!$A:$CY,2,FALSE),VLOOKUP(VLOOKUP(LEFT('1) Import fichier Remi (coller)'!$A27,9),'Concordance client liv et fact'!$A:$H,7,FALSE)+0,'Clients R2'!$A:$CY,2,FALSE))) -> MEBF MECA SA | S27: =IF($A27="","",PROPER(IF(ISERROR(VLOOKUP(LEFT('1) Import fichier Remi (coller)'!$A27,9),'Concordance client liv et fact'!$A:$H,8,FALSE))=TRUE,VLOOKUP(LEFT('1) Import fichier Remi (coller)'!$A27,9)+0,'Clients R2'!$A:$CY,27,FALSE),VLOOKUP(VLOOKUP(LEFT('1) Import fichier Remi (coller)'!$A27,9),'Concordance client liv et fact'!$A:$H,7,FALSE)+0,'Clients R2'!$A:$CY,27,FALSE)))) -> Rue Haute Marexhe, 176 | T27: =IF($A27="","",LEFT(UPPER(IF(ISERROR(VLOOKUP(LEFT('1) Import fichier Remi (coller)'!$A27,9),'Concordance client liv et fact'!$A:$H,8,FALSE))=TRUE,VLOOKUP(LEFT('1) Import fichier Remi (coller)'!$A27,9)+0,'Clients R2'!$A:$CY,28,FALSE),VLOOKUP(VLOOKUP(LEFT('1) Import fichier Remi (coller)'!$A27,9),'Concordance client liv et fact'!$A:$H,7,FALSE)+0,'Clients R2'!$A:$CY,28,FALSE))),2)&UPPER(IF(ISERROR(VLOOKUP(LEFT('1) Import fichier Remi (coller)'!$A27,9),'Concordance client liv et fact'!$A:$H,8,FALSE))=TRUE,VLOOKUP(LEFT('1) Import fichier Remi (coller)'!$A27,9)+0,'Clients R2'!$A:$CY,29,FALSE),VLOOKUP(VLOOKUP(LEFT('1) Import fichier Remi (coller)'!$A27,9),'Concordance client liv et fact'!$A:$H,7,FALSE)+0,'Clients R2'!$A:$CY,29,FALSE)))) -> B 4040 | U27: =IF($A27="","",PROPER(IF(ISERROR(VLOOKUP(LEFT('1) Import fichier Remi (coller)'!$A27,9),'Concordance client liv et fact'!$A:$H,8,FALSE))=TRUE,VLOOKUP(LEFT('1) Import fichier Remi (coller)'!$A27,9)+0,'Clients R2'!$A:$CY,30,FALSE),VLOOKUP(VLOOKUP(LEFT('1) Import fichier Remi (coller)'!$A27,9),'Concordance client liv et fact'!$A:$H,7,FALSE)+0,'Clients R2'!$A:$CY,30,FALSE)))) -> Herstal | V27: =IF($A27="","",LEFT(UPPER(IF(ISERROR(VLOOKUP(LEFT('1) Import fichier Remi (coller)'!$A27,9),'Concordance client liv et fact'!$A:$H,8,FALSE))=TRUE,IF(VLOOKUP(LEFT('1) Import fichier Remi (coller)'!$A27,9)+0,'Clients R2'!$A:$CY,22,FALSE)=4,"NA",VLOOKUP(LEFT('1) Import fichier Remi (coller)'!$A27,9)+0,'Clients R2'!$A:$CY,3,FALSE)),IF(VLOOKUP(VLOOKUP(LEFT('1) Import fichier Remi (coller)'!$A27,9),'Concordance client liv et fact'!$A:$H,7,FALSE)+0,'Clients R2'!$A:$CY,22,FALSE)=4,"NA",VLOOKUP(VLOOKUP(LEFT('1) Import fichier Remi (coller)'!$A27,9),'Concordance client liv et fact'!$A:$H,7,FALSE)+0,'Clients R2'!$A:$CY,3,FALSE)))),2)) -> BE | X27: =IF($A27="","",IF(ISERROR(VLOOKUP(LEFT('1) Import fichier Remi (coller)'!$A27,9),'Concordance client liv et fact'!$A:$H,8,FALSE))=TRUE,VLOOKUP(LEFT('1) Import fichier Remi (coller)'!$A27,9)+0,'Clients R2'!$A:$CY,102,FALSE),VLOOKUP(VLOOKUP(LEFT('1) Import fichier Remi (coller)'!$A27,9),'Concordance client liv et fact'!$A:$H,7,FALSE)+0,'Clients R2'!$A:$CY,102,FALSE))) -> invoice@mebf.be | Y27: CF11261601.PDF | Z27: =IF(A27="","",IF(OR(H27="705099999",H27="705001002"),VLOOKUP('1) Import fichier Remi (coller)'!J27,'Analytique personnel'!$A:$B,2,FALSE),"")) | AA27: =IF($A27="VE11","",IF(LEFT($H27,4)="7050","",IF('1) Import fichier Remi (coller)'!M27="","",'1) Import fichier Remi (coller)'!M27))) | AB27: =IF($A27="VE11","",IF(LEFT($H27,4)="7050","",IF('1) Import fichier Remi (coller)'!N27="","",'1) Import fichier Remi (coller)'!N27))) | AC27: =IF(A27="","",VLOOKUP(LEFT('1) Import fichier Remi (coller)'!A27,9)+0,'Concordance Client R2 BOB'!$B:$C,2,FALSE)) -> METAUXEM
A28: =IF('1) Import fichier Remi (coller)'!D28="","",'1) Import fichier Remi (coller)'!D28) -> VE11 | B28: =IF(A28="","",YEAR('1) Import fichier Remi (coller)'!F28)) -> 2026 | C28: =IF(A28="","",MONTH('1) Import fichier Remi (coller)'!F28)) -> 9 | D28: =IF(A28="","",'1) Import fichier Remi (coller)'!F28) -> 46281 | E28: =IF(A28="","",'1) Import fichier Remi (coller)'!G28) -> 46281 | F28: =IF(A28="","",'1) Import fichier Remi (coller)'!E28) -> 11261522 | G28: =IF(A28="","",IF(ISERROR(VLOOKUP(LEFT('1) Import fichier Remi (coller)'!A28,9),'Concordance client liv et fact'!$A:$H,8,FALSE))=TRUE,'1) Import fichier Remi (coller)'!B28,VLOOKUP(LEFT('1) Import fichier Remi (coller)'!A28,9),'Concordance client liv et fact'!$A:$H,8,FALSE))) -> METAUXEM | H28: =IF(A28="","",IF(ISERROR(VLOOKUP('1) Import fichier Remi (coller)'!K28&" - "&'1) Import fichier Remi (coller)'!L28,'Spécifique comptes'!$A:$G,1,FALSE))=TRUE,'1) Import fichier Remi (coller)'!V28,VLOOKUP('1) Import fichier Remi (coller)'!K28&" - "&'1) Import fichier Remi (coller)'!L28,'Spécifique comptes'!$A:$G,IF(LEFT('2) BOB compta (completer-forcer'!F28,2)="11",4,IF(LEFT('2) BOB compta (completer-forcer'!F28,2)="12",5,IF(LEFT('2) BOB compta (completer-forcer'!F28,2)="13",6,IF(LEFT('2) BOB compta (completer-forcer'!F28,2)="15",7,"Erreur Compte")))),FALSE))) -> 704100000 | I28: =IF(A28="","",IF(H28="70100000",'1) Import fichier Remi (coller)'!J28,'1) Import fichier Remi (coller)'!U28)) -> +++003/7261/52239+++ | J28: =IF(A28="","",'1) Import fichier Remi (coller)'!U28) -> +++003/7261/52239+++ | K28: =IF(A28="","",SUMIFS(N:N,A:A,A28,F:F,F28)+SUMIFS(O:O,A:A,A28,F:F,F28)) -> 4082.02 | L28: =IF(A28="","",IF(LEFT(T28,1)="B","V","PRT")) -> V | M28: =IF(A28="","",'1) Import fichier Remi (coller)'!S28) -> 21 | N28: =IF($A28="","",IF(OR($A28="NCV",$A28="NC15"),-'1) Import fichier Remi (coller)'!R28,'1) Import fichier Remi (coller)'!R28)) -> 142.43 | O28: =IF($A28="","",IF(OR($A28="NCV",$A28="NC15"),-'1) Import fichier Remi (coller)'!T28,'1) Import fichier Remi (coller)'!T28)) -> 29.91 | R28: =IF($A28="","",IF(ISERROR(VLOOKUP(LEFT('1) Import fichier Remi (coller)'!$A28,9),'Concordance client liv et fact'!$A:$H,8,FALSE))=TRUE,VLOOKUP(LEFT('1) Import fichier Remi (coller)'!$A28,9)+0,'Clients R2'!$A:$CY,2,FALSE),VLOOKUP(VLOOKUP(LEFT('1) Import fichier Remi (coller)'!$A28,9),'Concordance client liv et fact'!$A:$H,7,FALSE)+0,'Clients R2'!$A:$CY,2,FALSE))) -> MEBF MECA SA | S28: =IF($A28="","",PROPER(IF(ISERROR(VLOOKUP(LEFT('1) Import fichier Remi (coller)'!$A28,9),'Concordance client liv et fact'!$A:$H,8,FALSE))=TRUE,VLOOKUP(LEFT('1) Import fichier Remi (coller)'!$A28,9)+0,'Clients R2'!$A:$CY,27,FALSE),VLOOKUP(VLOOKUP(LEFT('1) Import fichier Remi (coller)'!$A28,9),'Concordance client liv et fact'!$A:$H,7,FALSE)+0,'Clients R2'!$A:$CY,27,FALSE)))) -> Rue Haute Marexhe, 176 | T28: =IF($A28="","",LEFT(UPPER(IF(ISERROR(VLOOKUP(LEFT('1) Import fichier Remi (coller)'!$A28,9),'Concordance client liv et fact'!$A:$H,8,FALSE))=TRUE,VLOOKUP(LEFT('1) Import fichier Remi (coller)'!$A28,9)+0,'Clients R2'!$A:$CY,28,FALSE),VLOOKUP(VLOOKUP(LEFT('1) Import fichier Remi (coller)'!$A28,9),'Concordance client liv et fact'!$A:$H,7,FALSE)+0,'Clients R2'!$A:$CY,28,FALSE))),2)&UPPER(IF(ISERROR(VLOOKUP(LEFT('1) Import fichier Remi (coller)'!$A28,9),'Concordance client liv et fact'!$A:$H,8,FALSE))=TRUE,VLOOKUP(LEFT('1) Import fichier Remi (coller)'!$A28,9)+0,'Clients R2'!$A:$CY,29,FALSE),VLOOKUP(VLOOKUP(LEFT('1) Import fichier Remi (coller)'!$A28,9),'Concordance client liv et fact'!$A:$H,7,FALSE)+0,'Clients R2'!$A:$CY,29,FALSE)))) -> B 4040 | U28: =IF($A28="","",PROPER(IF(ISERROR(VLOOKUP(LEFT('1) Import fichier Remi (coller)'!$A28,9),'Concordance client liv et fact'!$A:$H,8,FALSE))=TRUE,VLOOKUP(LEFT('1) Import fichier Remi (coller)'!$A28,9)+0,'Clients R2'!$A:$CY,30,FALSE),VLOOKUP(VLOOKUP(LEFT('1) Import fichier Remi (coller)'!$A28,9),'Concordance client liv et fact'!$A:$H,7,FALSE)+0,'Clients R2'!$A:$CY,30,FALSE)))) -> Herstal | V28: =IF($A28="","",LEFT(UPPER(IF(ISERROR(VLOOKUP(LEFT('1) Import fichier Remi (coller)'!$A28,9),'Concordance client liv et fact'!$A:$H,8,FALSE))=TRUE,IF(VLOOKUP(LEFT('1) Import fichier Remi (coller)'!$A28,9)+0,'Clients R2'!$A:$CY,22,FALSE)=4,"NA",VLOOKUP(LEFT('1) Import fichier Remi (coller)'!$A28,9)+0,'Clients R2'!$A:$CY,3,FALSE)),IF(VLOOKUP(VLOOKUP(LEFT('1) Import fichier Remi (coller)'!$A28,9),'Concordance client liv et fact'!$A:$H,7,FALSE)+0,'Clients R2'!$A:$CY,22,FALSE)=4,"NA",VLOOKUP(VLOOKUP(LEFT('1) Import fichier Remi (coller)'!$A28,9),'Concordance client liv et fact'!$A:$H,7,FALSE)+0,'Clients R2'!$A:$CY,3,FALSE)))),2)) -> BE | X28: =IF($A28="","",IF(ISERROR(VLOOKUP(LEFT('1) Import fichier Remi (coller)'!$A28,9),'Concordance client liv et fact'!$A:$H,8,FALSE))=TRUE,VLOOKUP(LEFT('1) Import fichier Remi (coller)'!$A28,9)+0,'Clients R2'!$A:$CY,102,FALSE),VLOOKUP(VLOOKUP(LEFT('1) Import fichier Remi (coller)'!$A28,9),'Concordance client liv et fact'!$A:$H,7,FALSE)+0,'Clients R2'!$A:$CY,102,FALSE))) -> invoice@mebf.be | Y28: CF11261601.PDF | Z28: =IF(A28="","",IF(OR(H28="705099999",H28="705001002"),VLOOKUP('1) Import fichier Remi (coller)'!J28,'Analytique personnel'!$A:$B,2,FALSE),"")) | AA28: =IF($A28="VE11","",IF(LEFT($H28,4)="7050","",IF('1) Import fichier Remi (coller)'!M28="","",'1) Import fichier Remi (coller)'!M28))) | AB28: =IF($A28="VE11","",IF(LEFT($H28,4)="7050","",IF('1) Import fichier Remi (coller)'!N28="","",'1) Import fichier Remi (coller)'!N28))) | AC28: =IF(A28="","",VLOOKUP(LEFT('1) Import fichier Remi (coller)'!A28,9)+0,'Concordance Client R2 BOB'!$B:$C,2,FALSE)) -> METAUXEM
A29: =IF('1) Import fichier Remi (coller)'!D29="","",'1) Import fichier Remi (coller)'!D29) -> VE11 | B29: =IF(A29="","",YEAR('1) Import fichier Remi (coller)'!F29)) -> 2026 | C29: =IF(A29="","",MONTH('1) Import fichier Remi (coller)'!F29)) -> 9 | D29: =IF(A29="","",'1) Import fichier Remi (coller)'!F29) -> 46281 | E29: =IF(A29="","",'1) Import fichier Remi (coller)'!G29) -> 46281 | F29: =IF(A29="","",'1) Import fichier Remi (coller)'!E29) -> 11261522 | G29: =IF(A29="","",IF(ISERROR(VLOOKUP(LEFT('1) Import fichier Remi (coller)'!A29,9),'Concordance client liv et fact'!$A:$H,8,FALSE))=TRUE,'1) Import fichier Remi (coller)'!B29,VLOOKUP(LEFT('1) Import fichier Remi (coller)'!A29,9),'Concordance client liv et fact'!$A:$H,8,FALSE))) -> METAUXEM | H29: =IF(A29="","",IF(ISERROR(VLOOKUP('1) Import fichier Remi (coller)'!K29&" - "&'1) Import fichier Remi (coller)'!L29,'Spécifique comptes'!$A:$G,1,FALSE))=TRUE,'1) Import fichier Remi (coller)'!V29,VLOOKUP('1) Import fichier Remi (coller)'!K29&" - "&'1) Import fichier Remi (coller)'!L29,'Spécifique comptes'!$A:$G,IF(LEFT('2) BOB compta (completer-forcer'!F29,2)="11",4,IF(LEFT('2) BOB compta (completer-forcer'!F29,2)="12",5,IF(LEFT('2) BOB compta (completer-forcer'!F29,2)="13",6,IF(LEFT('2) BOB compta (completer-forcer'!F29,2)="15",7,"Erreur Compte")))),FALSE))) -> 704100000 | I29: =IF(A29="","",IF(H29="70100000",'1) Import fichier Remi (coller)'!J29,'1) Import fichier Remi (coller)'!U29)) -> +++003/7261/52239+++ | J29: =IF(A29="","",'1) Import fichier Remi (coller)'!U29) -> +++003/7261/52239+++ | K29: =IF(A29="","",SUMIFS(N:N,A:A,A29,F:F,F29)+SUMIFS(O:O,A:A,A29,F:F,F29)) -> 4082.02 | L29: =IF(A29="","",IF(LEFT(T29,1)="B","V","PRT")) -> V | M29: =IF(A29="","",'1) Import fichier Remi (coller)'!S29) -> 21 | N29: =IF($A29="","",IF(OR($A29="NCV",$A29="NC15"),-'1) Import fichier Remi (coller)'!R29,'1) Import fichier Remi (coller)'!R29)) -> 26.04 | O29: =IF($A29="","",IF(OR($A29="NCV",$A29="NC15"),-'1) Import fichier Remi (coller)'!T29,'1) Import fichier Remi (coller)'!T29)) -> 5.47 | R29: =IF($A29="","",IF(ISERROR(VLOOKUP(LEFT('1) Import fichier Remi (coller)'!$A29,9),'Concordance client liv et fact'!$A:$H,8,FALSE))=TRUE,VLOOKUP(LEFT('1) Import fichier Remi (coller)'!$A29,9)+0,'Clients R2'!$A:$CY,2,FALSE),VLOOKUP(VLOOKUP(LEFT('1) Import fichier Remi (coller)'!$A29,9),'Concordance client liv et fact'!$A:$H,7,FALSE)+0,'Clients R2'!$A:$CY,2,FALSE))) -> MEBF MECA SA | S29: =IF($A29="","",PROPER(IF(ISERROR(VLOOKUP(LEFT('1) Import fichier Remi (coller)'!$A29,9),'Concordance client liv et fact'!$A:$H,8,FALSE))=TRUE,VLOOKUP(LEFT('1) Import fichier Remi (coller)'!$A29,9)+0,'Clients R2'!$A:$CY,27,FALSE),VLOOKUP(VLOOKUP(LEFT('1) Import fichier Remi (coller)'!$A29,9),'Concordance client liv et fact'!$A:$H,7,FALSE)+0,'Clients R2'!$A:$CY,27,FALSE)))) -> Rue Haute Marexhe, 176 | T29: =IF($A29="","",LEFT(UPPER(IF(ISERROR(VLOOKUP(LEFT('1) Import fichier Remi (coller)'!$A29,9),'Concordance client liv et fact'!$A:$H,8,FALSE))=TRUE,VLOOKUP(LEFT('1) Import fichier Remi (coller)'!$A29,9)+0,'Clients R2'!$A:$CY,28,FALSE),VLOOKUP(VLOOKUP(LEFT('1) Import fichier Remi (coller)'!$A29,9),'Concordance client liv et fact'!$A:$H,7,FALSE)+0,'Clients R2'!$A:$CY,28,FALSE))),2)&UPPER(IF(ISERROR(VLOOKUP(LEFT('1) Import fichier Remi (coller)'!$A29,9),'Concordance client liv et fact'!$A:$H,8,FALSE))=TRUE,VLOOKUP(LEFT('1) Import fichier Remi (coller)'!$A29,9)+0,'Clients R2'!$A:$CY,29,FALSE),VLOOKUP(VLOOKUP(LEFT('1) Import fichier Remi (coller)'!$A29,9),'Concordance client liv et fact'!$A:$H,7,FALSE)+0,'Clients R2'!$A:$CY,29,FALSE)))) -> B 4040 | U29: =IF($A29="","",PROPER(IF(ISERROR(VLOOKUP(LEFT('1) Import fichier Remi (coller)'!$A29,9),'Concordance client liv et fact'!$A:$H,8,FALSE))=TRUE,VLOOKUP(LEFT('1) Import fichier Remi (coller)'!$A29,9)+0,'Clients R2'!$A:$CY,30,FALSE),VLOOKUP(VLOOKUP(LEFT('1) Import fichier Remi (coller)'!$A29,9),'Concordance client liv et fact'!$A:$H,7,FALSE)+0,'Clients R2'!$A:$CY,30,FALSE)))) -> Herstal | V29: =IF($A29="","",LEFT(UPPER(IF(ISERROR(VLOOKUP(LEFT('1) Import fichier Remi (coller)'!$A29,9),'Concordance client liv et fact'!$A:$H,8,FALSE))=TRUE,IF(VLOOKUP(LEFT('1) Import fichier Remi (coller)'!$A29,9)+0,'Clients R2'!$A:$CY,22,FALSE)=4,"NA",VLOOKUP(LEFT('1) Import fichier Remi (coller)'!$A29,9)+0,'Clients R2'!$A:$CY,3,FALSE)),IF(VLOOKUP(VLOOKUP(LEFT('1) Import fichier Remi (coller)'!$A29,9),'Concordance client liv et fact'!$A:$H,7,FALSE)+0,'Clients R2'!$A:$CY,22,FALSE)=4,"NA",VLOOKUP(VLOOKUP(LEFT('1) Import fichier Remi (coller)'!$A29,9),'Concordance client liv et fact'!$A:$H,7,FALSE)+0,'Clients R2'!$A:$CY,3,FALSE)))),2)) -> BE | X29: =IF($A29="","",IF(ISERROR(VLOOKUP(LEFT('1) Import fichier Remi (coller)'!$A29,9),'Concordance client liv et fact'!$A:$H,8,FALSE))=TRUE,VLOOKUP(LEFT('1) Import fichier Remi (coller)'!$A29,9)+0,'Clients R2'!$A:$CY,102,FALSE),VLOOKUP(VLOOKUP(LEFT('1) Import fichier Remi (coller)'!$A29,9),'Concordance client liv et fact'!$A:$H,7,FALSE)+0,'Clients R2'!$A:$CY,102,FALSE))) -> invoice@mebf.be | Y29: CF11261601.PDF | Z29: =IF(A29="","",IF(OR(H29="705099999",H29="705001002"),VLOOKUP('1) Import fichier Remi (coller)'!J29,'Analytique personnel'!$A:$B,2,FALSE),"")) | AA29: =IF($A29="VE11","",IF(LEFT($H29,4)="7050","",IF('1) Import fichier Remi (coller)'!M29="","",'1) Import fichier Remi (coller)'!M29))) | AB29: =IF($A29="VE11","",IF(LEFT($H29,4)="7050","",IF('1) Import fichier Remi (coller)'!N29="","",'1) Import fichier Remi (coller)'!N29))) | AC29: =IF(A29="","",VLOOKUP(LEFT('1) Import fichier Remi (coller)'!A29,9)+0,'Concordance Client R2 BOB'!$B:$C,2,FALSE)) -> METAUXEM
A30: =IF('1) Import fichier Remi (coller)'!D30="","",'1) Import fichier Remi (coller)'!D30) -> VE11 | B30: =IF(A30="","",YEAR('1) Import fichier Remi (coller)'!F30)) -> 2026 | C30: =IF(A30="","",MONTH('1) Import fichier Remi (coller)'!F30)) -> 9 | D30: =IF(A30="","",'1) Import fichier Remi (coller)'!F30) -> 46281 | E30: =IF(A30="","",'1) Import fichier Remi (coller)'!G30) -> 46281 | F30: =IF(A30="","",'1) Import fichier Remi (coller)'!E30) -> 11261522 | G30: =IF(A30="","",IF(ISERROR(VLOOKUP(LEFT('1) Import fichier Remi (coller)'!A30,9),'Concordance client liv et fact'!$A:$H,8,FALSE))=TRUE,'1) Import fichier Remi (coller)'!B30,VLOOKUP(LEFT('1) Import fichier Remi (coller)'!A30,9),'Concordance client liv et fact'!$A:$H,8,FALSE))) -> METAUXEM | H30: =IF(A30="","",IF(ISERROR(VLOOKUP('1) Import fichier Remi (coller)'!K30&" - "&'1) Import fichier Remi (coller)'!L30,'Spécifique comptes'!$A:$G,1,FALSE))=TRUE,'1) Import fichier Remi (coller)'!V30,VLOOKUP('1) Import fichier Remi (coller)'!K30&" - "&'1) Import fichier Remi (coller)'!L30,'Spécifique comptes'!$A:$G,IF(LEFT('2) BOB compta (completer-forcer'!F30,2)="11",4,IF(LEFT('2) BOB compta (completer-forcer'!F30,2)="12",5,IF(LEFT('2) BOB compta (completer-forcer'!F30,2)="13",6,IF(LEFT('2) BOB compta (completer-forcer'!F30,2)="15",7,"Erreur Compte")))),FALSE))) -> 704100000 | I30: =IF(A30="","",IF(H30="70100000",'1) Import fichier Remi (coller)'!J30,'1) Import fichier Remi (coller)'!U30)) -> +++003/7261/52239+++ | J30: =IF(A30="","",'1) Import fichier Remi (coller)'!U30) -> +++003/7261/52239+++ | K30: =IF(A30="","",SUMIFS(N:N,A:A,A30,F:F,F30)+SUMIFS(O:O,A:A,A30,F:F,F30)) -> 4082.02 | L30: =IF(A30="","",IF(LEFT(T30,1)="B","V","PRT")) -> V | M30: =IF(A30="","",'1) Import fichier Remi (coller)'!S30) -> 21 | N30: =IF($A30="","",IF(OR($A30="NCV",$A30="NC15"),-'1) Import fichier Remi (coller)'!R30,'1) Import fichier Remi (coller)'!R30)) -> 17.62 | O30: =IF($A30="","",IF(OR($A30="NCV",$A30="NC15"),-'1) Import fichier Remi (coller)'!T30,'1) Import fichier Remi (coller)'!T30)) -> 3.7 | R30: =IF($A30="","",IF(ISERROR(VLOOKUP(LEFT('1) Import fichier Remi (coller)'!$A30,9),'Concordance client liv et fact'!$A:$H,8,FALSE))=TRUE,VLOOKUP(LEFT('1) Import fichier Remi (coller)'!$A30,9)+0,'Clients R2'!$A:$CY,2,FALSE),VLOOKUP(VLOOKUP(LEFT('1) Import fichier Remi (coller)'!$A30,9),'Concordance client liv et fact'!$A:$H,7,FALSE)+0,'Clients R2'!$A:$CY,2,FALSE))) -> MEBF MECA SA | S30: =IF($A30="","",PROPER(IF(ISERROR(VLOOKUP(LEFT('1) Import fichier Remi (coller)'!$A30,9),'Concordance client liv et fact'!$A:$H,8,FALSE))=TRUE,VLOOKUP(LEFT('1) Import fichier Remi (coller)'!$A30,9)+0,'Clients R2'!$A:$CY,27,FALSE),VLOOKUP(VLOOKUP(LEFT('1) Import fichier Remi (coller)'!$A30,9),'Concordance client liv et fact'!$A:$H,7,FALSE)+0,'Clients R2'!$A:$CY,27,FALSE)))) -> Rue Haute Marexhe, 176 | T30: =IF($A30="","",LEFT(UPPER(IF(ISERROR(VLOOKUP(LEFT('1) Import fichier Remi (coller)'!$A30,9),'Concordance client liv et fact'!$A:$H,8,FALSE))=TRUE,VLOOKUP(LEFT('1) Import fichier Remi (coller)'!$A30,9)+0,'Clients R2'!$A:$CY,28,FALSE),VLOOKUP(VLOOKUP(LEFT('1) Import fichier Remi (coller)'!$A30,9),'Concordance client liv et fact'!$A:$H,7,FALSE)+0,'Clients R2'!$A:$CY,28,FALSE))),2)&UPPER(IF(ISERROR(VLOOKUP(LEFT('1) Import fichier Remi (coller)'!$A30,9),'Concordance client liv et fact'!$A:$H,8,FALSE))=TRUE,VLOOKUP(LEFT('1) Import fichier Remi (coller)'!$A30,9)+0,'Clients R2'!$A:$CY,29,FALSE),VLOOKUP(VLOOKUP(LEFT('1) Import fichier Remi (coller)'!$A30,9),'Concordance client liv et fact'!$A:$H,7,FALSE)+0,'Clients R2'!$A:$CY,29,FALSE)))) -> B 4040 | U30: =IF($A30="","",PROPER(IF(ISERROR(VLOOKUP(LEFT('1) Import fichier Remi (coller)'!$A30,9),'Concordance client liv et fact'!$A:$H,8,FALSE))=TRUE,VLOOKUP(LEFT('1) Import fichier Remi (coller)'!$A30,9)+0,'Clients R2'!$A:$CY,30,FALSE),VLOOKUP(VLOOKUP(LEFT('1) Import fichier Remi (coller)'!$A30,9),'Concordance client liv et fact'!$A:$H,7,FALSE)+0,'Clients R2'!$A:$CY,30,FALSE)))) -> Herstal | V30: =IF($A30="","",LEFT(UPPER(IF(ISERROR(VLOOKUP(LEFT('1) Import fichier Remi (coller)'!$A30,9),'Concordance client liv et fact'!$A:$H,8,FALSE))=TRUE,IF(VLOOKUP(LEFT('1) Import fichier Remi (coller)'!$A30,9)+0,'Clients R2'!$A:$CY,22,FALSE)=4,"NA",VLOOKUP(LEFT('1) Import fichier Remi (coller)'!$A30,9)+0,'Clients R2'!$A:$CY,3,FALSE)),IF(VLOOKUP(VLOOKUP(LEFT('1) Import fichier Remi (coller)'!$A30,9),'Concordance client liv et fact'!$A:$H,7,FALSE)+0,'Clients R2'!$A:$CY,22,FALSE)=4,"NA",VLOOKUP(VLOOKUP(LEFT('1) Import fichier Remi (coller)'!$A30,9),'Concordance client liv et fact'!$A:$H,7,FALSE)+0,'Clients R2'!$A:$CY,3,FALSE)))),2)) -> BE | X30: =IF($A30="","",IF(ISERROR(VLOOKUP(LEFT('1) Import fichier Remi (coller)'!$A30,9),'Concordance client liv et fact'!$A:$H,8,FALSE))=TRUE,VLOOKUP(LEFT('1) Import fichier Remi (coller)'!$A30,9)+0,'Clients R2'!$A:$CY,102,FALSE),VLOOKUP(VLOOKUP(LEFT('1) Import fichier Remi (coller)'!$A30,9),'Concordance client liv et fact'!$A:$H,7,FALSE)+0,'Clients R2'!$A:$CY,102,FALSE))) -> invoice@mebf.be | Y30: CF11261601.PDF | Z30: =IF(A30="","",IF(OR(H30="705099999",H30="705001002"),VLOOKUP('1) Import fichier Remi (coller)'!J30,'Analytique personnel'!$A:$B,2,FALSE),"")) | AA30: =IF($A30="VE11","",IF(LEFT($H30,4)="7050","",IF('1) Import fichier Remi (coller)'!M30="","",'1) Import fichier Remi (coller)'!M30))) | AB30: =IF($A30="VE11","",IF(LEFT($H30,4)="7050","",IF('1) Import fichier Remi (coller)'!N30="","",'1) Import fichier Remi (coller)'!N30))) | AC30: =IF(A30="","",VLOOKUP(LEFT('1) Import fichier Remi (coller)'!A30,9)+0,'Concordance Client R2 BOB'!$B:$C,2,FALSE)) -> METAUXEM
A31: =IF('1) Import fichier Remi (coller)'!D31="","",'1) Import fichier Remi (coller)'!D31) -> VE11 | B31: =IF(A31="","",YEAR('1) Import fichier Remi (coller)'!F31)) -> 2026 | C31: =IF(A31="","",MONTH('1) Import fichier Remi (coller)'!F31)) -> 9 | D31: =IF(A31="","",'1) Import fichier Remi (coller)'!F31) -> 46281 | E31: =IF(A31="","",'1) Import fichier Remi (coller)'!G31) -> 46281 | F31: =IF(A31="","",'1) Import fichier Remi (coller)'!E31) -> 11261522 | G31: =IF(A31="","",IF(ISERROR(VLOOKUP(LEFT('1) Import fichier Remi (coller)'!A31,9),'Concordance client liv et fact'!$A:$H,8,FALSE))=TRUE,'1) Import fichier Remi (coller)'!B31,VLOOKUP(LEFT('1) Import fichier Remi (coller)'!A31,9),'Concordance client liv et fact'!$A:$H,8,FALSE))) -> METAUXEM | H31: =IF(A31="","",IF(ISERROR(VLOOKUP('1) Import fichier Remi (coller)'!K31&" - "&'1) Import fichier Remi (coller)'!L31,'Spécifique comptes'!$A:$G,1,FALSE))=TRUE,'1) Import fichier Remi (coller)'!V31,VLOOKUP('1) Import fichier Remi (coller)'!K31&" - "&'1) Import fichier Remi (coller)'!L31,'Spécifique comptes'!$A:$G,IF(LEFT('2) BOB compta (completer-forcer'!F31,2)="11",4,IF(LEFT('2) BOB compta (completer-forcer'!F31,2)="12",5,IF(LEFT('2) BOB compta (completer-forcer'!F31,2)="13",6,IF(LEFT('2) BOB compta (completer-forcer'!F31,2)="15",7,"Erreur Compte")))),FALSE))) -> 704100000 | I31: =IF(A31="","",IF(H31="70100000",'1) Import fichier Remi (coller)'!J31,'1) Import fichier Remi (coller)'!U31)) -> +++003/7261/52239+++ | J31: =IF(A31="","",'1) Import fichier Remi (coller)'!U31) -> +++003/7261/52239+++ | K31: =IF(A31="","",SUMIFS(N:N,A:A,A31,F:F,F31)+SUMIFS(O:O,A:A,A31,F:F,F31)) -> 4082.02 | L31: =IF(A31="","",IF(LEFT(T31,1)="B","V","PRT")) -> V | M31: =IF(A31="","",'1) Import fichier Remi (coller)'!S31) -> 21 | N31: =IF($A31="","",IF(OR($A31="NCV",$A31="NC15"),-'1) Import fichier Remi (coller)'!R31,'1) Import fichier Remi (coller)'!R31)) -> 748.92 | O31: =IF($A31="","",IF(OR($A31="NCV",$A31="NC15"),-'1) Import fichier Remi (coller)'!T31,'1) Import fichier Remi (coller)'!T31)) -> 157.28 | R31: =IF($A31="","",IF(ISERROR(VLOOKUP(LEFT('1) Import fichier Remi (coller)'!$A31,9),'Concordance client liv et fact'!$A:$H,8,FALSE))=TRUE,VLOOKUP(LEFT('1) Import fichier Remi (coller)'!$A31,9)+0,'Clients R2'!$A:$CY,2,FALSE),VLOOKUP(VLOOKUP(LEFT('1) Import fichier Remi (coller)'!$A31,9),'Concordance client liv et fact'!$A:$H,7,FALSE)+0,'Clients R2'!$A:$CY,2,FALSE))) -> MEBF MECA SA | S31: =IF($A31="","",PROPER(IF(ISERROR(VLOOKUP(LEFT('1) Import fichier Remi (coller)'!$A31,9),'Concordance client liv et fact'!$A:$H,8,FALSE))=TRUE,VLOOKUP(LEFT('1) Import fichier Remi (coller)'!$A31,9)+0,'Clients R2'!$A:$CY,27,FALSE),VLOOKUP(VLOOKUP(LEFT('1) Import fichier Remi (coller)'!$A31,9),'Concordance client liv et fact'!$A:$H,7,FALSE)+0,'Clients R2'!$A:$CY,27,FALSE)))) -> Rue Haute Marexhe, 176 | T31: =IF($A31="","",LEFT(UPPER(IF(ISERROR(VLOOKUP(LEFT('1) Import fichier Remi (coller)'!$A31,9),'Concordance client liv et fact'!$A:$H,8,FALSE))=TRUE,VLOOKUP(LEFT('1) Import fichier Remi (coller)'!$A31,9)+0,'Clients R2'!$A:$CY,28,FALSE),VLOOKUP(VLOOKUP(LEFT('1) Import fichier Remi (coller)'!$A31,9),'Concordance client liv et fact'!$A:$H,7,FALSE)+0,'Clients R2'!$A:$CY,28,FALSE))),2)&UPPER(IF(ISERROR(VLOOKUP(LEFT('1) Import fichier Remi (coller)'!$A31,9),'Concordance client liv et fact'!$A:$H,8,FALSE))=TRUE,VLOOKUP(LEFT('1) Import fichier Remi (coller)'!$A31,9)+0,'Clients R2'!$A:$CY,29,FALSE),VLOOKUP(VLOOKUP(LEFT('1) Import fichier Remi (coller)'!$A31,9),'Concordance client liv et fact'!$A:$H,7,FALSE)+0,'Clients R2'!$A:$CY,29,FALSE)))) -> B 4040 | U31: =IF($A31="","",PROPER(IF(ISERROR(VLOOKUP(LEFT('1) Import fichier Remi (coller)'!$A31,9),'Concordance client liv et fact'!$A:$H,8,FALSE))=TRUE,VLOOKUP(LEFT('1) Import fichier Remi (coller)'!$A31,9)+0,'Clients R2'!$A:$CY,30,FALSE),VLOOKUP(VLOOKUP(LEFT('1) Import fichier Remi (coller)'!$A31,9),'Concordance client liv et fact'!$A:$H,7,FALSE)+0,'Clients R2'!$A:$CY,30,FALSE)))) -> Herstal | V31: =IF($A31="","",LEFT(UPPER(IF(ISERROR(VLOOKUP(LEFT('1) Import fichier Remi (coller)'!$A31,9),'Concordance client liv et fact'!$A:$H,8,FALSE))=TRUE,IF(VLOOKUP(LEFT('1) Import fichier Remi (coller)'!$A31,9)+0,'Clients R2'!$A:$CY,22,FALSE)=4,"NA",VLOOKUP(LEFT('1) Import fichier Remi (coller)'!$A31,9)+0,'Clients R2'!$A:$CY,3,FALSE)),IF(VLOOKUP(VLOOKUP(LEFT('1) Import fichier Remi (coller)'!$A31,9),'Concordance client liv et fact'!$A:$H,7,FALSE)+0,'Clients R2'!$A:$CY,22,FALSE)=4,"NA",VLOOKUP(VLOOKUP(LEFT('1) Import fichier Remi (coller)'!$A31,9),'Concordance client liv et fact'!$A:$H,7,FALSE)+0,'Clients R2'!$A:$CY,3,FALSE)))),2)) -> BE | X31: =IF($A31="","",IF(ISERROR(VLOOKUP(LEFT('1) Import fichier Remi (coller)'!$A31,9),'Concordance client liv et fact'!$A:$H,8,FALSE))=TRUE,VLOOKUP(LEFT('1) Import fichier Remi (coller)'!$A31,9)+0,'Clients R2'!$A:$CY,102,FALSE),VLOOKUP(VLOOKUP(LEFT('1) Import fichier Remi (coller)'!$A31,9),'Concordance client liv et fact'!$A:$H,7,FALSE)+0,'Clients R2'!$A:$CY,102,FALSE))) -> invoice@mebf.be | Y31: CF11261601.PDF | Z31: =IF(A31="","",IF(OR(H31="705099999",H31="705001002"),VLOOKUP('1) Import fichier Remi (coller)'!J31,'Analytique personnel'!$A:$B,2,FALSE),"")) | AA31: =IF($A31="VE11","",IF(LEFT($H31,4)="7050","",IF('1) Import fichier Remi (coller)'!M31="","",'1) Import fichier Remi (coller)'!M31))) | AB31: =IF($A31="VE11","",IF(LEFT($H31,4)="7050","",IF('1) Import fichier Remi (coller)'!N31="","",'1) Import fichier Remi (coller)'!N31))) | AC31: =IF(A31="","",VLOOKUP(LEFT('1) Import fichier Remi (coller)'!A31,9)+0,'Concordance Client R2 BOB'!$B:$C,2,FALSE)) -> METAUXEM
A32: =IF('1) Import fichier Remi (coller)'!D32="","",'1) Import fichier Remi (coller)'!D32) -> VE11 | B32: =IF(A32="","",YEAR('1) Import fichier Remi (coller)'!F32)) -> 2026 | C32: =IF(A32="","",MONTH('1) Import fichier Remi (coller)'!F32)) -> 9 | D32: =IF(A32="","",'1) Import fichier Remi (coller)'!F32) -> 46281 | E32: =IF(A32="","",'1) Import fichier Remi (coller)'!G32) -> 46281 | F32: =IF(A32="","",'1) Import fichier Remi (coller)'!E32) -> 11261523 | G32: =IF(A32="","",IF(ISERROR(VLOOKUP(LEFT('1) Import fichier Remi (coller)'!A32,9),'Concordance client liv et fact'!$A:$H,8,FALSE))=TRUE,'1) Import fichier Remi (coller)'!B32,VLOOKUP(LEFT('1) Import fichier Remi (coller)'!A32,9),'Concordance client liv et fact'!$A:$H,8,FALSE))) -> CLINIQUEPO | H32: =IF(A32="","",IF(ISERROR(VLOOKUP('1) Import fichier Remi (coller)'!K32&" - "&'1) Import fichier Remi (coller)'!L32,'Spécifique comptes'!$A:$G,1,FALSE))=TRUE,'1) Import fichier Remi (coller)'!V32,VLOOKUP('1) Import fichier Remi (coller)'!K32&" - "&'1) Import fichier Remi (coller)'!L32,'Spécifique comptes'!$A:$G,IF(LEFT('2) BOB compta (completer-forcer'!F32,2)="11",4,IF(LEFT('2) BOB compta (completer-forcer'!F32,2)="12",5,IF(LEFT('2) BOB compta (completer-forcer'!F32,2)="13",6,IF(LEFT('2) BOB compta (completer-forcer'!F32,2)="15",7,"Erreur Compte")))),FALSE))) -> 705099999 | I32: =IF(A32="","",IF(H32="70100000",'1) Import fichier Remi (coller)'!J32,'1) Import fichier Remi (coller)'!U32)) -> +++003/7261/52340+++ | J32: =IF(A32="","",'1) Import fichier Remi (coller)'!U32) -> +++003/7261/52340+++ | K32: =IF(A32="","",SUMIFS(N:N,A:A,A32,F:F,F32)+SUMIFS(O:O,A:A,A32,F:F,F32)) -> 28.74 | L32: =IF(A32="","",IF(LEFT(T32,1)="B","V","PRT")) -> V | M32: =IF(A32="","",'1) Import fichier Remi (coller)'!S32) -> 21 | N32: =IF($A32="","",IF(OR($A32="NCV",$A32="NC15"),-'1) Import fichier Remi (coller)'!R32,'1) Import fichier Remi (coller)'!R32)) -> 23.75 | O32: =IF($A32="","",IF(OR($A32="NCV",$A32="NC15"),-'1) Import fichier Remi (coller)'!T32,'1) Import fichier Remi (coller)'!T32)) -> 4.99 | R32: =IF($A32="","",IF(ISERROR(VLOOKUP(LEFT('1) Import fichier Remi (coller)'!$A32,9),'Concordance client liv et fact'!$A:$H,8,FALSE))=TRUE,VLOOKUP(LEFT('1) Import fichier Remi (coller)'!$A32,9)+0,'Clients R2'!$A:$CY,2,FALSE),VLOOKUP(VLOOKUP(LEFT('1) Import fichier Remi (coller)'!$A32,9),'Concordance client liv et fact'!$A:$H,7,FALSE)+0,'Clients R2'!$A:$CY,2,FALSE))) -> CL. DENT. CDPY | S32: =IF($A32="","",PROPER(IF(ISERROR(VLOOKUP(LEFT('1) Import fichier Remi (coller)'!$A32,9),'Concordance client liv et fact'!$A:$H,8,FALSE))=TRUE,VLOOKUP(LEFT('1) Import fichier Remi (coller)'!$A32,9)+0,'Clients R2'!$A:$CY,27,FALSE),VLOOKUP(VLOOKUP(LEFT('1) Import fichier Remi (coller)'!$A32,9),'Concordance client liv et fact'!$A:$H,7,FALSE)+0,'Clients R2'!$A:$CY,27,FALSE)))) -> Boulevard Frere-Orban 12/11 | T32: =IF($A32="","",LEFT(UPPER(IF(ISERROR(VLOOKUP(LEFT('1) Import fichier Remi (coller)'!$A32,9),'Concordance client liv et fact'!$A:$H,8,FALSE))=TRUE,VLOOKUP(LEFT('1) Import fichier Remi (coller)'!$A32,9)+0,'Clients R2'!$A:$CY,28,FALSE),VLOOKUP(VLOOKUP(LEFT('1) Import fichier Remi (coller)'!$A32,9),'Concordance client liv et fact'!$A:$H,7,FALSE)+0,'Clients R2'!$A:$CY,28,FALSE))),2)&UPPER(IF(ISERROR(VLOOKUP(LEFT('1) Import fichier Remi (coller)'!$A32,9),'Concordance client liv et fact'!$A:$H,8,FALSE))=TRUE,VLOOKUP(LEFT('1) Import fichier Remi (coller)'!$A32,9)+0,'Clients R2'!$A:$CY,29,FALSE),VLOOKUP(VLOOKUP(LEFT('1) Import fichier Remi (coller)'!$A32,9),'Concordance client liv et fact'!$A:$H,7,FALSE)+0,'Clients R2'!$A:$CY,29,FALSE)))) -> B 4000 | U32: =IF($A32="","",PROPER(IF(ISERROR(VLOOKUP(LEFT('1) Import fichier Remi (coller)'!$A32,9),'Concordance client liv et fact'!$A:$H,8,FALSE))=TRUE,VLOOKUP(LEFT('1) Import fichier Remi (coller)'!$A32,9)+0,'Clients R2'!$A:$CY,30,FALSE),VLOOKUP(VLOOKUP(LEFT('1) Import fichier Remi (coller)'!$A32,9),'Concordance client liv et fact'!$A:$H,7,FALSE)+0,'Clients R2'!$A:$CY,30,FALSE)))) -> Liege | V32: =IF($A32="","",LEFT(UPPER(IF(ISERROR(VLOOKUP(LEFT('1) Import fichier Remi (coller)'!$A32,9),'Concordance client liv et fact'!$A:$H,8,FALSE))=TRUE,IF(VLOOKUP(LEFT('1) Import fichier Remi (coller)'!$A32,9)+0,'Clients R2'!$A:$CY,22,FALSE)=4,"NA",VLOOKUP(LEFT('1) Import fichier Remi (coller)'!$A32,9)+0,'Clients R2'!$A:$CY,3,FALSE)),IF(VLOOKUP(VLOOKUP(LEFT('1) Import fichier Remi (coller)'!$A32,9),'Concordance client liv et fact'!$A:$H,7,FALSE)+0,'Clients R2'!$A:$CY,22,FALSE)=4,"NA",VLOOKUP(VLOOKUP(LEFT('1) Import fichier Remi (coller)'!$A32,9),'Concordance client liv et fact'!$A:$H,7,FALSE)+0,'Clients R2'!$A:$CY,3,FALSE)))),2)) -> BE | X32: =IF($A32="","",IF(ISERROR(VLOOKUP(LEFT('1) Import fichier Remi (coller)'!$A32,9),'Concordance client liv et fact'!$A:$H,8,FALSE))=TRUE,VLOOKUP(LEFT('1) Import fichier Remi (coller)'!$A32,9)+0,'Clients R2'!$A:$CY,102,FALSE),VLOOKUP(VLOOKUP(LEFT('1) Import fichier Remi (coller)'!$A32,9),'Concordance client liv et fact'!$A:$H,7,FALSE)+0,'Clients R2'!$A:$CY,102,FALSE))) -> info@cdpy.be | Y32: CF11261601.PDF | Z32: =IF(A32="","",IF(OR(H32="705099999",H32="705001002"),VLOOKUP('1) Import fichier Remi (coller)'!J32,'Analytique personnel'!$A:$B,2,FALSE),"")) -> GDUHOUX | AA32: =IF($A32="VE11","",IF(LEFT($H32,4)="7050","",IF('1) Import fichier Remi (coller)'!M32="","",'1) Import fichier Remi (coller)'!M32))) | AB32: =IF($A32="VE11","",IF(LEFT($H32,4)="7050","",IF('1) Import fichier Remi (coller)'!N32="","",'1) Import fichier Remi (coller)'!N32))) | AC32: =IF(A32="","",VLOOKUP(LEFT('1) Import fichier Remi (coller)'!A32,9)+0,'Concordance Client R2 BOB'!$B:$C,2,FALSE)) -> CLINIQUEPO
... A37: =IF('1) Import fichier Remi (coller)'!D37="","",'1) Import fichier Remi (coller)'!D37) -> VE11 | B37: =IF(A37="","",YEAR('1) Import fichier Remi (coller)'!F37)) -> 2026 | C37: =IF(A37="","",MONTH('1) Import fichier Remi (coller)'!F37)) -> 9 | D37: =IF(A37="","",'1) Import fichier Remi (coller)'!F37) -> 46281 | E37: =IF(A37="","",'1) Import fichier Remi (coller)'!G37) -> 46281 | F37: =IF(A37="","",'1) Import fichier Remi (coller)'!E37) -> 11261528 | G37: =IF(A37="","",IF(ISERROR(VLOOKUP(LEFT('1) Import fichier Remi (coller)'!A37,9),'Concordance client liv et fact'!$A:$H,8,FALSE))=TRUE,'1) Import fichier Remi (coller)'!B37,VLOOKUP(LEFT('1) Import fichier Remi (coller)'!A37,9),'Concordance client liv et fact'!$A:$H,8,FALSE))) -> DRYTEC | H37: =IF(A37="","",IF(ISERROR(VLOOKUP('1) Import fichier Remi (coller)'!K37&" - "&'1) Import fichier Remi (coller)'!L37,'Spécifique comptes'!$A:$G,1,FALSE))=TRUE,'1) Import fichier Remi (coller)'!V37,VLOOKUP('1) Import fichier Remi (coller)'!K37&" - "&'1) Import fichier Remi (coller)'!L37,'Spécifique comptes'!$A:$G,IF(LEFT('2) BOB compta (completer-forcer'!F37,2)="11",4,IF(LEFT('2) BOB compta (completer-forcer'!F37,2)="12",5,IF(LEFT('2) BOB compta (completer-forcer'!F37,2)="13",6,IF(LEFT('2) BOB compta (completer-forcer'!F37,2)="15",7,"Erreur Compte")))),FALSE))) -> 705099999 | I37: =IF(A37="","",IF(H37="70100000",'1) Import fichier Remi (coller)'!J37,'1) Import fichier Remi (coller)'!U37)) -> +++003/7261/52845+++ | J37: =IF(A37="","",'1) Import fichier Remi (coller)'!U37) -> +++003/7261/52845+++ | K37: =IF(A37="","",SUMIFS(N:N,A:A,A37,F:F,F37)+SUMIFS(O:O,A:A,A37,F:F,F37)) -> 259.67 | L37: =IF(A37="","",IF(LEFT(T37,1)="B","V","PRT")) -> V | M37: =IF(A37="","",'1) Import fichier Remi (coller)'!S37) -> 21 | N37: =IF($A37="","",IF(OR($A37="NCV",$A37="NC15"),-'1) Import fichier Remi (coller)'!R37,'1) Import fichier Remi (coller)'!R37)) -> 150 | O37: =IF($A37="","",IF(OR($A37="NCV",$A37="NC15"),-'1) Import fichier Remi (coller)'!T37,'1) Import fichier Remi (coller)'!T37)) -> 31.5 | R37: =IF($A37="","",IF(ISERROR(VLOOKUP(LEFT('1) Import fichier Remi (coller)'!$A37,9),'Concordance client liv et fact'!$A:$H,8,FALSE))=TRUE,VLOOKUP(LEFT('1) Import fichier Remi (coller)'!$A37,9)+0,'Clients R2'!$A:$CY,2,FALSE),VLOOKUP(VLOOKUP(LEFT('1) Import fichier Remi (coller)'!$A37,9),'Concordance client liv et fact'!$A:$H,7,FALSE)+0,'Clients R2'!$A:$CY,2,FALSE))) -> DRYTEC SA | S37: =IF($A37="","",PROPER(IF(ISERROR(VLOOKUP(LEFT('1) Import fichier Remi (coller)'!$A37,9),'Concordance client liv et fact'!$A:$H,8,FALSE))=TRUE,VLOOKUP(LEFT('1) Import fichier Remi (coller)'!$A37,9)+0,'Clients R2'!$A:$CY,27,FALSE),VLOOKUP(VLOOKUP(LEFT('1) Import fichier Remi (coller)'!$A37,9),'Concordance client liv et fact'!$A:$H,7,FALSE)+0,'Clients R2'!$A:$CY,27,FALSE)))) -> Rue De La Legende, 36 | T37: =IF($A37="","",LEFT(UPPER(IF(ISERROR(VLOOKUP(LEFT('1) Import fichier Remi (coller)'!$A37,9),'Concordance client liv et fact'!$A:$H,8,FALSE))=TRUE,VLOOKUP(LEFT('1) Import fichier Remi (coller)'!$A37,9)+0,'Clients R2'!$A:$CY,28,FALSE),VLOOKUP(VLOOKUP(LEFT('1) Import fichier Remi (coller)'!$A37,9),'Concordance client liv et fact'!$A:$H,7,FALSE)+0,'Clients R2'!$A:$CY,28,FALSE))),2)&UPPER(IF(ISERROR(VLOOKUP(LEFT('1) Import fichier Remi (coller)'!$A37,9),'Concordance client liv et fact'!$A:$H,8,FALSE))=TRUE,VLOOKUP(LEFT('1) Import fichier Remi (coller)'!$A37,9)+0,'Clients R2'!$A:$CY,29,FALSE),VLOOKUP(VLOOKUP(LEFT('1) Import fichier Remi (coller)'!$A37,9),'Concordance client liv et fact'!$A:$H,7,FALSE)+0,'Clients R2'!$A:$CY,29,FALSE)))) -> B 4141 | U37: =IF($A37="","",PROPER(IF(ISERROR(VLOOKUP(LEFT('1) Import fichier Remi (coller)'!$A37,9),'Concordance client liv et fact'!$A:$H,8,FALSE))=TRUE,VLOOKUP(LEFT('1) Import fichier Remi (coller)'!$A37,9)+0,'Clients R2'!$A:$CY,30,FALSE),VLOOKUP(VLOOKUP(LEFT('1) Import fichier Remi (coller)'!$A37,9),'Concordance client liv et fact'!$A:$H,7,FALSE)+0,'Clients R2'!$A:$CY,30,FALSE)))) -> Louveigne | V37: =IF($A37="","",LEFT(UPPER(IF(ISERROR(VLOOKUP(LEFT('1) Import fichier Remi (coller)'!$A37,9),'Concordance client liv et fact'!$A:$H,8,FALSE))=TRUE,IF(VLOOKUP(LEFT('1) Import fichier Remi (coller)'!$A37,9)+0,'Clients R2'!$A:$CY,22,FALSE)=4,"NA",VLOOKUP(LEFT('1) Import fichier Remi (coller)'!$A37,9)+0,'Clients R2'!$A:$CY,3,FALSE)),IF(VLOOKUP(VLOOKUP(LEFT('1) Import fichier Remi (coller)'!$A37,9),'Concordance client liv et fact'!$A:$H,7,FALSE)+0,'Clients R2'!$A:$CY,22,FALSE)=4,"NA",VLOOKUP(VLOOKUP(LEFT('1) Import fichier Remi (coller)'!$A37,9),'Concordance client liv et fact'!$A:$H,7,FALSE)+0,'Clients R2'!$A:$CY,3,FALSE)))),2)) -> BE | X37: =IF($A37="","",IF(ISERROR(VLOOKUP(LEFT('1) Import fichier Remi (coller)'!$A37,9),'Concordance client liv et fact'!$A:$H,8,FALSE))=TRUE,VLOOKUP(LEFT('1) Import fichier Remi (coller)'!$A37,9)+0,'Clients R2'!$A:$CY,102,FALSE),VLOOKUP(VLOOKUP(LEFT('1) Import fichier Remi (coller)'!$A37,9),'Concordance client liv et fact'!$A:$H,7,FALSE)+0,'Clients R2'!$A:$CY,102,FALSE))) -> accounting.drytec@mikropor.com | Y37: CF11261601.PDF | Z37: =IF(A37="","",IF(OR(H37="705099999",H37="705001002"),VLOOKUP('1) Import fichier Remi (coller)'!J37,'Analytique personnel'!$A:$B,2,FALSE),"")) -> MFONTAINE | AA37: =IF($A37="VE11","",IF(LEFT($H37,4)="7050","",IF('1) Import fichier Remi (coller)'!M37="","",'1) Import fichier Remi (coller)'!M37))) | AB37: =IF($A37="VE11","",IF(LEFT($H37,4)="7050","",IF('1) Import fichier Remi (coller)'!N37="","",'1) Import fichier Remi (coller)'!N37))) | AC37: =IF(A37="","",VLOOKUP(LEFT('1) Import fichier Remi (coller)'!A37,9)+0,'Concordance Client R2 BOB'!$B:$C,2,FALSE)) -> DRYTEC
A38: =IF('1) Import fichier Remi (coller)'!D38="","",'1) Import fichier Remi (coller)'!D38) -> VE11 | B38: =IF(A38="","",YEAR('1) Import fichier Remi (coller)'!F38)) -> 2026 | C38: =IF(A38="","",MONTH('1) Import fichier Remi (coller)'!F38)) -> 9 | D38: =IF(A38="","",'1) Import fichier Remi (coller)'!F38) -> 46281 | E38: =IF(A38="","",'1) Import fichier Remi (coller)'!G38) -> 46281 | F38: =IF(A38="","",'1) Import fichier Remi (coller)'!E38) -> 11261528 | G38: =IF(A38="","",IF(ISERROR(VLOOKUP(LEFT('1) Import fichier Remi (coller)'!A38,9),'Concordance client liv et fact'!$A:$H,8,FALSE))=TRUE,'1) Import fichier Remi (coller)'!B38,VLOOKUP(LEFT('1) Import fichier Remi (coller)'!A38,9),'Concordance client liv et fact'!$A:$H,8,FALSE))) -> DRYTEC | H38: =IF(A38="","",IF(ISERROR(VLOOKUP('1) Import fichier Remi (coller)'!K38&" - "&'1) Import fichier Remi (coller)'!L38,'Spécifique comptes'!$A:$G,1,FALSE))=TRUE,'1) Import fichier Remi (coller)'!V38,VLOOKUP('1) Import fichier Remi (coller)'!K38&" - "&'1) Import fichier Remi (coller)'!L38,'Spécifique comptes'!$A:$G,IF(LEFT('2) BOB compta (completer-forcer'!F38,2)="11",4,IF(LEFT('2) BOB compta (completer-forcer'!F38,2)="12",5,IF(LEFT('2) BOB compta (completer-forcer'!F38,2)="13",6,IF(LEFT('2) BOB compta (completer-forcer'!F38,2)="15",7,"Erreur Compte")))),FALSE))) -> 705001002 | I38: =IF(A38="","",IF(H38="70100000",'1) Import fichier Remi (coller)'!J38,'1) Import fichier Remi (coller)'!U38)) -> +++003/7261/52845+++ | J38: =IF(A38="","",'1) Import fichier Remi (coller)'!U38) -> +++003/7261/52845+++ | K38: =IF(A38="","",SUMIFS(N:N,A:A,A38,F:F,F38)+SUMIFS(O:O,A:A,A38,F:F,F38)) -> 259.67 | L38: =IF(A38="","",IF(LEFT(T38,1)="B","V","PRT")) -> V | M38: =IF(A38="","",'1) Import fichier Remi (coller)'!S38) -> 21 | N38: =IF($A38="","",IF(OR($A38="NCV",$A38="NC15"),-'1) Import fichier Remi (coller)'!R38,'1) Import fichier Remi (coller)'!R38)) -> 64.6 | O38: =IF($A38="","",IF(OR($A38="NCV",$A38="NC15"),-'1) Import fichier Remi (coller)'!T38,'1) Import fichier Remi (coller)'!T38)) -> 13.57 | R38: =IF($A38="","",IF(ISERROR(VLOOKUP(LEFT('1) Import fichier Remi (coller)'!$A38,9),'Concordance client liv et fact'!$A:$H,8,FALSE))=TRUE,VLOOKUP(LEFT('1) Import fichier Remi (coller)'!$A38,9)+0,'Clients R2'!$A:$CY,2,FALSE),VLOOKUP(VLOOKUP(LEFT('1) Import fichier Remi (coller)'!$A38,9),'Concordance client liv et fact'!$A:$H,7,FALSE)+0,'Clients R2'!$A:$CY,2,FALSE))) -> DRYTEC SA | S38: =IF($A38="","",PROPER(IF(ISERROR(VLOOKUP(LEFT('1) Import fichier Remi (coller)'!$A38,9),'Concordance client liv et fact'!$A:$H,8,FALSE))=TRUE,VLOOKUP(LEFT('1) Import fichier Remi (coller)'!$A38,9)+0,'Clients R2'!$A:$CY,27,FALSE),VLOOKUP(VLOOKUP(LEFT('1) Import fichier Remi (coller)'!$A38,9),'Concordance client liv et fact'!$A:$H,7,FALSE)+0,'Clients R2'!$A:$CY,27,FALSE)))) -> Rue De La Legende, 36 | T38: =IF($A38="","",LEFT(UPPER(IF(ISERROR(VLOOKUP(LEFT('1) Import fichier Remi (coller)'!$A38,9),'Concordance client liv et fact'!$A:$H,8,FALSE))=TRUE,VLOOKUP(LEFT('1) Import fichier Remi (coller)'!$A38,9)+0,'Clients R2'!$A:$CY,28,FALSE),VLOOKUP(VLOOKUP(LEFT('1) Import fichier Remi (coller)'!$A38,9),'Concordance client liv et fact'!$A:$H,7,FALSE)+0,'Clients R2'!$A:$CY,28,FALSE))),2)&UPPER(IF(ISERROR(VLOOKUP(LEFT('1) Import fichier Remi (coller)'!$A38,9),'Concordance client liv et fact'!$A:$H,8,FALSE))=TRUE,VLOOKUP(LEFT('1) Import fichier Remi (coller)'!$A38,9)+0,'Clients R2'!$A:$CY,29,FALSE),VLOOKUP(VLOOKUP(LEFT('1) Import fichier Remi (coller)'!$A38,9),'Concordance client liv et fact'!$A:$H,7,FALSE)+0,'Clients R2'!$A:$CY,29,FALSE)))) -> B 4141 | U38: =IF($A38="","",PROPER(IF(ISERROR(VLOOKUP(LEFT('1) Import fichier Remi (coller)'!$A38,9),'Concordance client liv et fact'!$A:$H,8,FALSE))=TRUE,VLOOKUP(LEFT('1) Import fichier Remi (coller)'!$A38,9)+0,'Clients R2'!$A:$CY,30,FALSE),VLOOKUP(VLOOKUP(LEFT('1) Import fichier Remi (coller)'!$A38,9),'Concordance client liv et fact'!$A:$H,7,FALSE)+0,'Clients R2'!$A:$CY,30,FALSE)))) -> Louveigne | V38: =IF($A38="","",LEFT(UPPER(IF(ISERROR(VLOOKUP(LEFT('1) Import fichier Remi (coller)'!$A38,9),'Concordance client liv et fact'!$A:$H,8,FALSE))=TRUE,IF(VLOOKUP(LEFT('1) Import fichier Remi (coller)'!$A38,9)+0,'Clients R2'!$A:$CY,22,FALSE)=4,"NA",VLOOKUP(LEFT('1) Import fichier Remi (coller)'!$A38,9)+0,'Clients R2'!$A:$CY,3,FALSE)),IF(VLOOKUP(VLOOKUP(LEFT('1) Import fichier Remi (coller)'!$A38,9),'Concordance client liv et fact'!$A:$H,7,FALSE)+0,'Clients R2'!$A:$CY,22,FALSE)=4,"NA",VLOOKUP(VLOOKUP(LEFT('1) Import fichier Remi (coller)'!$A38,9),'Concordance client liv et fact'!$A:$H,7,FALSE)+0,'Clients R2'!$A:$CY,3,FALSE)))),2)) -> BE | X38: =IF($A38="","",IF(ISERROR(VLOOKUP(LEFT('1) Import fichier Remi (coller)'!$A38,9),'Concordance client liv et fact'!$A:$H,8,FALSE))=TRUE,VLOOKUP(LEFT('1) Import fichier Remi (coller)'!$A38,9)+0,'Clients R2'!$A:$CY,102,FALSE),VLOOKUP(VLOOKUP(LEFT('1) Import fichier Remi (coller)'!$A38,9),'Concordance client liv et fact'!$A:$H,7,FALSE)+0,'Clients R2'!$A:$CY,102,FALSE))) -> accounting.drytec@mikropor.com | Y38: CF11261601.PDF | Z38: MFONTAINE | AA38: =IF($A38="VE11","",IF(LEFT($H38,4)="7050","",IF('1) Import fichier Remi (coller)'!M38="","",'1) Import fichier Remi (coller)'!M38))) | AB38: =IF($A38="VE11","",IF(LEFT($H38,4)="7050","",IF('1) Import fichier Remi (coller)'!N38="","",'1) Import fichier Remi (coller)'!N38))) | AC38: =IF(A38="","",VLOOKUP(LEFT('1) Import fichier Remi (coller)'!A38,9)+0,'Concordance Client R2 BOB'!$B:$C,2,FALSE)) -> DRYTEC
A39: =IF('1) Import fichier Remi (coller)'!D39="","",'1) Import fichier Remi (coller)'!D39) -> VE11 | B39: =IF(A39="","",YEAR('1) Import fichier Remi (coller)'!F39)) -> 2026 | C39: =IF(A39="","",MONTH('1) Import fichier Remi (coller)'!F39)) -> 9 | D39: =IF(A39="","",'1) Import fichier Remi (coller)'!F39) -> 46281 | E39: =IF(A39="","",'1) Import fichier Remi (coller)'!G39) -> 46311 | F39: =IF(A39="","",'1) Import fichier Remi (coller)'!E39) -> 11261529 | G39: =IF(A39="","",IF(ISERROR(VLOOKUP(LEFT('1) Import fichier Remi (coller)'!A39,9),'Concordance client liv et fact'!$A:$H,8,FALSE))=TRUE,'1) Import fichier Remi (coller)'!B39,VLOOKUP(LEFT('1) Import fichier Remi (coller)'!A39,9),'Concordance client liv et fact'!$A:$H,8,FALSE))) -> HOFMAN | H39: =IF(A39="","",IF(ISERROR(VLOOKUP('1) Import fichier Remi (coller)'!K39&" - "&'1) Import fichier Remi (coller)'!L39,'Spécifique comptes'!$A:$G,1,FALSE))=TRUE,'1) Import fichier Remi (coller)'!V39,VLOOKUP('1) Import fichier Remi (coller)'!K39&" - "&'1) Import fichier Remi (coller)'!L39,'Spécifique comptes'!$A:$G,IF(LEFT('2) BOB compta (completer-forcer'!F39,2)="11",4,IF(LEFT('2) BOB compta (completer-forcer'!F39,2)="12",5,IF(LEFT('2) BOB compta (completer-forcer'!F39,2)="13",6,IF(LEFT('2) BOB compta (completer-forcer'!F39,2)="15",7,"Erreur Compte")))),FALSE))) -> 705099999 | I39: =IF(A39="","",IF(H39="70100000",'1) Import fichier Remi (coller)'!J39,'1) Import fichier Remi (coller)'!U39)) -> +++003/7261/52946+++ | J39: =IF(A39="","",'1) Import fichier Remi (coller)'!U39) -> +++003/7261/52946+++ | K39: =IF(A39="","",SUMIFS(N:N,A:A,A39,F:F,F39)+SUMIFS(O:O,A:A,A39,F:F,F39)) -> 28.74 | L39: =IF(A39="","",IF(LEFT(T39,1)="B","V","PRT")) -> V | M39: =IF(A39="","",'1) Import fichier Remi (coller)'!S39) -> 21 | N39: =IF($A39="","",IF(OR($A39="NCV",$A39="NC15"),-'1) Import fichier Remi (coller)'!R39,'1) Import fichier Remi (coller)'!R39)) -> 23.75 | O39: =IF($A39="","",IF(OR($A39="NCV",$A39="NC15"),-'1) Import fichier Remi (coller)'!T39,'1) Import fichier Remi (coller)'!T39)) -> 4.99 | R39: =IF($A39="","",IF(ISERROR(VLOOKUP(LEFT('1) Import fichier Remi (coller)'!$A39,9),'Concordance client liv et fact'!$A:$H,8,FALSE))=TRUE,VLOOKUP(LEFT('1) Import fichier Remi (coller)'!$A39,9)+0,'Clients R2'!$A:$CY,2,FALSE),VLOOKUP(VLOOKUP(LEFT('1) Import fichier Remi (coller)'!$A39,9),'Concordance client liv et fact'!$A:$H,7,FALSE)+0,'Clients R2'!$A:$CY,2,FALSE))) -> HOFMAN SA | S39: =IF($A39="","",PROPER(IF(ISERROR(VLOOKUP(LEFT('1) Import fichier Remi (coller)'!$A39,9),'Concordance client liv et fact'!$A:$H,8,FALSE))=TRUE,VLOOKUP(LEFT('1) Import fichier Remi (coller)'!$A39,9)+0,'Clients R2'!$A:$CY,27,FALSE),VLOOKUP(VLOOKUP(LEFT('1) Import fichier Remi (coller)'!$A39,9),'Concordance client liv et fact'!$A:$H,7,FALSE)+0,'Clients R2'!$A:$CY,27,FALSE)))) -> Rue Des Waides 17 | T39: =IF($A39="","",LEFT(UPPER(IF(ISERROR(VLOOKUP(LEFT('1) Import fichier Remi (coller)'!$A39,9),'Concordance client liv et fact'!$A:$H,8,FALSE))=TRUE,VLOOKUP(LEFT('1) Import fichier Remi (coller)'!$A39,9)+0,'Clients R2'!$A:$CY,28,FALSE),VLOOKUP(VLOOKUP(LEFT('1) Import fichier Remi (coller)'!$A39,9),'Concordance client liv et fact'!$A:$H,7,FALSE)+0,'Clients R2'!$A:$CY,28,FALSE))),2)&UPPER(IF(ISERROR(VLOOKUP(LEFT('1) Import fichier Remi (coller)'!$A39,9),'Concordance client liv et fact'!$A:$H,8,FALSE))=TRUE,VLOOKUP(LEFT('1) Import fichier Remi (coller)'!$A39,9)+0,'Clients R2'!$A:$CY,29,FALSE),VLOOKUP(VLOOKUP(LEFT('1) Import fichier Remi (coller)'!$A39,9),'Concordance client liv et fact'!$A:$H,7,FALSE)+0,'Clients R2'!$A:$CY,29,FALSE)))) -> B 4890 | U39: =IF($A39="","",PROPER(IF(ISERROR(VLOOKUP(LEFT('1) Import fichier Remi (coller)'!$A39,9),'Concordance client liv et fact'!$A:$H,8,FALSE))=TRUE,VLOOKUP(LEFT('1) Import fichier Remi (coller)'!$A39,9)+0,'Clients R2'!$A:$CY,30,FALSE),VLOOKUP(VLOOKUP(LEFT('1) Import fichier Remi (coller)'!$A39,9),'Concordance client liv et fact'!$A:$H,7,FALSE)+0,'Clients R2'!$A:$CY,30,FALSE)))) -> Thimister-Clermont | V39: =IF($A39="","",LEFT(UPPER(IF(ISERROR(VLOOKUP(LEFT('1) Import fichier Remi (coller)'!$A39,9),'Concordance client liv et fact'!$A:$H,8,FALSE))=TRUE,IF(VLOOKUP(LEFT('1) Import fichier Remi (coller)'!$A39,9)+0,'Clients R2'!$A:$CY,22,FALSE)=4,"NA",VLOOKUP(LEFT('1) Import fichier Remi (coller)'!$A39,9)+0,'Clients R2'!$A:$CY,3,FALSE)),IF(VLOOKUP(VLOOKUP(LEFT('1) Import fichier Remi (coller)'!$A39,9),'Concordance client liv et fact'!$A:$H,7,FALSE)+0,'Clients R2'!$A:$CY,22,FALSE)=4,"NA",VLOOKUP(VLOOKUP(LEFT('1) Import fichier Remi (coller)'!$A39,9),'Concordance client liv et fact'!$A:$H,7,FALSE)+0,'Clients R2'!$A:$CY,3,FALSE)))),2)) -> BE | X39: =IF($A39="","",IF(ISERROR(VLOOKUP(LEFT('1) Import fichier Remi (coller)'!$A39,9),'Concordance client liv et fact'!$A:$H,8,FALSE))=TRUE,VLOOKUP(LEFT('1) Import fichier Remi (coller)'!$A39,9)+0,'Clients R2'!$A:$CY,102,FALSE),VLOOKUP(VLOOKUP(LEFT('1) Import fichier Remi (coller)'!$A39,9),'Concordance client liv et fact'!$A:$H,7,FALSE)+0,'Clients R2'!$A:$CY,102,FALSE))) -> info@hofman-signalisation.be | Y39: CF11261601.PDF | Z39: =IF(A39="","",IF(OR(H39="705099999",H39="705001002"),VLOOKUP('1) Import fichier Remi (coller)'!J39,'Analytique personnel'!$A:$B,2,FALSE),"")) -> GDUHOUX | AA39: =IF($A39="VE11","",IF(LEFT($H39,4)="7050","",IF('1) Import fichier Remi (coller)'!M39="","",'1) Import fichier Remi (coller)'!M39))) | AB39: =IF($A39="VE11","",IF(LEFT($H39,4)="7050","",IF('1) Import fichier Remi (coller)'!N39="","",'1) Import fichier Remi (coller)'!N39))) | AC39: =IF(A39="","",VLOOKUP(LEFT('1) Import fichier Remi (coller)'!A39,9)+0,'Concordance Client R2 BOB'!$B:$C,2,FALSE)) -> HOFMAN
A40: =IF('1) Import fichier Remi (coller)'!D40="","",'1) Import fichier Remi (coller)'!D40) -> VE11 | B40: =IF(A40="","",YEAR('1) Import fichier Remi (coller)'!F40)) -> 2026 | C40: =IF(A40="","",MONTH('1) Import fichier Remi (coller)'!F40)) -> 9 | D40: =IF(A40="","",'1) Import fichier Remi (coller)'!F40) -> 46281 | E40: =IF(A40="","",'1) Import fichier Remi (coller)'!G40) -> 46281 | F40: =IF(A40="","",'1) Import fichier Remi (coller)'!E40) -> 11261530 | G40: =IF(A40="","",IF(ISERROR(VLOOKUP(LEFT('1) Import fichier Remi (coller)'!A40,9),'Concordance client liv et fact'!$A:$H,8,FALSE))=TRUE,'1) Import fichier Remi (coller)'!B40,VLOOKUP(LEFT('1) Import fichier Remi (coller)'!A40,9),'Concordance client liv et fact'!$A:$H,8,FALSE))) -> HOUBEN | H40: =IF(A40="","",IF(ISERROR(VLOOKUP('1) Import fichier Remi (coller)'!K40&" - "&'1) Import fichier Remi (coller)'!L40,'Spécifique comptes'!$A:$G,1,FALSE))=TRUE,'1) Import fichier Remi (coller)'!V40,VLOOKUP('1) Import fichier Remi (coller)'!K40&" - "&'1) Import fichier Remi (coller)'!L40,'Spécifique comptes'!$A:$G,IF(LEFT('2) BOB compta (completer-forcer'!F40,2)="11",4,IF(LEFT('2) BOB compta (completer-forcer'!F40,2)="12",5,IF(LEFT('2) BOB compta (completer-forcer'!F40,2)="13",6,IF(LEFT('2) BOB compta (completer-forcer'!F40,2)="15",7,"Erreur Compte")))),FALSE))) -> 705099999 | I40: =IF(A40="","",IF(H40="70100000",'1) Import fichier Remi (coller)'!J40,'1) Import fichier Remi (coller)'!U40)) -> +++003/7261/53047+++ | J40: =IF(A40="","",'1) Import fichier Remi (coller)'!U40) -> +++003/7261/53047+++ | K40: =IF(A40="","",SUMIFS(N:N,A:A,A40,F:F,F40)+SUMIFS(O:O,A:A,A40,F:F,F40)) -> 30.25 | L40: =IF(A40="","",IF(LEFT(T40,1)="B","V","PRT")) -> V | M40: =IF(A40="","",'1) Import fichier Remi (coller)'!S40) -> 21 | N40: =IF($A40="","",IF(OR($A40="NCV",$A40="NC15"),-'1) Import fichier Remi (coller)'!R40,'1) Import fichier Remi (coller)'!R40)) -> 25 | O40: =IF($A40="","",IF(OR($A40="NCV",$A40="NC15"),-'1) Import fichier Remi (coller)'!T40,'1) Import fichier Remi (coller)'!T40)) -> 5.25 | R40: =IF($A40="","",IF(ISERROR(VLOOKUP(LEFT('1) Import fichier Remi (coller)'!$A40,9),'Concordance client liv et fact'!$A:$H,8,FALSE))=TRUE,VLOOKUP(LEFT('1) Import fichier Remi (coller)'!$A40,9)+0,'Clients R2'!$A:$CY,2,FALSE),VLOOKUP(VLOOKUP(LEFT('1) Import fichier Remi (coller)'!$A40,9),'Concordance client liv et fact'!$A:$H,7,FALSE)+0,'Clients R2'!$A:$CY,2,FALSE))) -> HOUBEN | S40: =IF($A40="","",PROPER(IF(ISERROR(VLOOKUP(LEFT('1) Import fichier Remi (coller)'!$A40,9),'Concordance client liv et fact'!$A:$H,8,FALSE))=TRUE,VLOOKUP(LEFT('1) Import fichier Remi (coller)'!$A40,9)+0,'Clients R2'!$A:$CY,27,FALSE),VLOOKUP(VLOOKUP(LEFT('1) Import fichier Remi (coller)'!$A40,9),'Concordance client liv et fact'!$A:$H,7,FALSE)+0,'Clients R2'!$A:$CY,27,FALSE)))) -> Rue Vinave 32 | T40: =IF($A40="","",LEFT(UPPER(IF(ISERROR(VLOOKUP(LEFT('1) Import fichier Remi (coller)'!$A40,9),'Concordance client liv et fact'!$A:$H,8,FALSE))=TRUE,VLOOKUP(LEFT('1) Import fichier Remi (coller)'!$A40,9)+0,'Clients R2'!$A:$CY,28,FALSE),VLOOKUP(VLOOKUP(LEFT('1) Import fichier Remi (coller)'!$A40,9),'Concordance client liv et fact'!$A:$H,7,FALSE)+0,'Clients R2'!$A:$CY,28,FALSE))),2)&UPPER(IF(ISERROR(VLOOKUP(LEFT('1) Import fichier Remi (coller)'!$A40,9),'Concordance client liv et fact'!$A:$H,8,FALSE))=TRUE,VLOOKUP(LEFT('1) Import fichier Remi (coller)'!$A40,9)+0,'Clients R2'!$A:$CY,29,FALSE),VLOOKUP(VLOOKUP(LEFT('1) Import fichier Remi (coller)'!$A40,9),'Concordance client liv et fact'!$A:$H,7,FALSE)+0,'Clients R2'!$A:$CY,29,FALSE)))) -> B 4030 | U40: =IF($A40="","",PROPER(IF(ISERROR(VLOOKUP(LEFT('1) Import fichier Remi (coller)'!$A40,9),'Concordance client liv et fact'!$A:$H,8,FALSE))=TRUE,VLOOKUP(LEFT('1) Import fichier Remi (coller)'!$A40,9)+0,'Clients R2'!$A:$CY,30,FALSE),VLOOKUP(VLOOKUP(LEFT('1) Import fichier Remi (coller)'!$A40,9),'Concordance client liv et fact'!$A:$H,7,FALSE)+0,'Clients R2'!$A:$CY,30,FALSE)))) -> Grivegnee | V40: =IF($A40="","",LEFT(UPPER(IF(ISERROR(VLOOKUP(LEFT('1) Import fichier Remi (coller)'!$A40,9),'Concordance client liv et fact'!$A:$H,8,FALSE))=TRUE,IF(VLOOKUP(LEFT('1) Import fichier Remi (coller)'!$A40,9)+0,'Clients R2'!$A:$CY,22,FALSE)=4,"NA",VLOOKUP(LEFT('1) Import fichier Remi (coller)'!$A40,9)+0,'Clients R2'!$A:$CY,3,FALSE)),IF(VLOOKUP(VLOOKUP(LEFT('1) Import fichier Remi (coller)'!$A40,9),'Concordance client liv et fact'!$A:$H,7,FALSE)+0,'Clients R2'!$A:$CY,22,FALSE)=4,"NA",VLOOKUP(VLOOKUP(LEFT('1) Import fichier Remi (coller)'!$A40,9),'Concordance client liv et fact'!$A:$H,7,FALSE)+0,'Clients R2'!$A:$CY,3,FALSE)))),2)) -> BE | X40: =IF($A40="","",IF(ISERROR(VLOOKUP(LEFT('1) Import fichier Remi (coller)'!$A40,9),'Concordance client liv et fact'!$A:$H,8,FALSE))=TRUE,VLOOKUP(LEFT('1) Import fichier Remi (coller)'!$A40,9)+0,'Clients R2'!$A:$CY,102,FALSE),VLOOKUP(VLOOKUP(LEFT('1) Import fichier Remi (coller)'!$A40,9),'Concordance client liv et fact'!$A:$H,7,FALSE)+0,'Clients R2'!$A:$CY,102,FALSE))) -> marcel.houben@skynet.be | Y40: CF11261601.PDF | Z40: =IF(A40="","",IF(OR(H40="705099999",H40="705001002"),VLOOKUP('1) Import fichier Remi (coller)'!J40,'Analytique personnel'!$A:$B,2,FALSE),"")) -> BMELIN | AA40: =IF($A40="VE11","",IF(LEFT($H40,4)="7050","",IF('1) Import fichier Remi (coller)'!M40="","",'1) Import fichier Remi (coller)'!M40))) | AB40: =IF($A40="VE11","",IF(LEFT($H40,4)="7050","",IF('1) Import fichier Remi (coller)'!N40="","",'1) Import fichier Remi (coller)'!N40))) | AC40: =IF(A40="","",VLOOKUP(LEFT('1) Import fichier Remi (coller)'!A40,9)+0,'Concordance Client R2 BOB'!$B:$C,2,FALSE)) -> HOUBEN
